Workbook

Sheet Read me
A1: CASH-FLOW FORECAST — how to use this file
A3: JNN GLOBAL LTD, trading as ETABLIX. Company number 15405437.
A5: 1. Fill every shaded cell on the Assumptions sheet. They are the only cells you type into.
A6: 2. Fill the Basis column for every assumption. This is the column that matters. An assessor knows a forecast from a company with no trading history cannot be accurate — what they are testing is whether it is reasoned. A figure with a stated basis is evidence of thinking; the same figure with an empty basis is evidence of nothing.
A7: 3. Everything on the Monthly cash flow and Annual summary sheets is a formula. Do not type over a formula — change the assumption behind it.
A8: 4. Set the start month on the Assumptions sheet. Every month column is derived from it.
A10: What to be careful about
A12: • A forecast that shows the company never running short of cash is the one an assessor disbelieves first. If the model shows a trough, leave the trough in and say how it is funded. A stated, funded trough reads as competence; a flat line reads as a model that was adjusted until it looked comfortable.
A13: • Payment terms are the whole exercise. Revenue recognised in month 3 and collected in month 5 is a two-month hole that the profit figure does not show. That is what the debtor-days assumption is for, and it is the assumption to be pessimistic about.
A14: • Do not forecast more work than one person can deliver. Multiply the engagement count by the days each takes and check it against the working days available. The model does this for you on row 'Capacity check' — if it turns red, the forecast is claiming capacity the company does not have, and an assessor who spots that discounts everything else.
A15: • Do not put a figure in that you cannot defend in a meeting. You will be asked about exactly one number, and it will be the largest one.
A17: VAT and tax are modelled simply and are not tax advice. Have the accountant check the file before it is submitted.

Sheet Assumptions
A1: # | B1: Assumption | C1: Value | D1: Unit | E1: Basis — where this number comes from
B2: Period
A3: 1 | B3: First month of the forecast | D3: date
B4: Revenue — Model 01 Advisory
A5: 2 | B5: Engagements won per month, steady state | D5: number
A6: 3 | B6: Average engagement value | D6: £
A7: 4 | B7: Delivery days per engagement | D7: days
A8: 5 | B8: Months before steady state is reached | D8: months
B9: Revenue — Model 02 Management Integrator
A10: 6 | B10: Engagements running concurrently, steady state | D10: number
A11: 7 | B11: Monthly fee per engagement | D11: £
A12: 8 | B12: Delivery days per engagement per month | D12: days
A13: 9 | B13: Months before steady state is reached | D13: months
B14: Conversion — be pessimistic here
A15: 10 | B15: Qualified enquiries per month | D15: number
A16: 11 | B16: Proportion of enquiries that convert | D16: %
B17: Collection
A18: 12 | B18: Debtor days — invoice to cash | D18: days
A19: 13 | B19: Proportion written off | D19: %
B20: Cost base — monthly
A21: 14 | B21: Director's salary and drawings | D21: £/month
A22: 15 | B22: Other employment cost | D22: £/month
A23: 16 | B23: Insurance — PI, PL, EL, spread monthly | D23: £/month
A24: 17 | B24: Accountancy and payroll | D24: £/month
A25: 18 | B25: Software, hosting and telephony | D25: £/month
A26: 19 | B26: Travel and site attendance | D26: £/month
A27: 20 | B27: Marketing and business development | D27: £/month
A28: 21 | B28: Accreditation and membership, spread monthly | D28: £/month
A29: 22 | B29: Everything else | D29: £/month
A30: 23 | B30: Contingency on the cost base | D30: %
B31: Capacity — this is the honesty check
A32: 24 | B32: Working days available per month, all people | D32: days
B33: Tax and funding
A34: 25 | B34: VAT rate on sales | D34: %
A35: 26 | B35: Proportion of input VAT recoverable | D35: %
A36: 27 | B36: Corporation tax rate on profit | D36: %
A37: 28 | B37: Opening cash balance at month 1 | D37: £
A38: 29 | B38: Director's loan or equity injected at month 1 | D38: £
B40: Every shaded cell is yours to fill. Leave none of them, and leave no Basis empty — an assumption with no stated basis is the first thing an assessor discounts.

Sheet Monthly cash flow
A1: Month | B1: =EDATE(Assumptions!$C$3,0) | C1: =EDATE(Assumptions!$C$3,1) | D1: =EDATE(Assumptions!$C$3,2) | E1: =EDATE(Assumptions!$C$3,3) | F1: =EDATE(Assumptions!$C$3,4) | G1: =EDATE(Assumptions!$C$3,5) | H1: =EDATE(Assumptions!$C$3,6) | I1: =EDATE(Assumptions!$C$3,7) | J1: =EDATE(Assumptions!$C$3,8) | K1: =EDATE(Assumptions!$C$3,9) | L1: =EDATE(Assumptions!$C$3,10) | M1: =EDATE(Assumptions!$C$3,11) | N1: =EDATE(Assumptions!$C$3,12) | O1: =EDATE(Assumptions!$C$3,13) | P1: =EDATE(Assumptions!$C$3,14) | Q1: =EDATE(Assumptions!$C$3,15) | R1: =EDATE(Assumptions!$C$3,16) | S1: =EDATE(Assumptions!$C$3,17) | T1: =EDATE(Assumptions!$C$3,18) | U1: =EDATE(Assumptions!$C$3,19) | V1: =EDATE(Assumptions!$C$3,20) | W1: =EDATE(Assumptions!$C$3,21) | X1: =EDATE(Assumptions!$C$3,22) | Y1: =EDATE(Assumptions!$C$3,23) | Z1: =EDATE(Assumptions!$C$3,24) | AA1: =EDATE(Assumptions!$C$3,25) | AB1: =EDATE(Assumptions!$C$3,26) | AC1: =EDATE(Assumptions!$C$3,27) | AD1: =EDATE(Assumptions!$C$3,28) | AE1: =EDATE(Assumptions!$C$3,29) | AF1: =EDATE(Assumptions!$C$3,30) | AG1: =EDATE(Assumptions!$C$3,31) | AH1: =EDATE(Assumptions!$C$3,32) | AI1: =EDATE(Assumptions!$C$3,33) | AJ1: =EDATE(Assumptions!$C$3,34) | AK1: =EDATE(Assumptions!$C$3,35)
A2: REVENUE EARNED (accruals — not cash)
A3: Model 01 — advisory | B3: =Assumptions!$C$5*Assumptions!$C$6*MIN(1,(0+1)/MAX(1,Assumptions!$C$8)) | C3: =Assumptions!$C$5*Assumptions!$C$6*MIN(1,(1+1)/MAX(1,Assumptions!$C$8)) | D3: =Assumptions!$C$5*Assumptions!$C$6*MIN(1,(2+1)/MAX(1,Assumptions!$C$8)) | E3: =Assumptions!$C$5*Assumptions!$C$6*MIN(1,(3+1)/MAX(1,Assumptions!$C$8)) | F3: =Assumptions!$C$5*Assumptions!$C$6*MIN(1,(4+1)/MAX(1,Assumptions!$C$8)) | G3: =Assumptions!$C$5*Assumptions!$C$6*MIN(1,(5+1)/MAX(1,Assumptions!$C$8)) | H3: =Assumptions!$C$5*Assumptions!$C$6*MIN(1,(6+1)/MAX(1,Assumptions!$C$8)) | I3: =Assumptions!$C$5*Assumptions!$C$6*MIN(1,(7+1)/MAX(1,Assumptions!$C$8)) | J3: =Assumptions!$C$5*Assumptions!$C$6*MIN(1,(8+1)/MAX(1,Assumptions!$C$8)) | K3: =Assumptions!$C$5*Assumptions!$C$6*MIN(1,(9+1)/MAX(1,Assumptions!$C$8)) | L3: =Assumptions!$C$5*Assumptions!$C$6*MIN(1,(10+1)/MAX(1,Assumptions!$C$8)) | M3: =Assumptions!$C$5*Assumptions!$C$6*MIN(1,(11+1)/MAX(1,Assumptions!$C$8)) | N3: =Assumptions!$C$5*Assumptions!$C$6*MIN(1,(12+1)/MAX(1,Assumptions!$C$8)) | O3: =Assumptions!$C$5*Assumptions!$C$6*MIN(1,(13+1)/MAX(1,Assumptions!$C$8)) | P3: =Assumptions!$C$5*Assumptions!$C$6*MIN(1,(14+1)/MAX(1,Assumptions!$C$8)) | Q3: =Assumptions!$C$5*Assumptions!$C$6*MIN(1,(15+1)/MAX(1,Assumptions!$C$8)) | R3: =Assumptions!$C$5*Assumptions!$C$6*MIN(1,(16+1)/MAX(1,Assumptions!$C$8)) | S3: =Assumptions!$C$5*Assumptions!$C$6*MIN(1,(17+1)/MAX(1,Assumptions!$C$8)) | T3: =Assumptions!$C$5*Assumptions!$C$6*MIN(1,(18+1)/MAX(1,Assumptions!$C$8)) | U3: =Assumptions!$C$5*Assumptions!$C$6*MIN(1,(19+1)/MAX(1,Assumptions!$C$8)) | V3: =Assumptions!$C$5*Assumptions!$C$6*MIN(1,(20+1)/MAX(1,Assumptions!$C$8)) | W3: =Assumptions!$C$5*Assumptions!$C$6*MIN(1,(21+1)/MAX(1,Assumptions!$C$8)) | X3: =Assumptions!$C$5*Assumptions!$C$6*MIN(1,(22+1)/MAX(1,Assumptions!$C$8)) | Y3: =Assumptions!$C$5*Assumptions!$C$6*MIN(1,(23+1)/MAX(1,Assumptions!$C$8)) | Z3: =Assumptions!$C$5*Assumptions!$C$6*MIN(1,(24+1)/MAX(1,Assumptions!$C$8)) | AA3: =Assumptions!$C$5*Assumptions!$C$6*MIN(1,(25+1)/MAX(1,Assumptions!$C$8)) | AB3: =Assumptions!$C$5*Assumptions!$C$6*MIN(1,(26+1)/MAX(1,Assumptions!$C$8)) | AC3: =Assumptions!$C$5*Assumptions!$C$6*MIN(1,(27+1)/MAX(1,Assumptions!$C$8)) | AD3: =Assumptions!$C$5*Assumptions!$C$6*MIN(1,(28+1)/MAX(1,Assumptions!$C$8)) | AE3: =Assumptions!$C$5*Assumptions!$C$6*MIN(1,(29+1)/MAX(1,Assumptions!$C$8)) | AF3: =Assumptions!$C$5*Assumptions!$C$6*MIN(1,(30+1)/MAX(1,Assumptions!$C$8)) | AG3: =Assumptions!$C$5*Assumptions!$C$6*MIN(1,(31+1)/MAX(1,Assumptions!$C$8)) | AH3: =Assumptions!$C$5*Assumptions!$C$6*MIN(1,(32+1)/MAX(1,Assumptions!$C$8)) | AI3: =Assumptions!$C$5*Assumptions!$C$6*MIN(1,(33+1)/MAX(1,Assumptions!$C$8)) | AJ3: =Assumptions!$C$5*Assumptions!$C$6*MIN(1,(34+1)/MAX(1,Assumptions!$C$8)) | AK3: =Assumptions!$C$5*Assumptions!$C$6*MIN(1,(35+1)/MAX(1,Assumptions!$C$8))
A4: Model 02 — management integrator | B4: =Assumptions!$C$10*Assumptions!$C$11*MIN(1,(0+1)/MAX(1,Assumptions!$C$13)) | C4: =Assumptions!$C$10*Assumptions!$C$11*MIN(1,(1+1)/MAX(1,Assumptions!$C$13)) | D4: =Assumptions!$C$10*Assumptions!$C$11*MIN(1,(2+1)/MAX(1,Assumptions!$C$13)) | E4: =Assumptions!$C$10*Assumptions!$C$11*MIN(1,(3+1)/MAX(1,Assumptions!$C$13)) | F4: =Assumptions!$C$10*Assumptions!$C$11*MIN(1,(4+1)/MAX(1,Assumptions!$C$13)) | G4: =Assumptions!$C$10*Assumptions!$C$11*MIN(1,(5+1)/MAX(1,Assumptions!$C$13)) | H4: =Assumptions!$C$10*Assumptions!$C$11*MIN(1,(6+1)/MAX(1,Assumptions!$C$13)) | I4: =Assumptions!$C$10*Assumptions!$C$11*MIN(1,(7+1)/MAX(1,Assumptions!$C$13)) | J4: =Assumptions!$C$10*Assumptions!$C$11*MIN(1,(8+1)/MAX(1,Assumptions!$C$13)) | K4: =Assumptions!$C$10*Assumptions!$C$11*MIN(1,(9+1)/MAX(1,Assumptions!$C$13)) | L4: =Assumptions!$C$10*Assumptions!$C$11*MIN(1,(10+1)/MAX(1,Assumptions!$C$13)) | M4: =Assumptions!$C$10*Assumptions!$C$11*MIN(1,(11+1)/MAX(1,Assumptions!$C$13)) | N4: =Assumptions!$C$10*Assumptions!$C$11*MIN(1,(12+1)/MAX(1,Assumptions!$C$13)) | O4: =Assumptions!$C$10*Assumptions!$C$11*MIN(1,(13+1)/MAX(1,Assumptions!$C$13)) | P4: =Assumptions!$C$10*Assumptions!$C$11*MIN(1,(14+1)/MAX(1,Assumptions!$C$13)) | Q4: =Assumptions!$C$10*Assumptions!$C$11*MIN(1,(15+1)/MAX(1,Assumptions!$C$13)) | R4: =Assumptions!$C$10*Assumptions!$C$11*MIN(1,(16+1)/MAX(1,Assumptions!$C$13)) | S4: =Assumptions!$C$10*Assumptions!$C$11*MIN(1,(17+1)/MAX(1,Assumptions!$C$13)) | T4: =Assumptions!$C$10*Assumptions!$C$11*MIN(1,(18+1)/MAX(1,Assumptions!$C$13)) | U4: =Assumptions!$C$10*Assumptions!$C$11*MIN(1,(19+1)/MAX(1,Assumptions!$C$13)) | V4: =Assumptions!$C$10*Assumptions!$C$11*MIN(1,(20+1)/MAX(1,Assumptions!$C$13)) | W4: =Assumptions!$C$10*Assumptions!$C$11*MIN(1,(21+1)/MAX(1,Assumptions!$C$13)) | X4: =Assumptions!$C$10*Assumptions!$C$11*MIN(1,(22+1)/MAX(1,Assumptions!$C$13)) | Y4: =Assumptions!$C$10*Assumptions!$C$11*MIN(1,(23+1)/MAX(1,Assumptions!$C$13)) | Z4: =Assumptions!$C$10*Assumptions!$C$11*MIN(1,(24+1)/MAX(1,Assumptions!$C$13)) | AA4: =Assumptions!$C$10*Assumptions!$C$11*MIN(1,(25+1)/MAX(1,Assumptions!$C$13)) | AB4: =Assumptions!$C$10*Assumptions!$C$11*MIN(1,(26+1)/MAX(1,Assumptions!$C$13)) | AC4: =Assumptions!$C$10*Assumptions!$C$11*MIN(1,(27+1)/MAX(1,Assumptions!$C$13)) | AD4: =Assumptions!$C$10*Assumptions!$C$11*MIN(1,(28+1)/MAX(1,Assumptions!$C$13)) | AE4: =Assumptions!$C$10*Assumptions!$C$11*MIN(1,(29+1)/MAX(1,Assumptions!$C$13)) | AF4: =Assumptions!$C$10*Assumptions!$C$11*MIN(1,(30+1)/MAX(1,Assumptions!$C$13)) | AG4: =Assumptions!$C$10*Assumptions!$C$11*MIN(1,(31+1)/MAX(1,Assumptions!$C$13)) | AH4: =Assumptions!$C$10*Assumptions!$C$11*MIN(1,(32+1)/MAX(1,Assumptions!$C$13)) | AI4: =Assumptions!$C$10*Assumptions!$C$11*MIN(1,(33+1)/MAX(1,Assumptions!$C$13)) | AJ4: =Assumptions!$C$10*Assumptions!$C$11*MIN(1,(34+1)/MAX(1,Assumptions!$C$13)) | AK4: =Assumptions!$C$10*Assumptions!$C$11*MIN(1,(35+1)/MAX(1,Assumptions!$C$13))
A5: Revenue earned | B5: =SUM(B3:B4) | C5: =SUM(C3:C4) | D5: =SUM(D3:D4) | E5: =SUM(E3:E4) | F5: =SUM(F3:F4) | G5: =SUM(G3:G4) | H5: =SUM(H3:H4) | I5: =SUM(I3:I4) | ... AK5: =SUM(AK3:AK4)
A7: CAPACITY CHECK — does the company have the days to deliver this?
A8: Delivery days the forecast requires | B8: =Assumptions!$C$5*Assumptions!$C$7*MIN(1,(0+1)/MAX(1,Assumptions!$C$8))+Assumptions!$C$10*Assumptions!$C$12*MIN(1,(0+1)/MAX(1,Assumptions!$C$13)) | C8: =Assumptions!$C$5*Assumptions!$C$7*MIN(1,(1+1)/MAX(1,Assumptions!$C$8))+Assumptions!$C$10*Assumptions!$C$12*MIN(1,(1+1)/MAX(1,Assumptions!$C$13)) | D8: =Assumptions!$C$5*Assumptions!$C$7*MIN(1,(2+1)/MAX(1,Assumptions!$C$8))+Assumptions!$C$10*Assumptions!$C$12*MIN(1,(2+1)/MAX(1,Assumptions!$C$13)) | E8: =Assumptions!$C$5*Assumptions!$C$7*MIN(1,(3+1)/MAX(1,Assumptions!$C$8))+Assumptions!$C$10*Assumptions!$C$12*MIN(1,(3+1)/MAX(1,Assumptions!$C$13)) | F8: =Assumptions!$C$5*Assumptions!$C$7*MIN(1,(4+1)/MAX(1,Assumptions!$C$8))+Assumptions!$C$10*Assumptions!$C$12*MIN(1,(4+1)/MAX(1,Assumptions!$C$13)) | G8: =Assumptions!$C$5*Assumptions!$C$7*MIN(1,(5+1)/MAX(1,Assumptions!$C$8))+Assumptions!$C$10*Assumptions!$C$12*MIN(1,(5+1)/MAX(1,Assumptions!$C$13)) | H8: =Assumptions!$C$5*Assumptions!$C$7*MIN(1,(6+1)/MAX(1,Assumptions!$C$8))+Assumptions!$C$10*Assumptions!$C$12*MIN(1,(6+1)/MAX(1,Assumptions!$C$13)) | I8: =Assumptions!$C$5*Assumptions!$C$7*MIN(1,(7+1)/MAX(1,Assumptions!$C$8))+Assumptions!$C$10*Assumptions!$C$12*MIN(1,(7+1)/MAX(1,Assumptions!$C$13)) | J8: =Assumptions!$C$5*Assumptions!$C$7*MIN(1,(8+1)/MAX(1,Assumptions!$C$8))+Assumptions!$C$10*Assumptions!$C$12*MIN(1,(8+1)/MAX(1,Assumptions!$C$13)) | K8: =Assumptions!$C$5*Assumptions!$C$7*MIN(1,(9+1)/MAX(1,Assumptions!$C$8))+Assumptions!$C$10*Assumptions!$C$12*MIN(1,(9+1)/MAX(1,Assumptions!$C$13)) | L8: =Assumptions!$C$5*Assumptions!$C$7*MIN(1,(10+1)/MAX(1,Assumptions!$C$8))+Assumptions!$C$10*Assumptions!$C$12*MIN(1,(10+1)/MAX(1,Assumptions!$C$13)) | M8: =Assumptions!$C$5*Assumptions!$C$7*MIN(1,(11+1)/MAX(1,Assumptions!$C$8))+Assumptions!$C$10*Assumptions!$C$12*MIN(1,(11+1)/MAX(1,Assumptions!$C$13)) | N8: =Assumptions!$C$5*Assumptions!$C$7*MIN(1,(12+1)/MAX(1,Assumptions!$C$8))+Assumptions!$C$10*Assumptions!$C$12*MIN(1,(12+1)/MAX(1,Assumptions!$C$13)) | O8: =Assumptions!$C$5*Assumptions!$C$7*MIN(1,(13+1)/MAX(1,Assumptions!$C$8))+Assumptions!$C$10*Assumptions!$C$12*MIN(1,(13+1)/MAX(1,Assumptions!$C$13)) | P8: =Assumptions!$C$5*Assumptions!$C$7*MIN(1,(14+1)/MAX(1,Assumptions!$C$8))+Assumptions!$C$10*Assumptions!$C$12*MIN(1,(14+1)/MAX(1,Assumptions!$C$13)) | Q8: =Assumptions!$C$5*Assumptions!$C$7*MIN(1,(15+1)/MAX(1,Assumptions!$C$8))+Assumptions!$C$10*Assumptions!$C$12*MIN(1,(15+1)/MAX(1,Assumptions!$C$13)) | R8: =Assumptions!$C$5*Assumptions!$C$7*MIN(1,(16+1)/MAX(1,Assumptions!$C$8))+Assumptions!$C$10*Assumptions!$C$12*MIN(1,(16+1)/MAX(1,Assumptions!$C$13)) | S8: =Assumptions!$C$5*Assumptions!$C$7*MIN(1,(17+1)/MAX(1,Assumptions!$C$8))+Assumptions!$C$10*Assumptions!$C$12*MIN(1,(17+1)/MAX(1,Assumptions!$C$13)) | T8: =Assumptions!$C$5*Assumptions!$C$7*MIN(1,(18+1)/MAX(1,Assumptions!$C$8))+Assumptions!$C$10*Assumptions!$C$12*MIN(1,(18+1)/MAX(1,Assumptions!$C$13)) | U8: =Assumptions!$C$5*Assumptions!$C$7*MIN(1,(19+1)/MAX(1,Assumptions!$C$8))+Assumptions!$C$10*Assumptions!$C$12*MIN(1,(19+1)/MAX(1,Assumptions!$C$13)) | V8: =Assumptions!$C$5*Assumptions!$C$7*MIN(1,(20+1)/MAX(1,Assumptions!$C$8))+Assumptions!$C$10*Assumptions!$C$12*MIN(1,(20+1)/MAX(1,Assumptions!$C$13)) | W8: =Assumptions!$C$5*Assumptions!$C$7*MIN(1,(21+1)/MAX(1,Assumptions!$C$8))+Assumptions!$C$10*Assumptions!$C$12*MIN(1,(21+1)/MAX(1,Assumptions!$C$13)) | X8: =Assumptions!$C$5*Assumptions!$C$7*MIN(1,(22+1)/MAX(1,Assumptions!$C$8))+Assumptions!$C$10*Assumptions!$C$12*MIN(1,(22+1)/MAX(1,Assumptions!$C$13)) | Y8: =Assumptions!$C$5*Assumptions!$C$7*MIN(1,(23+1)/MAX(1,Assumptions!$C$8))+Assumptions!$C$10*Assumptions!$C$12*MIN(1,(23+1)/MAX(1,Assumptions!$C$13)) | Z8: =Assumptions!$C$5*Assumptions!$C$7*MIN(1,(24+1)/MAX(1,Assumptions!$C$8))+Assumptions!$C$10*Assumptions!$C$12*MIN(1,(24+1)/MAX(1,Assumptions!$C$13)) | AA8: =Assumptions!$C$5*Assumptions!$C$7*MIN(1,(25+1)/MAX(1,Assumptions!$C$8))+Assumptions!$C$10*Assumptions!$C$12*MIN(1,(25+1)/MAX(1,Assumptions!$C$13)) | AB8: =Assumptions!$C$5*Assumptions!$C$7*MIN(1,(26+1)/MAX(1,Assumptions!$C$8))+Assumptions!$C$10*Assumptions!$C$12*MIN(1,(26+1)/MAX(1,Assumptions!$C$13)) | AC8: =Assumptions!$C$5*Assumptions!$C$7*MIN(1,(27+1)/MAX(1,Assumptions!$C$8))+Assumptions!$C$10*Assumptions!$C$12*MIN(1,(27+1)/MAX(1,Assumptions!$C$13)) | AD8: =Assumptions!$C$5*Assumptions!$C$7*MIN(1,(28+1)/MAX(1,Assumptions!$C$8))+Assumptions!$C$10*Assumptions!$C$12*MIN(1,(28+1)/MAX(1,Assumptions!$C$13)) | AE8: =Assumptions!$C$5*Assumptions!$C$7*MIN(1,(29+1)/MAX(1,Assumptions!$C$8))+Assumptions!$C$10*Assumptions!$C$12*MIN(1,(29+1)/MAX(1,Assumptions!$C$13)) | AF8: =Assumptions!$C$5*Assumptions!$C$7*MIN(1,(30+1)/MAX(1,Assumptions!$C$8))+Assumptions!$C$10*Assumptions!$C$12*MIN(1,(30+1)/MAX(1,Assumptions!$C$13)) | AG8: =Assumptions!$C$5*Assumptions!$C$7*MIN(1,(31+1)/MAX(1,Assumptions!$C$8))+Assumptions!$C$10*Assumptions!$C$12*MIN(1,(31+1)/MAX(1,Assumptions!$C$13)) | AH8: =Assumptions!$C$5*Assumptions!$C$7*MIN(1,(32+1)/MAX(1,Assumptions!$C$8))+Assumptions!$C$10*Assumptions!$C$12*MIN(1,(32+1)/MAX(1,Assumptions!$C$13)) | AI8: =Assumptions!$C$5*Assumptions!$C$7*MIN(1,(33+1)/MAX(1,Assumptions!$C$8))+Assumptions!$C$10*Assumptions!$C$12*MIN(1,(33+1)/MAX(1,Assumptions!$C$13)) | AJ8: =Assumptions!$C$5*Assumptions!$C$7*MIN(1,(34+1)/MAX(1,Assumptions!$C$8))+Assumptions!$C$10*Assumptions!$C$12*MIN(1,(34+1)/MAX(1,Assumptions!$C$13)) | AK8: =Assumptions!$C$5*Assumptions!$C$7*MIN(1,(35+1)/MAX(1,Assumptions!$C$8))+Assumptions!$C$10*Assumptions!$C$12*MIN(1,(35+1)/MAX(1,Assumptions!$C$13))
A9: Delivery days available | B9: =Assumptions!$C$32 | C9: =Assumptions!$C$32 | D9: =Assumptions!$C$32 | E9: =Assumptions!$C$32 | F9: =Assumptions!$C$32 | G9: =Assumptions!$C$32 | H9: =Assumptions!$C$32 | I9: =Assumptions!$C$32 | ... AK9: =Assumptions!$C$32
A10: Capacity check | B10: =IF(B8>B9,"OVER","ok") | C10: =IF(C8>C9,"OVER","ok") | D10: =IF(D8>D9,"OVER","ok") | E10: =IF(E8>E9,"OVER","ok") | F10: =IF(F8>F9,"OVER","ok") | G10: =IF(G8>G9,"OVER","ok") | H10: =IF(H8>H9,"OVER","ok") | I10: =IF(I8>I9,"OVER","ok") | ... AK10: =IF(AK8>AK9,"OVER","ok")
A12: CASH IN
A13: Revenue collected | B13: =IFERROR(INDEX($B5:$AK5,1,1-ROUND(Assumptions!$C$18/30,0))*(1-Assumptions!$C$19),0) | C13: =IFERROR(INDEX($B5:$AK5,1,2-ROUND(Assumptions!$C$18/30,0))*(1-Assumptions!$C$19),0) | D13: =IFERROR(INDEX($B5:$AK5,1,3-ROUND(Assumptions!$C$18/30,0))*(1-Assumptions!$C$19),0) | E13: =IFERROR(INDEX($B5:$AK5,1,4-ROUND(Assumptions!$C$18/30,0))*(1-Assumptions!$C$19),0) | F13: =IFERROR(INDEX($B5:$AK5,1,5-ROUND(Assumptions!$C$18/30,0))*(1-Assumptions!$C$19),0) | G13: =IFERROR(INDEX($B5:$AK5,1,6-ROUND(Assumptions!$C$18/30,0))*(1-Assumptions!$C$19),0) | H13: =IFERROR(INDEX($B5:$AK5,1,7-ROUND(Assumptions!$C$18/30,0))*(1-Assumptions!$C$19),0) | I13: =IFERROR(INDEX($B5:$AK5,1,8-ROUND(Assumptions!$C$18/30,0))*(1-Assumptions!$C$19),0) | J13: =IFERROR(INDEX($B5:$AK5,1,9-ROUND(Assumptions!$C$18/30,0))*(1-Assumptions!$C$19),0) | K13: =IFERROR(INDEX($B5:$AK5,1,10-ROUND(Assumptions!$C$18/30,0))*(1-Assumptions!$C$19),0) | L13: =IFERROR(INDEX($B5:$AK5,1,11-ROUND(Assumptions!$C$18/30,0))*(1-Assumptions!$C$19),0) | M13: =IFERROR(INDEX($B5:$AK5,1,12-ROUND(Assumptions!$C$18/30,0))*(1-Assumptions!$C$19),0) | N13: =IFERROR(INDEX($B5:$AK5,1,13-ROUND(Assumptions!$C$18/30,0))*(1-Assumptions!$C$19),0) | O13: =IFERROR(INDEX($B5:$AK5,1,14-ROUND(Assumptions!$C$18/30,0))*(1-Assumptions!$C$19),0) | P13: =IFERROR(INDEX($B5:$AK5,1,15-ROUND(Assumptions!$C$18/30,0))*(1-Assumptions!$C$19),0) | Q13: =IFERROR(INDEX($B5:$AK5,1,16-ROUND(Assumptions!$C$18/30,0))*(1-Assumptions!$C$19),0) | R13: =IFERROR(INDEX($B5:$AK5,1,17-ROUND(Assumptions!$C$18/30,0))*(1-Assumptions!$C$19),0) | S13: =IFERROR(INDEX($B5:$AK5,1,18-ROUND(Assumptions!$C$18/30,0))*(1-Assumptions!$C$19),0) | T13: =IFERROR(INDEX($B5:$AK5,1,19-ROUND(Assumptions!$C$18/30,0))*(1-Assumptions!$C$19),0) | U13: =IFERROR(INDEX($B5:$AK5,1,20-ROUND(Assumptions!$C$18/30,0))*(1-Assumptions!$C$19),0) | V13: =IFERROR(INDEX($B5:$AK5,1,21-ROUND(Assumptions!$C$18/30,0))*(1-Assumptions!$C$19),0) | W13: =IFERROR(INDEX($B5:$AK5,1,22-ROUND(Assumptions!$C$18/30,0))*(1-Assumptions!$C$19),0) | X13: =IFERROR(INDEX($B5:$AK5,1,23-ROUND(Assumptions!$C$18/30,0))*(1-Assumptions!$C$19),0) | Y13: =IFERROR(INDEX($B5:$AK5,1,24-ROUND(Assumptions!$C$18/30,0))*(1-Assumptions!$C$19),0) | Z13: =IFERROR(INDEX($B5:$AK5,1,25-ROUND(Assumptions!$C$18/30,0))*(1-Assumptions!$C$19),0) | AA13: =IFERROR(INDEX($B5:$AK5,1,26-ROUND(Assumptions!$C$18/30,0))*(1-Assumptions!$C$19),0) | AB13: =IFERROR(INDEX($B5:$AK5,1,27-ROUND(Assumptions!$C$18/30,0))*(1-Assumptions!$C$19),0) | AC13: =IFERROR(INDEX($B5:$AK5,1,28-ROUND(Assumptions!$C$18/30,0))*(1-Assumptions!$C$19),0) | AD13: =IFERROR(INDEX($B5:$AK5,1,29-ROUND(Assumptions!$C$18/30,0))*(1-Assumptions!$C$19),0) | AE13: =IFERROR(INDEX($B5:$AK5,1,30-ROUND(Assumptions!$C$18/30,0))*(1-Assumptions!$C$19),0) | AF13: =IFERROR(INDEX($B5:$AK5,1,31-ROUND(Assumptions!$C$18/30,0))*(1-Assumptions!$C$19),0) | AG13: =IFERROR(INDEX($B5:$AK5,1,32-ROUND(Assumptions!$C$18/30,0))*(1-Assumptions!$C$19),0) | AH13: =IFERROR(INDEX($B5:$AK5,1,33-ROUND(Assumptions!$C$18/30,0))*(1-Assumptions!$C$19),0) | AI13: =IFERROR(INDEX($B5:$AK5,1,34-ROUND(Assumptions!$C$18/30,0))*(1-Assumptions!$C$19),0) | AJ13: =IFERROR(INDEX($B5:$AK5,1,35-ROUND(Assumptions!$C$18/30,0))*(1-Assumptions!$C$19),0) | AK13: =IFERROR(INDEX($B5:$AK5,1,36-ROUND(Assumptions!$C$18/30,0))*(1-Assumptions!$C$19),0)
A14: VAT collected on those receipts | B14: =B13*Assumptions!$C$34 | C14: =C13*Assumptions!$C$34 | D14: =D13*Assumptions!$C$34 | E14: =E13*Assumptions!$C$34 | F14: =F13*Assumptions!$C$34 | G14: =G13*Assumptions!$C$34 | H14: =H13*Assumptions!$C$34 | I14: =I13*Assumptions!$C$34 | ... AK14: =AK13*Assumptions!$C$34
A15: Director's loan / equity injected | B15: =Assumptions!$C$38 | C15: =0 | D15: =0 | E15: =0 | F15: =0 | G15: =0 | H15: =0 | I15: =0 | J15: =0 | ... AK15: =0
A16: Total cash in | B16: =B13+B14+B15 | C16: =C13+C14+C15 | D16: =D13+D14+D15 | E16: =E13+E14+E15 | F16: =F13+F14+F15 | G16: =G13+G14+G15 | H16: =H13+H14+H15 | I16: =I13+I14+I15 | ... AK16: =AK13+AK14+AK15
A18: CASH OUT
A19: Director's salary and drawings | B19: =Assumptions!$C$21 | C19: =Assumptions!$C$21 | D19: =Assumptions!$C$21 | E19: =Assumptions!$C$21 | F19: =Assumptions!$C$21 | G19: =Assumptions!$C$21 | H19: =Assumptions!$C$21 | I19: =Assumptions!$C$21 | ... AK19: =Assumptions!$C$21
A20: Other employment cost | B20: =Assumptions!$C$22 | C20: =Assumptions!$C$22 | D20: =Assumptions!$C$22 | E20: =Assumptions!$C$22 | F20: =Assumptions!$C$22 | G20: =Assumptions!$C$22 | H20: =Assumptions!$C$22 | I20: =Assumptions!$C$22 | ... AK20: =Assumptions!$C$22
A21: Insurance | B21: =Assumptions!$C$23 | C21: =Assumptions!$C$23 | D21: =Assumptions!$C$23 | E21: =Assumptions!$C$23 | F21: =Assumptions!$C$23 | G21: =Assumptions!$C$23 | H21: =Assumptions!$C$23 | I21: =Assumptions!$C$23 | ... AK21: =Assumptions!$C$23
A22: Accountancy and payroll | B22: =Assumptions!$C$24 | C22: =Assumptions!$C$24 | D22: =Assumptions!$C$24 | E22: =Assumptions!$C$24 | F22: =Assumptions!$C$24 | G22: =Assumptions!$C$24 | H22: =Assumptions!$C$24 | I22: =Assumptions!$C$24 | ... AK22: =Assumptions!$C$24
A23: Software, hosting and telephony | B23: =Assumptions!$C$25 | C23: =Assumptions!$C$25 | D23: =Assumptions!$C$25 | E23: =Assumptions!$C$25 | F23: =Assumptions!$C$25 | G23: =Assumptions!$C$25 | H23: =Assumptions!$C$25 | I23: =Assumptions!$C$25 | ... AK23: =Assumptions!$C$25
A24: Travel and site attendance | B24: =Assumptions!$C$26 | C24: =Assumptions!$C$26 | D24: =Assumptions!$C$26 | E24: =Assumptions!$C$26 | F24: =Assumptions!$C$26 | G24: =Assumptions!$C$26 | H24: =Assumptions!$C$26 | I24: =Assumptions!$C$26 | ... AK24: =Assumptions!$C$26
A25: Marketing and business development | B25: =Assumptions!$C$27 | C25: =Assumptions!$C$27 | D25: =Assumptions!$C$27 | E25: =Assumptions!$C$27 | F25: =Assumptions!$C$27 | G25: =Assumptions!$C$27 | H25: =Assumptions!$C$27 | I25: =Assumptions!$C$27 | ... AK25: =Assumptions!$C$27
A26: Accreditation and membership | B26: =Assumptions!$C$28 | C26: =Assumptions!$C$28 | D26: =Assumptions!$C$28 | E26: =Assumptions!$C$28 | F26: =Assumptions!$C$28 | G26: =Assumptions!$C$28 | H26: =Assumptions!$C$28 | I26: =Assumptions!$C$28 | ... AK26: =Assumptions!$C$28
A27: Everything else | B27: =Assumptions!$C$29 | C27: =Assumptions!$C$29 | D27: =Assumptions!$C$29 | E27: =Assumptions!$C$29 | F27: =Assumptions!$C$29 | G27: =Assumptions!$C$29 | H27: =Assumptions!$C$29 | I27: =Assumptions!$C$29 | ... AK27: =Assumptions!$C$29
A28: Contingency | B28: =SUM(B19:B27)*Assumptions!$C$30 | C28: =SUM(C19:C27)*Assumptions!$C$30 | D28: =SUM(D19:D27)*Assumptions!$C$30 | E28: =SUM(E19:E27)*Assumptions!$C$30 | F28: =SUM(F19:F27)*Assumptions!$C$30 | G28: =SUM(G19:G27)*Assumptions!$C$30 | H28: =SUM(H19:H27)*Assumptions!$C$30 | I28: =SUM(I19:I27)*Assumptions!$C$30 | ... AK28: =SUM(AK19:AK27)*Assumptions!$C$30
A29: Operating cost | B29: =SUM(B19:B28) | C29: =SUM(C19:C28) | D29: =SUM(D19:D28) | E29: =SUM(E19:E28) | F29: =SUM(F19:F28) | G29: =SUM(G19:G28) | H29: =SUM(H19:H28) | I29: =SUM(I19:I28) | ... AK29: =SUM(AK19:AK28)
A30: VAT paid on costs | B30: =B29*Assumptions!$C$34*Assumptions!$C$35 | C30: =C29*Assumptions!$C$34*Assumptions!$C$35 | D30: =D29*Assumptions!$C$34*Assumptions!$C$35 | E30: =E29*Assumptions!$C$34*Assumptions!$C$35 | F30: =F29*Assumptions!$C$34*Assumptions!$C$35 | G30: =G29*Assumptions!$C$34*Assumptions!$C$35 | H30: =H29*Assumptions!$C$34*Assumptions!$C$35 | I30: =I29*Assumptions!$C$34*Assumptions!$C$35 | ... AK30: =AK29*Assumptions!$C$34*Assumptions!$C$35
A31: VAT paid over to HMRC (quarterly) | B31: =0 | C31: =0 | D31: =SUM(B14,C14,D14)-SUM(B30,C30,D30) | E31: =0 | F31: =0 | G31: =SUM(E14,F14,G14)-SUM(E30,F30,G30) | H31: =0 | I31: =0 | J31: =SUM(H14,I14,J14)-SUM(H30,I30,J30) | K31: =0 | L31: =0 | M31: =SUM(K14,L14,M14)-SUM(K30,L30,M30) | N31: =0 | O31: =0 | P31: =SUM(N14,O14,P14)-SUM(N30,O30,P30) | Q31: =0 | R31: =0 | S31: =SUM(Q14,R14,S14)-SUM(Q30,R30,S30) | T31: =0 | U31: =0 | V31: =SUM(T14,U14,V14)-SUM(T30,U30,V30) | W31: =0 | X31: =0 | Y31: =SUM(W14,X14,Y14)-SUM(W30,X30,Y30) | Z31: =0 | AA31: =0 | AB31: =SUM(Z14,AA14,AB14)-SUM(Z30,AA30,AB30) | AC31: =0 | AD31: =0 | AE31: =SUM(AC14,AD14,AE14)-SUM(AC30,AD30,AE30) | AF31: =0 | AG31: =0 | AH31: =SUM(AF14,AG14,AH14)-SUM(AF30,AG30,AH30) | AI31: =0 | AJ31: =0 | AK31: =SUM(AI14,AJ14,AK14)-SUM(AI30,AJ30,AK30)
A32: Corporation tax paid | B32: =0 | C32: =0 | D32: =0 | E32: =0 | F32: =0 | G32: =0 | H32: =0 | I32: =0 | ... V32: =0 | W32: =MAX(0,SUM(B5:M5)-SUM(B29:M29))*Assumptions!$C$36 | X32: =0 | Y32: =0 | Z32: =0 | AA32: =0 | AB32: =0 | AC32: =0 | AD32: =0 | AE32: =0 | ... AH32: =0 | AI32: =MAX(0,SUM(N5:Y5)-SUM(N29:Y29))*Assumptions!$C$36 | AJ32: =0 | AK32: =0
A33: Total cash out | B33: =B29+B30+B31+B32 | C33: =C29+C30+C31+C32 | D33: =D29+D30+D31+D32 | E33: =E29+E30+E31+E32 | F33: =F29+F30+F31+F32 | G33: =G29+G30+G31+G32 | H33: =H29+H30+H31+H32 | I33: =I29+I30+I31+I32 | ... AK33: =AK29+AK30+AK31+AK32
A35: CASH POSITION
A36: Opening balance | B36: =Assumptions!$C$37 | C36: =B38 | D36: =C38 | E36: =D38 | F36: =E38 | G36: =F38 | H36: =G38 | I36: =H38 | J36: =I38 | ... AK36: =AJ38
A37: Net movement | B37: =B16-B33 | C37: =C16-C33 | D37: =D16-D33 | E37: =E16-E33 | F37: =F16-F33 | G37: =G16-G33 | H37: =H16-H33 | I37: =I16-I33 | ... AK37: =AK16-AK33
A38: Closing balance | B38: =B36+B37 | C38: =C36+C37 | D38: =D36+D37 | E38: =E36+E37 | F38: =F36+F37 | G38: =G36+G37 | H38: =H36+H37 | I38: =I36+I37 | ... AK38: =AK36+AK37
A39: Lowest point reached to date | B39: =MIN($B38:B38) | C39: =MIN($B38:C38) | D39: =MIN($B38:D38) | E39: =MIN($B38:E38) | F39: =MIN($B38:F38) | G39: =MIN($B38:G38) | H39: =MIN($B38:H38) | I39: =MIN($B38:I38) | ... AK39: =MIN($B38:AK38)

Sheet Annual summary
B1: Year 1 | C1: Year 2 | D1: Year 3
A2: Revenue earned | B2: =SUM('Monthly cash flow'!B5:'Monthly cash flow'!M5) | C2: =SUM('Monthly cash flow'!N5:'Monthly cash flow'!Y5) | D2: =SUM('Monthly cash flow'!Z5:'Monthly cash flow'!AK5)
A3: Operating cost | B3: =SUM('Monthly cash flow'!B29:'Monthly cash flow'!M29) | C3: =SUM('Monthly cash flow'!N29:'Monthly cash flow'!Y29) | D3: =SUM('Monthly cash flow'!Z29:'Monthly cash flow'!AK29)
A4: Profit before tax | B4: =B2-B3 | C4: =C2-C3 | D4: =D2-D3
A6: Cash collected | B6: =SUM('Monthly cash flow'!B13:'Monthly cash flow'!M13) | C6: =SUM('Monthly cash flow'!N13:'Monthly cash flow'!Y13) | D6: =SUM('Monthly cash flow'!Z13:'Monthly cash flow'!AK13)
A7: Closing cash at year end | B7: ='Monthly cash flow'!M38 | C7: ='Monthly cash flow'!Y38 | D7: ='Monthly cash flow'!AK38
A8: Lowest cash position in the year | B8: =MIN('Monthly cash flow'!B38:'Monthly cash flow'!M38) | C8: =MIN('Monthly cash flow'!N38:'Monthly cash flow'!Y38) | D8: =MIN('Monthly cash flow'!Z38:'Monthly cash flow'!AK38)
A10: The lowest cash position is the number an assessor looks for. If it is negative, say in the narrative how it is funded — a stated, funded trough reads as competence. A model with no trough at all reads as a model that was adjusted until it looked comfortable.
