Workbook

Sheet ReadMe
A1: ETABLIX — Five-to-One Consolidation Decision and Cost Model
A2: Companion to ETX-PB-01. Built 08 September 2026. Yellow cells are inputs; everything else is computed.
A4: WHAT THIS ANSWERS
A5: The playbook says consolidate a load problem and not a performance problem, and it says expect a 17–21 per cent wrap.
A6: It cannot say whether the wrap is worth it on YOUR job, because that depends on four sums, a management cost and a
A7: liquidated damages position that are different every time. This model says.
A9: THE SHEETS
A10: Inputs The four transferred sums, the prime's own package, the stack percentages, the client's own management
A11: cost, and the liquidated damages position. Everything else reads from here.
A12: DecisionTest The eight questions at playbook clause 5.3, scored 0/1/2. The verdict is computed, not typed.
A13: LoadModel What the client actually carries with five packages: interfaces, statutory notice deadlines, valuations,
A14: and the management hours behind them, costed. This is the number the wrap is compared against.
... A29: own re-implementation fails the build rather than shipping.

Sheet Inputs
A1: Inputs
A2: Yellow cells only. Every other sheet reads from here.
A4: Input | B4: Value | C4: Note
A5: THE TRANSFERRED PACKAGES
A6: P1 Civil works — contract sum | B6: 3400000 | C6: Fixed at the cut-off valuation. Never provisional — playbook 8.3.
A7: P2 Modular accommodation — contract sum | B7: 11800000 | C7: Usually the largest of the five.
A8: P3 Kitchen fit-out — contract sum | B8: 1150000
A9: P4 Furniture, fittings and equipment — contract sum | B9: 820000
A10: Number of packages actually transferred | B10: 4 | C10: Set to 3 to model a partial consolidation — playbook 6.4.
A11: THE PRIME'S OWN PACKAGE
A12: P5 FM and operation — contract sum | B12: 6900000 | C12: NOT part of the transferred value. The stack is never applied to it.
A13: THE WRAP
A14: Management and integration | B14: 0.07 | C14: Playbook range 6–9%. The only line with a headcount behind it.
A15: Corporate overhead recovery | B15: 0.04 | C15: Range 3–5%.
A16: Profit and prime risk | B16: 0.06 | C16: Range 5–8%.
A17: Controlled contingency | B17: 0.04 | C17: Range 3–5%. Not profit — held against the joint register.
A18: Contingency expected to be returned | B18: 0.5 | C18: Set to 0 if the prime keeps it all; 1 if it is fully returned unused.
A19: THE CLIENT'S OWN COST OF CARRYING FIVE
A20: Months the client would carry the load | B20: 24 | C20: From now to the last practical completion.
A21: Hours per month, per contract administered | B21: 14 | C21: Valuation, notices, change, reporting, correspondence.
A22: Hours per month, per interface held | B22: 9 | C22: Meetings, chasing drawings, reconciling two programmes.
A23: Hours per month, per main-project interface | B23: 5 | C23: The accommodation against the main works.
A24: All-in cost of a client management hour | B24: 78 | C24: Salary, on-costs, overhead — not a charge-out rate.
A25: Cost of one missed pay-less notice | B25: 180000 | C25: The sum applied for becomes payable in full. Size it on one month's application.
A26: Probability of missing one, per notice | B26: 0.004 | C26: 0.4% per deadline. Sixty deadlines a year is not a small number of chances.
A27: DELAY RISK — WHAT SINGLE-POINT ACCOUNTABILITY IS ACTUALLY FOR
A28: Beds in the village | B28: 225
A29: Cost per bed per day if a bed is not available | B29: 145 | C29: Substitute accommodation, subsistence, travel and administration. See the P2 Employer's Requirements.
A30: Months of delay at risk | B30: 1.5 | C30: The realistic exposure if the interfaces are not held.
A31: Probability of that delay with five packages | B31: 0.35
A32: Probability of that delay after consolidation | B32: 0.15 | C32: It does not go to zero. The prime can be late too.
A33: LIQUIDATED DAMAGES
A34: LD cap, per contract | B34: 0.05 | C34: Five per cent of the contract sum is the common position.
A35: Expected delay exposure, as a share of each cap | B35: 0.6 | C35: How much of each cap you would realistically be claiming.
A36: Transaction cost of the consolidation | B36: 95000 | C36: Five deeds, four cut-off valuations, and twelve weeks of management time.

Sheet DecisionTest
A1: Decision test
A2: Playbook clause 5.3. Score each line 0, 1 or 2. The verdict is computed.
A4: Question | B4: Score | C4: What a 2 means
A5: Can the client name one person, with time, who holds the ten interfaces? | B5: 2 | C5: No, or the name is someone already full
A6: How many coordination deliverables are overdue? | B6: 2 | C6: Three or more
A7: Has a statutory payment or pay-less notice been missed, or nearly missed? | B7: 1 | C7: Yes, on any package
A8: Are the five progress reports reconciled against one programme every month? | B8: 2 | C8: No, or only sometimes
A9: Is the accommodation competing for the same people as the main project? | B9: 2 | C9: Yes, the same people hold both
A10: Are the four enabling clauses in all five contracts? | B10: 2 | C10: Yes, all four — otherwise read playbook 7.5 first
A11: Is every package performing to its own contract? | B11: 2 | C11: Yes. A 0 here STOPS the model — see the Verdict sheet
A12: Is at least one of the five capable of holding the other four? | B12: 2 | C12: Yes, clearly
A14: Total score, out of 16 | B14: =SUM(B5:B12) | C14: 8 or more: consolidate. Below 6: resource the interfaces instead. 6 to 8: consolidate a subset.
A15: Every package performing? | B15: =IF(B11=0,"NO — STOP","Yes") | C15: Playbook 5.1. Consolidating a performance problem buries it and pays a wrap to acquire it.
A16: Verdict | B16: =IF(B11=0,"DO NOT CONSOLIDATE — fix the failing package first",IF(DecisionTest!$B$14>=8,"CONSOLIDATE",IF(DecisionTest!$B$14>=6,"CONSOLIDATE A SUBSET","DO NOT CONSOLIDATE — resource the interfaces")))

Sheet LoadModel
A1: What five packages actually cost the client to carry
A2: Interfaces grow as n(n−1)÷2. This is the number the wrap is compared against.
A4: Measure | B4: With five | C4: After | D4: Note
A5: Packages | B5: 5 | C5: 1 | D5: The prime becomes the single counterparty.
A6: Interfaces between packages, n(n−1)÷2 | B6: =5*(5-1)/2 | C6: 0 | D6: They do not disappear. They move inside the prime's scope and are priced there.
A7: Interfaces with the main project | B7: 5 | C7: 1
A8: Contracts administered | B8: 5 | C8: 1
A9: Statutory notice deadlines per year (payment + pay-less) | B9: =5*12*2 | C9: =1*12*2 | D9: Miss one pay-less notice and the sum applied for is payable in full.
A11: MANAGEMENT HOURS PER MONTH
A12: Contract administration | B12: =B8*Inputs!$B$21 | C12: =C8*Inputs!$B$21
A13: Interfaces between packages | B13: =B6*Inputs!$B$22 | C13: =C6*Inputs!$B$22
A14: Main-project interfaces | B14: =B7*Inputs!$B$23 | C14: =C7*Inputs!$B$23
A15: Total hours per month | B15: =SUM(B12:B14) | C15: =SUM(C12:C14) | D15: At the all-in cost on Inputs, not a charge-out rate.
A17: Management cost over the period | B17: =LoadModel!$B$15*Inputs!$B$20*Inputs!$B$24 | C17: =LoadModel!$C$15*Inputs!$B$20*Inputs!$B$24
A18: Expected cost of missed notices over the period | B18: =B9/12*Inputs!$B$20*Inputs!$B$26*Inputs!$B$25 | C18: =C9/12*Inputs!$B$20*Inputs!$B$26*Inputs!$B$25 | D18: Probability × exposure. Not a worst case — an expected value.
A19: TOTAL COST OF CARRYING THE LOAD | B19: =LoadModel!$B$17+LoadModel!$B$18 | C19: =LoadModel!$C$17+LoadModel!$C$18
A20: Load cost avoided by consolidating | B20: =LoadModel!$B$19-LoadModel!$C$19 | D20: Management hours and expected notice losses only.
A22: DELAY RISK — the benefit that dwarfs the management hours
A23: Cost of one month of the village being late | B23: =Inputs!$B$28*30*Inputs!$B$29 | D23: Beds x 30 days x the daily cost of not having one.
A24: Expected delay cost, with five packages | B24: =LoadModel!$B$23*Inputs!$B$30*Inputs!$B$31
A25: Expected delay cost, after consolidation | B25: =LoadModel!$B$23*Inputs!$B$30*Inputs!$B$32
A26: Delay risk avoided | B26: =LoadModel!$B$24-LoadModel!$B$25 | D26: This is what single-point accountability is actually bought for. It is larger than the management saving and it is the line that is never modelled.

Sheet WrapCost
A1: The wrap
A2: Applied to the transferred value only — never to the prime's own package.
A4: Transferred value (the packages actually moving) | B4: =IF(Inputs!$B$10>=4,Inputs!$B$6+Inputs!$B$7+Inputs!$B$8+Inputs!$B$9,IF(Inputs!$B$10=3,Inputs!$B$6+Inputs!$B$7+Inputs!$B$8,IF(Inputs!$B$10=2,Inputs!$B$6+Inputs!$B$7,Inputs!$B$6))) | D4: Packages drop off from P4 upward as the transferred count falls.
A5: The prime's own package, excluded | B5: =Inputs!$B$12 | D5: Already competed in its own tender. A stack on this is the same money taken twice.
A7: Stack line | B7: Rate | C7: Amount | D7: Note
A8: Management and integration | B8: =Inputs!$B$14 | C8: =WrapCost!$B$4*Inputs!$B$14 | D8: The only line with a headcount behind it. Ask for names and time.
A9: Corporate overhead recovery | B9: =Inputs!$B$15 | C9: =WrapCost!$B$4*Inputs!$B$15 | D9: Lower than a full prime contract — the prime already carries this.
A10: Profit and prime risk | B10: =Inputs!$B$16 | C10: =WrapCost!$B$4*Inputs!$B$16 | D10: Should rise if a package is in difficulty and fall if all are performing.
A11: Controlled contingency | B11: =Inputs!$B$17 | C11: =WrapCost!$B$4*Inputs!$B$17 | D11: Not profit. Drawn only against the joint register.
A12: TOTAL ADDITION | B12: =SUM(B8:B11) | C12: =SUM(C8:C11) | D12: Playbook range 17–27%. Expect the lower half on competed prices in good order.
A13: Less contingency expected back | B13: =Inputs!$B$18 | C13: =-WrapCost!$B$4*Inputs!$B$17*Inputs!$B$18 | D13: Unused contingency returned or shared. Zero this if the prime keeps it.
A14: Transaction cost of the transfer | C14: =Inputs!$B$36 | D14: Five deeds, four cut-off valuations, twelve weeks of management.
A15: NET COST OF CONSOLIDATING | C15: =WrapCost!$C$12+WrapCost!$C$13+WrapCost!$C$14 | D15: Compare against LoadModel — the cost avoided.

Sheet LDImpact
A1: Liquidated damages: four caps become one
A2: The prime will not raise this. It is a real reduction in what the client can recover.
A4: Position | B4: Basis | C4: Recoverable | D4: Note
A5: With five separate contracts | B5: =(Inputs!$B$6+Inputs!$B$7+Inputs!$B$8+Inputs!$B$9+Inputs!$B$12)*Inputs!$B$34 | C5: =B5*Inputs!$B$35 | D5: Five caps, five contracts, five independent claims.
A6: After consolidation — one contract with the prime | B6: =(Inputs!$B$6+Inputs!$B$7+Inputs!$B$8+Inputs!$B$9+Inputs!$B$12)*Inputs!$B$34 | C6: =B6*Inputs!$B$35 | D6: One cap on the consolidated sum. Same percentage, one contract.
A7: Difference | C7: =LDImpact!$C$6-LDImpact!$C$5 | D7: Zero where the cap is a percentage of the whole. It is NOT zero where the prime negotiates a cap in absolute terms — model that below.
A9: IF THE PRIME NEGOTIATES AN ABSOLUTE CAP
A10: Absolute cap the prime asks for | B10: 500000 | D10: A single sum, not a percentage. This is the ask to watch for.
A11: Recoverable under an absolute cap | C11: =MIN(LDImpact!$B$10,LDImpact!$C$5)
A12: LOST RECOVERY | C12: =LDImpact!$C$5-LDImpact!$C$11 | D12: Add this to the cost of consolidating. It is as real as the wrap and it is never on the invoice.

Sheet Verdict
A1: The answer
A2: Three numbers, and whether the trade is worth it.
B4: Amount | C4: Where it comes from
A5: Load cost avoided by consolidating | B5: =LoadModel!$B$20 | C5: LoadModel — management hours and expected notice losses
A6: Delay risk avoided | B6: =LoadModel!$B$26 | C6: LoadModel — the larger of the two benefits, and the one usually left out
A7: Net cost of consolidating | B7: =-WrapCost!$C$15 | C7: WrapCost — the stack, less contingency returned, plus the transaction cost
A8: Liquidated damages recovery lost | B8: =-LDImpact!$C$12 | C8: LDImpact — only where the prime negotiates an absolute cap
A9: NET POSITION | B9: =Verdict!$B$5+Verdict!$B$6+Verdict!$B$7+Verdict!$B$8 | C9: Positive: the measurable benefits exceed the wrap. Negative: they do not — read the break-even below before concluding anything.
A11: Total measurable benefit | B11: =Verdict!$B$5+Verdict!$B$6-LDImpact!$C$12 | C11: Management, notices and delay risk, less the liquidated damages recovery given up.
A12: BREAK-EVEN WRAP RATE | B12: =(Verdict!$B$11-Inputs!$B$36)/WrapCost!$B$4 | C12: The gross stack rate at which consolidation pays for itself on measurable expected value alone. Negotiate toward it, knowing the market sits well above it.
A13: The rate actually offered | B13: =WrapCost!$B$12 | C13: WrapCost
A14: The gap, in money | B14: =(WrapCost!$B$12-Verdict!$B$12)*WrapCost!$B$4 | C14: What the client pays above measurable expected value. It is not waste — it is the price of certainty and of management capacity that cannot be hired. But it should be paid knowingly.
A16: Decision test verdict | B16: =DecisionTest!$B$16 | C16: DecisionTest
A17: THE ANSWER | B17: =IF(DecisionTest!$B$11=0,"NO — fix the failing package first. The numbers below are not the question.",IF(AND(DecisionTest!$B$14>=8,Verdict!$B$9>0),"YES — consolidate. The load costs more than the wrap.",IF(AND(DecisionTest!$B$14>=8,Verdict!$B$9<=0),"CONSOLIDATE ON JUDGEMENT, NOT ON THIS MODEL — the load is real but the wrap does not pay for itself on these numbers.",IF(DecisionTest!$B$14>=6,"CONSOLIDATE A SUBSET — see playbook 6.4.","NO — resource the interfaces instead.")))) | C17: The score and the money have to agree. Where they do not, the sheet says so rather than picking one.
A19: A caution, and it is the point of the model
A20: A positive net position is not a reason to consolidate a performance problem, and the model refuses to give one.
A21: A negative net position is not a reason to refuse a consolidation the decision test says you need: management capacity
A22: you do not have cannot be bought at any rate on the Inputs sheet, and the model cannot see that.
A23: The numbers are here so the decision is argued about with them, not instead of them.
A25: EXPECT THE NET POSITION TO BE NEGATIVE. On measurable expected value a market-rate wrap almost never pays for
A26: itself, and a model that produced a positive number here would be flattering the decision rather than testing it.
A27: What the client buys above the break-even rate is certainty and capacity: single-point accountability, and a management
A28: team it could not hire, assemble and hold for the duration at any rate on the Inputs sheet. That is a real purchase and
A29: it is a legitimate one. It is also the number to take into the negotiation at playbook 8.2 — because a prime that knows
A30: the client has done this arithmetic prices differently from one that assumes it has not.
