Workbook

Sheet ReadMe
B2: WORKERS ACCOMMODATION VILLAGE — RESOURCE AND OPERATING PLAN
B3: 300-person peak · 38-month programme · multi-company site
B4: ETABLIX — Integrated Site Services, part of Groupe Nseya
B7: WHAT THIS IS | C7: A working model, not a picture of one. Change a driver on Assumptions and every bed, cover, litre, kilowatt, bus seat, FTE and pound downstream moves with it. Nothing below Assumptions is typed in by hand.
B9: HOW TO USE IT | C9: 1. Set the drivers on Assumptions. Blue cells are yours to change; yellow are the ones that move the answer most.
C10: 2. Put your real companies, teams and dates on Teams. Add or delete rows — everything else follows the range.
C11: 3. Read Workforce, then BedDemand. Those two decide the village.
C12: 4. Accommodation, Facilities, Utilities, Transport and VillageStaff size what you build and who runs it.
C13: 5. Capex, Opex and CostSummary cost it. Replace every rate with your own quotation before anyone quotes from this.
C14: 6. Compliance, Risks and Mobilisation are the parts that get forgotten and then hurt.
B16: COLOUR | C16: Blue text = type here. Black = calculated, do not overtype. Green = pulled from another sheet. Yellow fill = a driver that changes the answer materially.
B18: THE ONE RULE | C18: Every figure here is a first-pass planning figure for validation by a competent person. It is not a design, a price or an instruction. Loads, flows, ratios and durations size a decision; they do not survive procurement without an engineer, and nothing safety-critical is resolved in a spreadsheet.
B20: ON THE COSTS | C20: Every rate on Capex and Opex is INDICATIVE and marked as such — an order-of-magnitude figure to size the decision, not a quotation and not a budget. They are blue because they are yours to replace. A number taken from here into a tender without a supplier behind it is your risk, not an estimate.
B22: WHAT DRIVES WHAT
B24: Teams → Workforce | C24: each team's start, peak and end become a headcount curve across 38 months
B25: Workforce → BedDemand | C25: travelling percentage per team turns headcount into people needing a bed
B26: BedDemand → Accommodation | C26: peak beds, plus void, contingency and accessible provision, becomes a room schedule
B27: BedDemand → Facilities | C27: occupancy becomes canteen covers, laundry machines, drying, WCs and social space
B28: BedDemand → Utilities | C28: occupancy becomes water, foul, power, heat and waste, month by month
B29: BedDemand → Transport | C29: residents become bus seats, journeys and parking
B30: BedDemand → VillageStaff | C30: occupancy becomes the FTEs who run the village, 24/7 cover included
B31: Accommodation → Capex | C31: rooms and blocks become what it costs to create the village
B32: VillageStaff + Utilities → Opex | C32: people, energy and consumption become what it costs to run it each month
B33: Capex + Opex → CostSummary | C33: whole-life cost, cost per bed-night, and the cost recharged to each company
B34: Packages → Capex | C34: the five packages you buy — civil works, modular accommodation, kitchen, furniture, FM and operation
B35: Packages → the interfaces | C35: fifteen of them. A village fails between packages, not inside them — that table is the one to argue about before anything is let
B36: Capex + Opex → CostSummary | C36: whole-life cost by package, cost per bed-night, and the break-even against booking rooms

Sheet Assumptions
B2: ASSUMPTIONS AND DRIVERS
B3: Blue = type here. Yellow = changes the answer materially. Every figure carries its basis; a basis of “to verify” means exactly that.
A5: ONE PLACE FOR EVERY NUMBER THIS PLAN RESTS ON
B6: Driver | C6: Value | D6: Unit | E6: Basis — and whether it is verified
A8: PROJECT
B9: Project / site | C9: Project NORTHREACH — worked example | E9: Replace with the real project. Nothing else keys off this.
B10: Programme start (month 1) | C10: 46388 | D10: date | E10: A real date, not text. Every month label across the workbook is EDATE from this cell, so a text value here puts #VALUE! in 190 header cells.
B11: Programme duration | C11: 38 | D11: months | E11: The plan is built for 38 columns. Changing this does not add columns.
B12: Peak site population | C12: =MAX(Workforce!C29:AN29) | D12: people | E12: Calculated from Teams. The headline 300 is the planning figure; the model says what the curve actually peaks at.
B13: Peak travelling population | C13: =MAX(BedDemand!C7:AN7) | D13: people | E13: The number that decides the village. Everyone else goes home at night.
A15: WHO NEEDS A BED
B16: Rooms allocated per traveller | C16: 1 | D16: rooms | E16: One room per person. Sharing on rotation cuts rooms but needs strict rota discipline and personal storage; drop to 0.7 only if the rotation is contractual.
B17: Rotation presence factor | C17: 1 | D17: × | E17: 1.00 = everyone on site at once. A 3-on/1-off rotation is about 0.75. Verify against the actual rota before sizing.
B18: Void and turnover allowance | C18: 0.05 | D18: % | E18: Rooms out of service for cleaning, changeover, damage and maintenance. Industry practice 4–6%; to verify against your operator.
B19: Contingency rooms | C19: 0.05 | D19: % | E19: Headroom for a package running late over one running early. Not a substitute for a proper curve.
B20: Female provision | C20: 0.08 | D20: % | E20: Of the travelling population. Drives a separate lockable block or floor, not just a room count. Set from your own diversity data — 8% is a placeholder.
B21: Accessible rooms | C21: 0.05 | D21: % | E21: Wheelchair-accessible rooms with level access and accessible WC/shower. Confirm the required proportion with Building Control — this is a placeholder, not a standard.
B22: Senior / manager rooms | C22: 0.06 | D22: % | E22: Larger room with a desk. A commercial decision, not a requirement.
B23: Visitor and spare rooms | C23: 6 | D23: rooms | E23: Auditors, inspectors, client visits, isolation. Not optional in practice.
A25: ROOM AND BLOCK SIZING
B26: Standard room — floor area | C26: 11 | D26: m² | E26: Single ensuite. Typical modular workforce room 10–12 m² including shower room. To verify against the module you actually procure.
B27: Accessible room — floor area | C27: 16 | D27: m² | E27: Turning circle and accessible shower room. To verify with Building Control.
B28: Senior room — floor area | C28: 14 | D28: m²
B29: Rooms per accommodation block | C29: 24 | D29: rooms | E29: Two storeys of twelve is a common modular block. Set from the supplier's standard module.
B30: Circulation, plant and stair gross-up | C30: 1.35 | D30: × | E30: Corridors, stairs, risers, plant. Applied to net room area to get gross block area.
B31: External space per bed | C31: 45 | D31: m² | E31: Roads, parking, footpaths, drainage, landscaping and the standoff between blocks for fire and privacy. At 22 m² the total site came out at 0.75 ha for 225 rooms, which cannot hold roads, parking and separation. 45 m² gives about 1.6 ha, which is the order a village of this size actually occupies. To verify against a real layout.
A33: CATERING
B34: Take breakfast on site | C34: 0.85 | D34: % | E34: Of residents. Drives covers and food cost.
B35: Take evening meal on site | C35: 0.92 | D35: % | E35: Of residents.
B36: Packed lunches taken | C36: 0.9 | D36: % | E36: Of residents. Made in the same kitchen, no covers needed.
B37: Sittings per meal service | C37: 2 | D37: no. | E37: Two sittings halves the dining room. Three is possible and unpopular.
B38: Dining area per cover | C38: 1.6 | D38: m² | E38: Table, chair and circulation. 1.5–1.8 m² typical; to verify.
B39: Kitchen and servery per cover | C39: 0.55 | D39: m² | E39: Preparation, cooking, servery, wash-up, dry and cold store. To verify with the caterer.
A41: LAUNDRY, HOUSEKEEPING AND SOCIAL
B42: Residents per washing machine | C42: 14 | D42: people | E42: Self-service laundry. To verify — depends whether linen is contracted out.
B43: Residents per tumble dryer | C43: 16 | D43: people
B44: Drying room capacity per 100 residents | C44: 1 | D44: rooms | E44: Wet PPE and boots. Separate from the laundry and non-negotiable in a wet climate.
B45: Rooms cleaned per housekeeper per shift | C45: 18 | D45: rooms | E45: Full clean and linen change. To verify with the operator.
B46: Linen change frequency | C46: 1 | D46: per week
B47: Gym area per 100 residents | C47: 45 | D47: m² | E47: A gym is not a luxury on a 38-month village; it is retention.
B48: Social / TV space per 100 residents | C48: 60 | D48: m² | E48: Quiet room, TV room, games. Splitting it into several small rooms works better than one large one.
A50: UTILITIES AND WASTE
B51: Water demand | C51: 140 | D51: l/person/day | E51: Residential occupancy including showers, laundry and catering. Far above the site-welfare figure. To verify with the water undertaker.
B52: Hot water proportion | C52: 0.4 | D52: % | E52: Of total water. Drives the heating load and the calorifier sizing.
B53: Foul return | C53: 0.95 | D53: % | E53: Of water in. Drives treatment plant or tanker frequency.
B54: Electrical load per bed | C54: 1.6 | D54: kW | E54: Lighting, small power, ventilation, hot water. Excludes catering and electric heating. To verify with an engineer.
B55: Diversity factor | C55: 0.65 | D55: × | E55: Not every load runs at once. Applied to connected load to get demand. To verify.
B56: Catering electrical load | C56: 90 | D56: kW | E56: Kitchen, servery, cold stores, wash-up. Add if the kitchen is electric rather than gas.
B57: Heating load per bed | C57: 1.2 | D57: kW | E57: Space heating at design outside temperature. To verify with the module supplier's U-values.
B58: Power factor | C58: 0.9 | D58: × | E58: Converts kW to kVA for generation or a DNO connection. Sets are rated in kVA.
B59: Waste arisings | C59: 1.1 | D59: kg/person/day | E59: Residential plus catering. To verify with the waste contractor.
B60: Recycling and diversion target | C60: 0.55 | D60: %
A62: TRANSPORT
B63: Residents transported to site | C63: 0.95 | D63: % | E63: The rest drive or walk. A village next to the site changes this.
B64: Bus seats | C64: 53 | D64: seats | E64: Standard coach. A 16-seat minibus changes the arithmetic entirely.
B65: Bus load factor | C65: 0.85 | D65: % | E65: Nobody fills every seat every run.
B66: Runs per shift change | C66: 2 | D66: no. | E66: Two runs staggers the arrival peak at the gate.
B67: Shift changes per day | C67: 2 | D67: no. | E67: One for a single shift, two for two-shift working.
B68: Resident parking per 10 residents | C68: 1.5 | D68: spaces | E68: Most residents are bussed; some keep a car for days off.
B69: Village staff and visitor parking | C69: 25 | D69: spaces
A71: RUNNING THE VILLAGE — STAFFING RATIOS
B72: FTE contracted hours | C72: 42 | D72: h/week
B73: 24/7 post cover factor | C73: 4.6 | D73: FTE/post | E73: 168 hours a week divided by contracted hours, plus leave, sickness and training cover. To verify with your HR model.
B74: Reception posts (24/7) | C74: 1 | D74: posts
B75: Security posts (24/7) | C75: 2 | D75: posts | E75: Gatehouse plus patrol. Confirm against the security risk assessment.
B76: Beds per housekeeping FTE | C76: 32 | D76: beds | E76: Derived from rooms per shift; shown here so it can be overridden directly.
B77: Covers per catering FTE | C77: 45 | D77: covers | E77: Chefs, servery, wash-up and stores across the meal cycle. To verify with the caterer.
B78: Maintenance FTE per 100 beds | C78: 0.9 | D78: FTE | E78: Reactive and planned, including grounds and waste.
B79: Village management FTE | C79: 2 | D79: FTE | E79: Village manager and deputy. Below about 150 beds, one.
B80: Administration and welfare FTE | C80: 1.5 | D80: FTE | E80: Bookings, inductions, pastoral and complaints. The last one is why villages succeed or fail.
A82: INDICATIVE RATES — REPLACE EVERY ONE BEFORE QUOTING
B83: Room module — supply, deliver, install | C83: 24000 | D83: £/room | E83: INDICATIVE ORDER OF MAGNITUDE. Not a quotation. Varies enormously with specification and distance.
B84: Groundworks and hardstanding | C84: 95 | D84: £/m² | E84: INDICATIVE. Depends entirely on ground conditions, which are not known here.
B85: Utility connections and infrastructure | C85: 850000 | D85: £ lump | E85: INDICATIVE. Wholly dependent on distance to the mains and DNO capacity.
B86: Furniture, fittings and equipment | C86: 3200 | D86: £/room | E86: INDICATIVE.
B87: Catering fit-out | C87: 4200 | D87: £/cover | E87: INDICATIVE.
B88: Design, consents and surveys | C88: 380000 | D88: £ lump | E88: INDICATIVE. Planning for a temporary village is not a formality.
B89: Demobilisation and reinstatement | C89: 0.1 | D89: % of capex | E89: INDICATIVE, applied to the physical packages P1–P4 only. You do not demobilise a design fee or a mobilisation cost. Ten per cent of the physical works is an order-of-magnitude figure for removal, making good and reinstatement — replace it with a real scope.
B90: Room hire | C90: 620 | D90: £/room/month | E90: INDICATIVE, where modules are hired rather than bought. Set to zero if purchased above.
B91: Utilities | C91: 145 | D91: £/bed/month | E91: INDICATIVE.
B92: Catering | C92: 24 | D92: £/resident/day | E92: INDICATIVE. Three meals including packed lunch.
B93: Housekeeping and laundry | C93: 118 | D93: £/room/month | E93: INDICATIVE.
B94: Transport | C94: 9500 | D94: £/bus/month | E94: INDICATIVE. Driver, fuel, maintenance, insurance.
... B97: Maintenance and consumables | C97: 42 | D97: £/room/month | E97: INDICATIVE.
A99: VILLAGE DELIVERY PROGRAMME
B100: Design, planning and consents | C100: 7 | D100: months | E100: A temporary workers village usually needs full planning permission. To verify with the local authority.
B101: Procurement and module lead time | C101: 5 | D101: months | E101: Runs partly in parallel with consents at your own risk.
B102: Groundworks and infrastructure | C102: 4 | D102: months
B103: Module delivery and installation | C103: 3 | D103: months
B104: Commissioning and handover | C104: 1 | D104: months
B105: Village must be live by month | C105: 4 | D105: month no. | E105: The first travelling worker arrives in month 3 on this curve. Work backwards from that, not forwards from today.

Sheet Teams
A2: COMPANIES AND TEAMS
A3: Every blue cell is yours. Add or remove rows inside the block and the whole model follows — but if you add rows below the last team, extend the ranges on Workforce and BedDemand to match.
A4: Ref | B4: Company | C4: Team / package | D4: Trade | E4: Peak | F4: Start month | G4: At full month | H4: Last full month | I4: End month | J4: Travelling % | K4: Shift pattern | L4: Role | M4: Notes
A5: T01 | B5: Marrowbridge Infrastructure Ltd | C5: Project management team | D5: Management | E5: 18 | F5: 1 | G5: 3 | H5: 36 | I5: 38 | J5: 0.55 | K5: Days Mon–Fri | L5: Main contractor
A6: T02 | B6: Marrowbridge Infrastructure Ltd | C6: Site supervision | D6: Supervision | E6: 20 | F6: 3 | G6: 6 | H6: 34 | I6: 36 | J6: 0.6 | K6: Days + back shift | L6: Main contractor
A7: T03 | B7: Marrowbridge Infrastructure Ltd | C7: HSEQ & quality | D7: HSEQ | E7: 8 | F7: 2 | G7: 4 | H7: 35 | I7: 37 | J7: 0.5 | K7: Days Mon–Fri | L7: Main contractor
A8: T04 | B8: Redmoor Groundworks Ltd | C8: Earthworks gang A | D8: Earthworks | E8: 34 | F8: 3 | G8: 5 | H8: 14 | I8: 16 | J8: 0.35 | K8: Days 6/7 | L8: Subcontractor
A9: T05 | B9: Redmoor Groundworks Ltd | C9: Earthworks gang B | D9: Earthworks | E9: 26 | F9: 5 | G9: 7 | H9: 13 | I9: 15 | J9: 0.35 | K9: Days 6/7 | L9: Subcontractor
A10: T06 | B10: Calderbrook Civils Ltd | C10: Compound & hardstanding | D10: Civils | E10: 30 | F10: 2 | G10: 4 | H10: 9 | I10: 11 | J10: 0.4 | K10: Days 6/7 | L10: Subcontractor
A11: T07 | B11: Calderbrook Civils Ltd | C11: Foundations & structures | D11: Civils | E11: 33 | F11: 8 | G11: 11 | H11: 22 | I11: 25 | J11: 0.45 | K11: Days 6/7 | L11: Subcontractor
A12: T08 | B12: Calderbrook Civils Ltd | C12: Drainage & ducting | D12: Civils | E12: 16 | F12: 6 | G12: 8 | H12: 20 | I12: 22 | J12: 0.4 | K12: Days 6/7 | L12: Subcontractor
A13: T09 | B13: Northgate Steel Ltd | C13: Steel erection | D13: Steelwork | E13: 33 | F13: 14 | G13: 17 | H13: 26 | I13: 29 | J13: 0.8 | K13: Two shift | L13: Subcontractor
A14: T10 | B14: Northgate Steel Ltd | C14: Cladding & envelope | D14: Envelope | E14: 21 | F14: 20 | G14: 22 | H14: 30 | I14: 32 | J14: 0.75 | K14: Two shift | L14: Subcontractor
A15: T11 | B15: Ledwyn Scaffolding Ltd | C15: Scaffold gangs | D15: Scaffold | E15: 14 | F15: 12 | G15: 14 | H15: 30 | I15: 33 | J15: 0.7 | K15: Days 6/7 | L15: Subcontractor
A16: T12 | B16: Penmark Cable Services Ltd | C16: Cable pulling | D16: Cable | E16: 26 | F16: 16 | G16: 19 | H16: 30 | I16: 33 | J16: 0.85 | K16: Two shift | L16: Specialist
... A26: T22 | B26: Hollins Catering Ltd | C26: Catering & housekeeping | D26: Catering | E26: 14 | F26: 2 | G26: 4 | H26: 37 | I26: 38 | J26: 0.4 | K26: Split shift | L26: Village operator
B28: Companies represented | E28: =SUMPRODUCT(1/COUNTIF(B5:B26,B5:B26))
B29: Teams | E29: =COUNTA(A5:A26)
B30: Sum of team peaks (not the site peak — teams peak at different times) | E30: =SUM(E5:E26)

Sheet Packages
B2: THE FIVE PACKAGES — AND WHAT FALLS BETWEEN THEM
B3: Five packages is a clean way to buy a village. It also creates fifteen interfaces, and a village fails at the interfaces, not inside the packages. The second table is the one to argue about before anything is let.
B5: Ref | C5: Package | D5: In one line | E5: What is in it | F5: What is expressly NOT in it
B6: P1 | C6: Civil works | D6: Everything below and between the buildings | E6: Site clearance, cut and fill, ground improvement · foundations, bases and plinths for every module · roads, hardstanding, footpaths, parking · surface and foul drainage · incoming utility infrastructure to the module connection point · fencing, gates, lighting columns · landscaping · reinstatement at the end | F6: Above the module connection point · anything inside a module · maintenance of roads and drainage once the village is live
B7: P2 | C7: Modular accommodation | D7: The buildings, delivered and connected | E7: Bedroom blocks · amenity buildings (gym, social, laundry, drying) · reception and village office · corridors, stairs, fire compartmentation · module transport, craneage and setting out · internal M&E within the module · connection to the civils' termination points · commissioning of the building services | F7: Ground preparation and bases · loose furniture · catering equipment · operation
B8: P3 | C8: Kitchen | D8: The catering facility as a working kitchen | E8: Kitchen fit-out, servery and wash-up · cold and dry stores · extraction, interlocks and gas safety · catering equipment supply and commissioning · food hygiene registration support · dining room servery counters | F8: The building shell (P2) · dining tables and chairs (P4) · the people who cook (P5)
B9: P4 | C9: Furniture | D9: Everything loose, in every room | E9: Bed, mattress, wardrobe, desk, chair, storage per bedroom · soft furnishings, curtains, floor coverings if loose · dining tables and chairs · social and gym furniture · office and reception furniture · white goods in laundries · signage | F9: Fixed joinery inside modules (P2) · catering equipment (P3) · replacement of damaged items in operation (P5)
B10: P5 | C10: FM and operation | D10: Running it for 38 months | E10: Village management, reception 24/7, security 24/7 · housekeeping and linen · catering operation and food supply · maintenance, grounds and waste · transport and drivers · utilities management and metering · resident welfare, inductions and complaints · statutory compliance in operation — legionella, fire, gas, electrical, food hygiene | F10: Capital replacement · anything that is a defect under P1–P4
A13: THE INTERFACES — WHERE THE MONEY AND THE ARGUMENTS ARE
B14: Ref | C14: Between | D14: The interface | E14: What fails if nobody owns it | F14: Where it should sit
B15: IF-01 | C15: P1 ↔ P2 | D15: Setting-out, levels and base tolerance for every module | E15: Modules arrive to bases that are out of tolerance. Craneage stands, the programme slips a week per block, and neither party accepts the levels. | F15: P1 sets out and certifies levels to the module supplier's tolerance, in writing, before delivery.
B16: IF-02 | C16: P1 ↔ P2 | D16: The utility termination point — exactly where civils stop and the module starts | E16: Water, foul, power and comms arrive near the module but not connected to it. Two contractors each price to the other's boundary and neither crosses it. | F16: One drawing showing a termination point per service per block, signed by both. This is the commonest village dispute there is.
B17: IF-03 | C17: P2 ↔ P3 | D17: Whether the kitchen is a module or a fit-out into a shell | E17: The kitchen is ordered twice or not at all. Extraction penetrations are not in the module drawing and get cut on site. | F17: Decide before P2 is ordered. If a fit-out, P2 supplies a shell with agreed penetrations, floor loading and drainage falls.
B18: IF-04 | C18: P3 ↔ P4 | D18: Dining tables and chairs | E18: The dining room has a servery and no seats on opening day. Both packages assumed the other had it. | F18: P4. Anything loose is furniture, including in the dining room — say so in both scopes.
B19: IF-05 | C19: P2 ↔ P4 | D19: Fixed joinery versus loose furniture in the bedroom | E19: Wardrobes and desks are either duplicated or missing. Modular suppliers vary on what is included as standard. | F19: Fix the bedroom specification item by item before either package is let, and attach it to both.
B20: IF-06 | C20: P4 ↔ P5 | D20: Replacement of damaged or worn furniture over 38 months | E20: Broken beds are nobody's, and rooms go out of service. Void rate rises and nobody can say why. | F20: P5, from a replacement allowance funded in Opex, with a stock level agreed at handover.
B21: IF-07 | C21: P1 ↔ P5 | D21: Maintenance of roads, drainage, lighting and grounds in operation | E21: Gullies block, the car park floods, the access degrades under bus traffic and there is no maintenance budget. | F21: P5, with a condition survey at handover defining the standard being taken on.
B22: IF-08 | C22: P3 ↔ P5 | D22: Ownership and maintenance of catering equipment, and who holds the hygiene registration | E22: Equipment fails, warranty is disputed, and the registration is in the wrong name at the first inspection. | F22: P5 holds the registration and the maintenance; P3 hands over with warranties assigned and an asset register.
B23: IF-09 | C23: P2 ↔ P5 | D23: Building services commissioning, handover and the defects period | E23: The village is occupied before commissioning is complete, and defects become operational problems nobody logs. | F23: No occupation before commissioning sign-off. A defects liaison route in P5's scope from day one.
B24: IF-10 | C24: P2 ↔ P5 | D24: Legionella duty from first fill of the water system | E24: The system is filled at installation and sits at low occupancy for weeks. The duty starts at fill; nobody has started flushing. | F24: P5 takes the water safety plan from first fill, not from first occupation. Write it into P2's handover.
B25: IF-11 | C25: P1 ↔ P3 | D25: Kitchen drainage, grease interceptor and its maintenance | E25: The interceptor is installed by one and never emptied by anyone. | F25: P1 installs to P3's specification; P5 maintains it on a stated frequency.
... B29: IF-15 | C29: All five ↔ the project | D29: One accountable owner for the village as a system | E29: Five suppliers each doing their scope correctly while nobody owns whether the village works. This is precisely the gap ETABLIX exists to close. | F29: A single integrator over all five, with the interface register above as their instrument.

Sheet Workforce
A2: WORKFORCE CURVE — HEADCOUNT BY TEAM, BY MONTH
A3: Calculated from Teams. Nothing here is typed. A team ramps from its start month to full, holds, then ramps down to its end month.
B5: Month label | C5: =TEXT(EDATE(Assumptions!$C$10,0),"mmm-yy") | D5: =TEXT(EDATE(Assumptions!$C$10,1),"mmm-yy") | E5: =TEXT(EDATE(Assumptions!$C$10,2),"mmm-yy") | F5: =TEXT(EDATE(Assumptions!$C$10,3),"mmm-yy") | G5: =TEXT(EDATE(Assumptions!$C$10,4),"mmm-yy") | H5: =TEXT(EDATE(Assumptions!$C$10,5),"mmm-yy") | I5: =TEXT(EDATE(Assumptions!$C$10,6),"mmm-yy") | J5: =TEXT(EDATE(Assumptions!$C$10,7),"mmm-yy") | K5: =TEXT(EDATE(Assumptions!$C$10,8),"mmm-yy") | L5: =TEXT(EDATE(Assumptions!$C$10,9),"mmm-yy") | M5: =TEXT(EDATE(Assumptions!$C$10,10),"mmm-yy") | N5: =TEXT(EDATE(Assumptions!$C$10,11),"mmm-yy") | O5: =TEXT(EDATE(Assumptions!$C$10,12),"mmm-yy") | P5: =TEXT(EDATE(Assumptions!$C$10,13),"mmm-yy") | Q5: =TEXT(EDATE(Assumptions!$C$10,14),"mmm-yy") | R5: =TEXT(EDATE(Assumptions!$C$10,15),"mmm-yy") | S5: =TEXT(EDATE(Assumptions!$C$10,16),"mmm-yy") | T5: =TEXT(EDATE(Assumptions!$C$10,17),"mmm-yy") | U5: =TEXT(EDATE(Assumptions!$C$10,18),"mmm-yy") | V5: =TEXT(EDATE(Assumptions!$C$10,19),"mmm-yy") | W5: =TEXT(EDATE(Assumptions!$C$10,20),"mmm-yy") | X5: =TEXT(EDATE(Assumptions!$C$10,21),"mmm-yy") | Y5: =TEXT(EDATE(Assumptions!$C$10,22),"mmm-yy") | Z5: =TEXT(EDATE(Assumptions!$C$10,23),"mmm-yy") | AA5: =TEXT(EDATE(Assumptions!$C$10,24),"mmm-yy") | AB5: =TEXT(EDATE(Assumptions!$C$10,25),"mmm-yy") | AC5: =TEXT(EDATE(Assumptions!$C$10,26),"mmm-yy") | AD5: =TEXT(EDATE(Assumptions!$C$10,27),"mmm-yy") | AE5: =TEXT(EDATE(Assumptions!$C$10,28),"mmm-yy") | AF5: =TEXT(EDATE(Assumptions!$C$10,29),"mmm-yy") | AG5: =TEXT(EDATE(Assumptions!$C$10,30),"mmm-yy") | AH5: =TEXT(EDATE(Assumptions!$C$10,31),"mmm-yy") | AI5: =TEXT(EDATE(Assumptions!$C$10,32),"mmm-yy") | AJ5: =TEXT(EDATE(Assumptions!$C$10,33),"mmm-yy") | AK5: =TEXT(EDATE(Assumptions!$C$10,34),"mmm-yy") | AL5: =TEXT(EDATE(Assumptions!$C$10,35),"mmm-yy") | AM5: =TEXT(EDATE(Assumptions!$C$10,36),"mmm-yy") | AN5: =TEXT(EDATE(Assumptions!$C$10,37),"mmm-yy")
B6: Month number | C6: 1 | D6: 2 | E6: 3 | F6: 4 | G6: 5 | H6: 6 | I6: 7 | J6: 8 | K6: 9 | L6: 10 | M6: 11 | N6: 12 | O6: 13 | P6: 14 | Q6: 15 | R6: 16 | S6: 17 | T6: 18 | U6: 19 | V6: 20 | W6: 21 | X6: 22 | Y6: 23 | Z6: 24 | AA6: 25 | AB6: 26 | AC6: 27 | AD6: 28 | AE6: 29 | AF6: 30 | AG6: 31 | AH6: 32 | AI6: 33 | AJ6: 34 | AK6: 35 | AL6: 36 | AM6: 37 | AN6: 38
A7: =Teams!A5 | B7: =Teams!C5&" — "&Teams!B5 | C7: =IF(OR(C$6<Teams!$F5,C$6>Teams!$I5),0,IF(C$6<Teams!$G5,ROUND(Teams!$E5*(C$6-Teams!$F5+1)/(Teams!$G5-Teams!$F5+1),0),IF(C$6<=Teams!$H5,Teams!$E5,ROUND(Teams!$E5*(Teams!$I5-C$6+1)/(Teams!$I5-Teams!$H5),0)))) | D7: =IF(OR(D$6<Teams!$F5,D$6>Teams!$I5),0,IF(D$6<Teams!$G5,ROUND(Teams!$E5*(D$6-Teams!$F5+1)/(Teams!$G5-Teams!$F5+1),0),IF(D$6<=Teams!$H5,Teams!$E5,ROUND(Teams!$E5*(Teams!$I5-D$6+1)/(Teams!$I5-Teams!$H5),0)))) | E7: =IF(OR(E$6<Teams!$F5,E$6>Teams!$I5),0,IF(E$6<Teams!$G5,ROUND(Teams!$E5*(E$6-Teams!$F5+1)/(Teams!$G5-Teams!$F5+1),0),IF(E$6<=Teams!$H5,Teams!$E5,ROUND(Teams!$E5*(Teams!$I5-E$6+1)/(Teams!$I5-Teams!$H5),0)))) | F7: =IF(OR(F$6<Teams!$F5,F$6>Teams!$I5),0,IF(F$6<Teams!$G5,ROUND(Teams!$E5*(F$6-Teams!$F5+1)/(Teams!$G5-Teams!$F5+1),0),IF(F$6<=Teams!$H5,Teams!$E5,ROUND(Teams!$E5*(Teams!$I5-F$6+1)/(Teams!$I5-Teams!$H5),0)))) | G7: =IF(OR(G$6<Teams!$F5,G$6>Teams!$I5),0,IF(G$6<Teams!$G5,ROUND(Teams!$E5*(G$6-Teams!$F5+1)/(Teams!$G5-Teams!$F5+1),0),IF(G$6<=Teams!$H5,Teams!$E5,ROUND(Teams!$E5*(Teams!$I5-G$6+1)/(Teams!$I5-Teams!$H5),0)))) | H7: =IF(OR(H$6<Teams!$F5,H$6>Teams!$I5),0,IF(H$6<Teams!$G5,ROUND(Teams!$E5*(H$6-Teams!$F5+1)/(Teams!$G5-Teams!$F5+1),0),IF(H$6<=Teams!$H5,Teams!$E5,ROUND(Teams!$E5*(Teams!$I5-H$6+1)/(Teams!$I5-Teams!$H5),0)))) | I7: =IF(OR(I$6<Teams!$F5,I$6>Teams!$I5),0,IF(I$6<Teams!$G5,ROUND(Teams!$E5*(I$6-Teams!$F5+1)/(Teams!$G5-Teams!$F5+1),0),IF(I$6<=Teams!$H5,Teams!$E5,ROUND(Teams!$E5*(Teams!$I5-I$6+1)/(Teams!$I5-Teams!$H5),0)))) | J7: =IF(OR(J$6<Teams!$F5,J$6>Teams!$I5),0,IF(J$6<Teams!$G5,ROUND(Teams!$E5*(J$6-Teams!$F5+1)/(Teams!$G5-Teams!$F5+1),0),IF(J$6<=Teams!$H5,Teams!$E5,ROUND(Teams!$E5*(Teams!$I5-J$6+1)/(Teams!$I5-Teams!$H5),0)))) | ... AN7: =IF(OR(AN$6<Teams!$F5,AN$6>Teams!$I5),0,IF(AN$6<Teams!$G5,ROUND(Teams!$E5*(AN$6-Teams!$F5+1)/(Teams!$G5-Teams!$F5+1),0),IF(AN$6<=Teams!$H5,Teams!$E5,ROUND(Teams!$E5*(Teams!$I5-AN$6+1)/(Teams!$I5-Teams!$H5),0))))
A8: =Teams!A6 | B8: =Teams!C6&" — "&Teams!B6 | C8: =IF(OR(C$6<Teams!$F6,C$6>Teams!$I6),0,IF(C$6<Teams!$G6,ROUND(Teams!$E6*(C$6-Teams!$F6+1)/(Teams!$G6-Teams!$F6+1),0),IF(C$6<=Teams!$H6,Teams!$E6,ROUND(Teams!$E6*(Teams!$I6-C$6+1)/(Teams!$I6-Teams!$H6),0)))) | D8: =IF(OR(D$6<Teams!$F6,D$6>Teams!$I6),0,IF(D$6<Teams!$G6,ROUND(Teams!$E6*(D$6-Teams!$F6+1)/(Teams!$G6-Teams!$F6+1),0),IF(D$6<=Teams!$H6,Teams!$E6,ROUND(Teams!$E6*(Teams!$I6-D$6+1)/(Teams!$I6-Teams!$H6),0)))) | E8: =IF(OR(E$6<Teams!$F6,E$6>Teams!$I6),0,IF(E$6<Teams!$G6,ROUND(Teams!$E6*(E$6-Teams!$F6+1)/(Teams!$G6-Teams!$F6+1),0),IF(E$6<=Teams!$H6,Teams!$E6,ROUND(Teams!$E6*(Teams!$I6-E$6+1)/(Teams!$I6-Teams!$H6),0)))) | F8: =IF(OR(F$6<Teams!$F6,F$6>Teams!$I6),0,IF(F$6<Teams!$G6,ROUND(Teams!$E6*(F$6-Teams!$F6+1)/(Teams!$G6-Teams!$F6+1),0),IF(F$6<=Teams!$H6,Teams!$E6,ROUND(Teams!$E6*(Teams!$I6-F$6+1)/(Teams!$I6-Teams!$H6),0)))) | G8: =IF(OR(G$6<Teams!$F6,G$6>Teams!$I6),0,IF(G$6<Teams!$G6,ROUND(Teams!$E6*(G$6-Teams!$F6+1)/(Teams!$G6-Teams!$F6+1),0),IF(G$6<=Teams!$H6,Teams!$E6,ROUND(Teams!$E6*(Teams!$I6-G$6+1)/(Teams!$I6-Teams!$H6),0)))) | H8: =IF(OR(H$6<Teams!$F6,H$6>Teams!$I6),0,IF(H$6<Teams!$G6,ROUND(Teams!$E6*(H$6-Teams!$F6+1)/(Teams!$G6-Teams!$F6+1),0),IF(H$6<=Teams!$H6,Teams!$E6,ROUND(Teams!$E6*(Teams!$I6-H$6+1)/(Teams!$I6-Teams!$H6),0)))) | I8: =IF(OR(I$6<Teams!$F6,I$6>Teams!$I6),0,IF(I$6<Teams!$G6,ROUND(Teams!$E6*(I$6-Teams!$F6+1)/(Teams!$G6-Teams!$F6+1),0),IF(I$6<=Teams!$H6,Teams!$E6,ROUND(Teams!$E6*(Teams!$I6-I$6+1)/(Teams!$I6-Teams!$H6),0)))) | J8: =IF(OR(J$6<Teams!$F6,J$6>Teams!$I6),0,IF(J$6<Teams!$G6,ROUND(Teams!$E6*(J$6-Teams!$F6+1)/(Teams!$G6-Teams!$F6+1),0),IF(J$6<=Teams!$H6,Teams!$E6,ROUND(Teams!$E6*(Teams!$I6-J$6+1)/(Teams!$I6-Teams!$H6),0)))) | ... AN8: =IF(OR(AN$6<Teams!$F6,AN$6>Teams!$I6),0,IF(AN$6<Teams!$G6,ROUND(Teams!$E6*(AN$6-Teams!$F6+1)/(Teams!$G6-Teams!$F6+1),0),IF(AN$6<=Teams!$H6,Teams!$E6,ROUND(Teams!$E6*(Teams!$I6-AN$6+1)/(Teams!$I6-Teams!$H6),0))))
A9: =Teams!A7 | B9: =Teams!C7&" — "&Teams!B7 | C9: =IF(OR(C$6<Teams!$F7,C$6>Teams!$I7),0,IF(C$6<Teams!$G7,ROUND(Teams!$E7*(C$6-Teams!$F7+1)/(Teams!$G7-Teams!$F7+1),0),IF(C$6<=Teams!$H7,Teams!$E7,ROUND(Teams!$E7*(Teams!$I7-C$6+1)/(Teams!$I7-Teams!$H7),0)))) | D9: =IF(OR(D$6<Teams!$F7,D$6>Teams!$I7),0,IF(D$6<Teams!$G7,ROUND(Teams!$E7*(D$6-Teams!$F7+1)/(Teams!$G7-Teams!$F7+1),0),IF(D$6<=Teams!$H7,Teams!$E7,ROUND(Teams!$E7*(Teams!$I7-D$6+1)/(Teams!$I7-Teams!$H7),0)))) | E9: =IF(OR(E$6<Teams!$F7,E$6>Teams!$I7),0,IF(E$6<Teams!$G7,ROUND(Teams!$E7*(E$6-Teams!$F7+1)/(Teams!$G7-Teams!$F7+1),0),IF(E$6<=Teams!$H7,Teams!$E7,ROUND(Teams!$E7*(Teams!$I7-E$6+1)/(Teams!$I7-Teams!$H7),0)))) | F9: =IF(OR(F$6<Teams!$F7,F$6>Teams!$I7),0,IF(F$6<Teams!$G7,ROUND(Teams!$E7*(F$6-Teams!$F7+1)/(Teams!$G7-Teams!$F7+1),0),IF(F$6<=Teams!$H7,Teams!$E7,ROUND(Teams!$E7*(Teams!$I7-F$6+1)/(Teams!$I7-Teams!$H7),0)))) | G9: =IF(OR(G$6<Teams!$F7,G$6>Teams!$I7),0,IF(G$6<Teams!$G7,ROUND(Teams!$E7*(G$6-Teams!$F7+1)/(Teams!$G7-Teams!$F7+1),0),IF(G$6<=Teams!$H7,Teams!$E7,ROUND(Teams!$E7*(Teams!$I7-G$6+1)/(Teams!$I7-Teams!$H7),0)))) | H9: =IF(OR(H$6<Teams!$F7,H$6>Teams!$I7),0,IF(H$6<Teams!$G7,ROUND(Teams!$E7*(H$6-Teams!$F7+1)/(Teams!$G7-Teams!$F7+1),0),IF(H$6<=Teams!$H7,Teams!$E7,ROUND(Teams!$E7*(Teams!$I7-H$6+1)/(Teams!$I7-Teams!$H7),0)))) | I9: =IF(OR(I$6<Teams!$F7,I$6>Teams!$I7),0,IF(I$6<Teams!$G7,ROUND(Teams!$E7*(I$6-Teams!$F7+1)/(Teams!$G7-Teams!$F7+1),0),IF(I$6<=Teams!$H7,Teams!$E7,ROUND(Teams!$E7*(Teams!$I7-I$6+1)/(Teams!$I7-Teams!$H7),0)))) | J9: =IF(OR(J$6<Teams!$F7,J$6>Teams!$I7),0,IF(J$6<Teams!$G7,ROUND(Teams!$E7*(J$6-Teams!$F7+1)/(Teams!$G7-Teams!$F7+1),0),IF(J$6<=Teams!$H7,Teams!$E7,ROUND(Teams!$E7*(Teams!$I7-J$6+1)/(Teams!$I7-Teams!$H7),0)))) | ... AN9: =IF(OR(AN$6<Teams!$F7,AN$6>Teams!$I7),0,IF(AN$6<Teams!$G7,ROUND(Teams!$E7*(AN$6-Teams!$F7+1)/(Teams!$G7-Teams!$F7+1),0),IF(AN$6<=Teams!$H7,Teams!$E7,ROUND(Teams!$E7*(Teams!$I7-AN$6+1)/(Teams!$I7-Teams!$H7),0))))
A10: =Teams!A8 | B10: =Teams!C8&" — "&Teams!B8 | C10: =IF(OR(C$6<Teams!$F8,C$6>Teams!$I8),0,IF(C$6<Teams!$G8,ROUND(Teams!$E8*(C$6-Teams!$F8+1)/(Teams!$G8-Teams!$F8+1),0),IF(C$6<=Teams!$H8,Teams!$E8,ROUND(Teams!$E8*(Teams!$I8-C$6+1)/(Teams!$I8-Teams!$H8),0)))) | D10: =IF(OR(D$6<Teams!$F8,D$6>Teams!$I8),0,IF(D$6<Teams!$G8,ROUND(Teams!$E8*(D$6-Teams!$F8+1)/(Teams!$G8-Teams!$F8+1),0),IF(D$6<=Teams!$H8,Teams!$E8,ROUND(Teams!$E8*(Teams!$I8-D$6+1)/(Teams!$I8-Teams!$H8),0)))) | E10: =IF(OR(E$6<Teams!$F8,E$6>Teams!$I8),0,IF(E$6<Teams!$G8,ROUND(Teams!$E8*(E$6-Teams!$F8+1)/(Teams!$G8-Teams!$F8+1),0),IF(E$6<=Teams!$H8,Teams!$E8,ROUND(Teams!$E8*(Teams!$I8-E$6+1)/(Teams!$I8-Teams!$H8),0)))) | F10: =IF(OR(F$6<Teams!$F8,F$6>Teams!$I8),0,IF(F$6<Teams!$G8,ROUND(Teams!$E8*(F$6-Teams!$F8+1)/(Teams!$G8-Teams!$F8+1),0),IF(F$6<=Teams!$H8,Teams!$E8,ROUND(Teams!$E8*(Teams!$I8-F$6+1)/(Teams!$I8-Teams!$H8),0)))) | G10: =IF(OR(G$6<Teams!$F8,G$6>Teams!$I8),0,IF(G$6<Teams!$G8,ROUND(Teams!$E8*(G$6-Teams!$F8+1)/(Teams!$G8-Teams!$F8+1),0),IF(G$6<=Teams!$H8,Teams!$E8,ROUND(Teams!$E8*(Teams!$I8-G$6+1)/(Teams!$I8-Teams!$H8),0)))) | H10: =IF(OR(H$6<Teams!$F8,H$6>Teams!$I8),0,IF(H$6<Teams!$G8,ROUND(Teams!$E8*(H$6-Teams!$F8+1)/(Teams!$G8-Teams!$F8+1),0),IF(H$6<=Teams!$H8,Teams!$E8,ROUND(Teams!$E8*(Teams!$I8-H$6+1)/(Teams!$I8-Teams!$H8),0)))) | I10: =IF(OR(I$6<Teams!$F8,I$6>Teams!$I8),0,IF(I$6<Teams!$G8,ROUND(Teams!$E8*(I$6-Teams!$F8+1)/(Teams!$G8-Teams!$F8+1),0),IF(I$6<=Teams!$H8,Teams!$E8,ROUND(Teams!$E8*(Teams!$I8-I$6+1)/(Teams!$I8-Teams!$H8),0)))) | J10: =IF(OR(J$6<Teams!$F8,J$6>Teams!$I8),0,IF(J$6<Teams!$G8,ROUND(Teams!$E8*(J$6-Teams!$F8+1)/(Teams!$G8-Teams!$F8+1),0),IF(J$6<=Teams!$H8,Teams!$E8,ROUND(Teams!$E8*(Teams!$I8-J$6+1)/(Teams!$I8-Teams!$H8),0)))) | ... AN10: =IF(OR(AN$6<Teams!$F8,AN$6>Teams!$I8),0,IF(AN$6<Teams!$G8,ROUND(Teams!$E8*(AN$6-Teams!$F8+1)/(Teams!$G8-Teams!$F8+1),0),IF(AN$6<=Teams!$H8,Teams!$E8,ROUND(Teams!$E8*(Teams!$I8-AN$6+1)/(Teams!$I8-Teams!$H8),0))))
A11: =Teams!A9 | B11: =Teams!C9&" — "&Teams!B9 | C11: =IF(OR(C$6<Teams!$F9,C$6>Teams!$I9),0,IF(C$6<Teams!$G9,ROUND(Teams!$E9*(C$6-Teams!$F9+1)/(Teams!$G9-Teams!$F9+1),0),IF(C$6<=Teams!$H9,Teams!$E9,ROUND(Teams!$E9*(Teams!$I9-C$6+1)/(Teams!$I9-Teams!$H9),0)))) | D11: =IF(OR(D$6<Teams!$F9,D$6>Teams!$I9),0,IF(D$6<Teams!$G9,ROUND(Teams!$E9*(D$6-Teams!$F9+1)/(Teams!$G9-Teams!$F9+1),0),IF(D$6<=Teams!$H9,Teams!$E9,ROUND(Teams!$E9*(Teams!$I9-D$6+1)/(Teams!$I9-Teams!$H9),0)))) | E11: =IF(OR(E$6<Teams!$F9,E$6>Teams!$I9),0,IF(E$6<Teams!$G9,ROUND(Teams!$E9*(E$6-Teams!$F9+1)/(Teams!$G9-Teams!$F9+1),0),IF(E$6<=Teams!$H9,Teams!$E9,ROUND(Teams!$E9*(Teams!$I9-E$6+1)/(Teams!$I9-Teams!$H9),0)))) | F11: =IF(OR(F$6<Teams!$F9,F$6>Teams!$I9),0,IF(F$6<Teams!$G9,ROUND(Teams!$E9*(F$6-Teams!$F9+1)/(Teams!$G9-Teams!$F9+1),0),IF(F$6<=Teams!$H9,Teams!$E9,ROUND(Teams!$E9*(Teams!$I9-F$6+1)/(Teams!$I9-Teams!$H9),0)))) | G11: =IF(OR(G$6<Teams!$F9,G$6>Teams!$I9),0,IF(G$6<Teams!$G9,ROUND(Teams!$E9*(G$6-Teams!$F9+1)/(Teams!$G9-Teams!$F9+1),0),IF(G$6<=Teams!$H9,Teams!$E9,ROUND(Teams!$E9*(Teams!$I9-G$6+1)/(Teams!$I9-Teams!$H9),0)))) | H11: =IF(OR(H$6<Teams!$F9,H$6>Teams!$I9),0,IF(H$6<Teams!$G9,ROUND(Teams!$E9*(H$6-Teams!$F9+1)/(Teams!$G9-Teams!$F9+1),0),IF(H$6<=Teams!$H9,Teams!$E9,ROUND(Teams!$E9*(Teams!$I9-H$6+1)/(Teams!$I9-Teams!$H9),0)))) | I11: =IF(OR(I$6<Teams!$F9,I$6>Teams!$I9),0,IF(I$6<Teams!$G9,ROUND(Teams!$E9*(I$6-Teams!$F9+1)/(Teams!$G9-Teams!$F9+1),0),IF(I$6<=Teams!$H9,Teams!$E9,ROUND(Teams!$E9*(Teams!$I9-I$6+1)/(Teams!$I9-Teams!$H9),0)))) | J11: =IF(OR(J$6<Teams!$F9,J$6>Teams!$I9),0,IF(J$6<Teams!$G9,ROUND(Teams!$E9*(J$6-Teams!$F9+1)/(Teams!$G9-Teams!$F9+1),0),IF(J$6<=Teams!$H9,Teams!$E9,ROUND(Teams!$E9*(Teams!$I9-J$6+1)/(Teams!$I9-Teams!$H9),0)))) | ... AN11: =IF(OR(AN$6<Teams!$F9,AN$6>Teams!$I9),0,IF(AN$6<Teams!$G9,ROUND(Teams!$E9*(AN$6-Teams!$F9+1)/(Teams!$G9-Teams!$F9+1),0),IF(AN$6<=Teams!$H9,Teams!$E9,ROUND(Teams!$E9*(Teams!$I9-AN$6+1)/(Teams!$I9-Teams!$H9),0))))
A12: =Teams!A10 | B12: =Teams!C10&" — "&Teams!B10 | C12: =IF(OR(C$6<Teams!$F10,C$6>Teams!$I10),0,IF(C$6<Teams!$G10,ROUND(Teams!$E10*(C$6-Teams!$F10+1)/(Teams!$G10-Teams!$F10+1),0),IF(C$6<=Teams!$H10,Teams!$E10,ROUND(Teams!$E10*(Teams!$I10-C$6+1)/(Teams!$I10-Teams!$H10),0)))) | D12: =IF(OR(D$6<Teams!$F10,D$6>Teams!$I10),0,IF(D$6<Teams!$G10,ROUND(Teams!$E10*(D$6-Teams!$F10+1)/(Teams!$G10-Teams!$F10+1),0),IF(D$6<=Teams!$H10,Teams!$E10,ROUND(Teams!$E10*(Teams!$I10-D$6+1)/(Teams!$I10-Teams!$H10),0)))) | E12: =IF(OR(E$6<Teams!$F10,E$6>Teams!$I10),0,IF(E$6<Teams!$G10,ROUND(Teams!$E10*(E$6-Teams!$F10+1)/(Teams!$G10-Teams!$F10+1),0),IF(E$6<=Teams!$H10,Teams!$E10,ROUND(Teams!$E10*(Teams!$I10-E$6+1)/(Teams!$I10-Teams!$H10),0)))) | F12: =IF(OR(F$6<Teams!$F10,F$6>Teams!$I10),0,IF(F$6<Teams!$G10,ROUND(Teams!$E10*(F$6-Teams!$F10+1)/(Teams!$G10-Teams!$F10+1),0),IF(F$6<=Teams!$H10,Teams!$E10,ROUND(Teams!$E10*(Teams!$I10-F$6+1)/(Teams!$I10-Teams!$H10),0)))) | G12: =IF(OR(G$6<Teams!$F10,G$6>Teams!$I10),0,IF(G$6<Teams!$G10,ROUND(Teams!$E10*(G$6-Teams!$F10+1)/(Teams!$G10-Teams!$F10+1),0),IF(G$6<=Teams!$H10,Teams!$E10,ROUND(Teams!$E10*(Teams!$I10-G$6+1)/(Teams!$I10-Teams!$H10),0)))) | H12: =IF(OR(H$6<Teams!$F10,H$6>Teams!$I10),0,IF(H$6<Teams!$G10,ROUND(Teams!$E10*(H$6-Teams!$F10+1)/(Teams!$G10-Teams!$F10+1),0),IF(H$6<=Teams!$H10,Teams!$E10,ROUND(Teams!$E10*(Teams!$I10-H$6+1)/(Teams!$I10-Teams!$H10),0)))) | I12: =IF(OR(I$6<Teams!$F10,I$6>Teams!$I10),0,IF(I$6<Teams!$G10,ROUND(Teams!$E10*(I$6-Teams!$F10+1)/(Teams!$G10-Teams!$F10+1),0),IF(I$6<=Teams!$H10,Teams!$E10,ROUND(Teams!$E10*(Teams!$I10-I$6+1)/(Teams!$I10-Teams!$H10),0)))) | J12: =IF(OR(J$6<Teams!$F10,J$6>Teams!$I10),0,IF(J$6<Teams!$G10,ROUND(Teams!$E10*(J$6-Teams!$F10+1)/(Teams!$G10-Teams!$F10+1),0),IF(J$6<=Teams!$H10,Teams!$E10,ROUND(Teams!$E10*(Teams!$I10-J$6+1)/(Teams!$I10-Teams!$H10),0)))) | ... AN12: =IF(OR(AN$6<Teams!$F10,AN$6>Teams!$I10),0,IF(AN$6<Teams!$G10,ROUND(Teams!$E10*(AN$6-Teams!$F10+1)/(Teams!$G10-Teams!$F10+1),0),IF(AN$6<=Teams!$H10,Teams!$E10,ROUND(Teams!$E10*(Teams!$I10-AN$6+1)/(Teams!$I10-Teams!$H10),0))))
A13: =Teams!A11 | B13: =Teams!C11&" — "&Teams!B11 | C13: =IF(OR(C$6<Teams!$F11,C$6>Teams!$I11),0,IF(C$6<Teams!$G11,ROUND(Teams!$E11*(C$6-Teams!$F11+1)/(Teams!$G11-Teams!$F11+1),0),IF(C$6<=Teams!$H11,Teams!$E11,ROUND(Teams!$E11*(Teams!$I11-C$6+1)/(Teams!$I11-Teams!$H11),0)))) | D13: =IF(OR(D$6<Teams!$F11,D$6>Teams!$I11),0,IF(D$6<Teams!$G11,ROUND(Teams!$E11*(D$6-Teams!$F11+1)/(Teams!$G11-Teams!$F11+1),0),IF(D$6<=Teams!$H11,Teams!$E11,ROUND(Teams!$E11*(Teams!$I11-D$6+1)/(Teams!$I11-Teams!$H11),0)))) | E13: =IF(OR(E$6<Teams!$F11,E$6>Teams!$I11),0,IF(E$6<Teams!$G11,ROUND(Teams!$E11*(E$6-Teams!$F11+1)/(Teams!$G11-Teams!$F11+1),0),IF(E$6<=Teams!$H11,Teams!$E11,ROUND(Teams!$E11*(Teams!$I11-E$6+1)/(Teams!$I11-Teams!$H11),0)))) | F13: =IF(OR(F$6<Teams!$F11,F$6>Teams!$I11),0,IF(F$6<Teams!$G11,ROUND(Teams!$E11*(F$6-Teams!$F11+1)/(Teams!$G11-Teams!$F11+1),0),IF(F$6<=Teams!$H11,Teams!$E11,ROUND(Teams!$E11*(Teams!$I11-F$6+1)/(Teams!$I11-Teams!$H11),0)))) | G13: =IF(OR(G$6<Teams!$F11,G$6>Teams!$I11),0,IF(G$6<Teams!$G11,ROUND(Teams!$E11*(G$6-Teams!$F11+1)/(Teams!$G11-Teams!$F11+1),0),IF(G$6<=Teams!$H11,Teams!$E11,ROUND(Teams!$E11*(Teams!$I11-G$6+1)/(Teams!$I11-Teams!$H11),0)))) | H13: =IF(OR(H$6<Teams!$F11,H$6>Teams!$I11),0,IF(H$6<Teams!$G11,ROUND(Teams!$E11*(H$6-Teams!$F11+1)/(Teams!$G11-Teams!$F11+1),0),IF(H$6<=Teams!$H11,Teams!$E11,ROUND(Teams!$E11*(Teams!$I11-H$6+1)/(Teams!$I11-Teams!$H11),0)))) | I13: =IF(OR(I$6<Teams!$F11,I$6>Teams!$I11),0,IF(I$6<Teams!$G11,ROUND(Teams!$E11*(I$6-Teams!$F11+1)/(Teams!$G11-Teams!$F11+1),0),IF(I$6<=Teams!$H11,Teams!$E11,ROUND(Teams!$E11*(Teams!$I11-I$6+1)/(Teams!$I11-Teams!$H11),0)))) | J13: =IF(OR(J$6<Teams!$F11,J$6>Teams!$I11),0,IF(J$6<Teams!$G11,ROUND(Teams!$E11*(J$6-Teams!$F11+1)/(Teams!$G11-Teams!$F11+1),0),IF(J$6<=Teams!$H11,Teams!$E11,ROUND(Teams!$E11*(Teams!$I11-J$6+1)/(Teams!$I11-Teams!$H11),0)))) | ... AN13: =IF(OR(AN$6<Teams!$F11,AN$6>Teams!$I11),0,IF(AN$6<Teams!$G11,ROUND(Teams!$E11*(AN$6-Teams!$F11+1)/(Teams!$G11-Teams!$F11+1),0),IF(AN$6<=Teams!$H11,Teams!$E11,ROUND(Teams!$E11*(Teams!$I11-AN$6+1)/(Teams!$I11-Teams!$H11),0))))
A14: =Teams!A12 | B14: =Teams!C12&" — "&Teams!B12 | C14: =IF(OR(C$6<Teams!$F12,C$6>Teams!$I12),0,IF(C$6<Teams!$G12,ROUND(Teams!$E12*(C$6-Teams!$F12+1)/(Teams!$G12-Teams!$F12+1),0),IF(C$6<=Teams!$H12,Teams!$E12,ROUND(Teams!$E12*(Teams!$I12-C$6+1)/(Teams!$I12-Teams!$H12),0)))) | D14: =IF(OR(D$6<Teams!$F12,D$6>Teams!$I12),0,IF(D$6<Teams!$G12,ROUND(Teams!$E12*(D$6-Teams!$F12+1)/(Teams!$G12-Teams!$F12+1),0),IF(D$6<=Teams!$H12,Teams!$E12,ROUND(Teams!$E12*(Teams!$I12-D$6+1)/(Teams!$I12-Teams!$H12),0)))) | E14: =IF(OR(E$6<Teams!$F12,E$6>Teams!$I12),0,IF(E$6<Teams!$G12,ROUND(Teams!$E12*(E$6-Teams!$F12+1)/(Teams!$G12-Teams!$F12+1),0),IF(E$6<=Teams!$H12,Teams!$E12,ROUND(Teams!$E12*(Teams!$I12-E$6+1)/(Teams!$I12-Teams!$H12),0)))) | F14: =IF(OR(F$6<Teams!$F12,F$6>Teams!$I12),0,IF(F$6<Teams!$G12,ROUND(Teams!$E12*(F$6-Teams!$F12+1)/(Teams!$G12-Teams!$F12+1),0),IF(F$6<=Teams!$H12,Teams!$E12,ROUND(Teams!$E12*(Teams!$I12-F$6+1)/(Teams!$I12-Teams!$H12),0)))) | G14: =IF(OR(G$6<Teams!$F12,G$6>Teams!$I12),0,IF(G$6<Teams!$G12,ROUND(Teams!$E12*(G$6-Teams!$F12+1)/(Teams!$G12-Teams!$F12+1),0),IF(G$6<=Teams!$H12,Teams!$E12,ROUND(Teams!$E12*(Teams!$I12-G$6+1)/(Teams!$I12-Teams!$H12),0)))) | H14: =IF(OR(H$6<Teams!$F12,H$6>Teams!$I12),0,IF(H$6<Teams!$G12,ROUND(Teams!$E12*(H$6-Teams!$F12+1)/(Teams!$G12-Teams!$F12+1),0),IF(H$6<=Teams!$H12,Teams!$E12,ROUND(Teams!$E12*(Teams!$I12-H$6+1)/(Teams!$I12-Teams!$H12),0)))) | I14: =IF(OR(I$6<Teams!$F12,I$6>Teams!$I12),0,IF(I$6<Teams!$G12,ROUND(Teams!$E12*(I$6-Teams!$F12+1)/(Teams!$G12-Teams!$F12+1),0),IF(I$6<=Teams!$H12,Teams!$E12,ROUND(Teams!$E12*(Teams!$I12-I$6+1)/(Teams!$I12-Teams!$H12),0)))) | J14: =IF(OR(J$6<Teams!$F12,J$6>Teams!$I12),0,IF(J$6<Teams!$G12,ROUND(Teams!$E12*(J$6-Teams!$F12+1)/(Teams!$G12-Teams!$F12+1),0),IF(J$6<=Teams!$H12,Teams!$E12,ROUND(Teams!$E12*(Teams!$I12-J$6+1)/(Teams!$I12-Teams!$H12),0)))) | ... AN14: =IF(OR(AN$6<Teams!$F12,AN$6>Teams!$I12),0,IF(AN$6<Teams!$G12,ROUND(Teams!$E12*(AN$6-Teams!$F12+1)/(Teams!$G12-Teams!$F12+1),0),IF(AN$6<=Teams!$H12,Teams!$E12,ROUND(Teams!$E12*(Teams!$I12-AN$6+1)/(Teams!$I12-Teams!$H12),0))))
A15: =Teams!A13 | B15: =Teams!C13&" — "&Teams!B13 | C15: =IF(OR(C$6<Teams!$F13,C$6>Teams!$I13),0,IF(C$6<Teams!$G13,ROUND(Teams!$E13*(C$6-Teams!$F13+1)/(Teams!$G13-Teams!$F13+1),0),IF(C$6<=Teams!$H13,Teams!$E13,ROUND(Teams!$E13*(Teams!$I13-C$6+1)/(Teams!$I13-Teams!$H13),0)))) | D15: =IF(OR(D$6<Teams!$F13,D$6>Teams!$I13),0,IF(D$6<Teams!$G13,ROUND(Teams!$E13*(D$6-Teams!$F13+1)/(Teams!$G13-Teams!$F13+1),0),IF(D$6<=Teams!$H13,Teams!$E13,ROUND(Teams!$E13*(Teams!$I13-D$6+1)/(Teams!$I13-Teams!$H13),0)))) | E15: =IF(OR(E$6<Teams!$F13,E$6>Teams!$I13),0,IF(E$6<Teams!$G13,ROUND(Teams!$E13*(E$6-Teams!$F13+1)/(Teams!$G13-Teams!$F13+1),0),IF(E$6<=Teams!$H13,Teams!$E13,ROUND(Teams!$E13*(Teams!$I13-E$6+1)/(Teams!$I13-Teams!$H13),0)))) | F15: =IF(OR(F$6<Teams!$F13,F$6>Teams!$I13),0,IF(F$6<Teams!$G13,ROUND(Teams!$E13*(F$6-Teams!$F13+1)/(Teams!$G13-Teams!$F13+1),0),IF(F$6<=Teams!$H13,Teams!$E13,ROUND(Teams!$E13*(Teams!$I13-F$6+1)/(Teams!$I13-Teams!$H13),0)))) | G15: =IF(OR(G$6<Teams!$F13,G$6>Teams!$I13),0,IF(G$6<Teams!$G13,ROUND(Teams!$E13*(G$6-Teams!$F13+1)/(Teams!$G13-Teams!$F13+1),0),IF(G$6<=Teams!$H13,Teams!$E13,ROUND(Teams!$E13*(Teams!$I13-G$6+1)/(Teams!$I13-Teams!$H13),0)))) | H15: =IF(OR(H$6<Teams!$F13,H$6>Teams!$I13),0,IF(H$6<Teams!$G13,ROUND(Teams!$E13*(H$6-Teams!$F13+1)/(Teams!$G13-Teams!$F13+1),0),IF(H$6<=Teams!$H13,Teams!$E13,ROUND(Teams!$E13*(Teams!$I13-H$6+1)/(Teams!$I13-Teams!$H13),0)))) | I15: =IF(OR(I$6<Teams!$F13,I$6>Teams!$I13),0,IF(I$6<Teams!$G13,ROUND(Teams!$E13*(I$6-Teams!$F13+1)/(Teams!$G13-Teams!$F13+1),0),IF(I$6<=Teams!$H13,Teams!$E13,ROUND(Teams!$E13*(Teams!$I13-I$6+1)/(Teams!$I13-Teams!$H13),0)))) | J15: =IF(OR(J$6<Teams!$F13,J$6>Teams!$I13),0,IF(J$6<Teams!$G13,ROUND(Teams!$E13*(J$6-Teams!$F13+1)/(Teams!$G13-Teams!$F13+1),0),IF(J$6<=Teams!$H13,Teams!$E13,ROUND(Teams!$E13*(Teams!$I13-J$6+1)/(Teams!$I13-Teams!$H13),0)))) | ... AN15: =IF(OR(AN$6<Teams!$F13,AN$6>Teams!$I13),0,IF(AN$6<Teams!$G13,ROUND(Teams!$E13*(AN$6-Teams!$F13+1)/(Teams!$G13-Teams!$F13+1),0),IF(AN$6<=Teams!$H13,Teams!$E13,ROUND(Teams!$E13*(Teams!$I13-AN$6+1)/(Teams!$I13-Teams!$H13),0))))
A16: =Teams!A14 | B16: =Teams!C14&" — "&Teams!B14 | C16: =IF(OR(C$6<Teams!$F14,C$6>Teams!$I14),0,IF(C$6<Teams!$G14,ROUND(Teams!$E14*(C$6-Teams!$F14+1)/(Teams!$G14-Teams!$F14+1),0),IF(C$6<=Teams!$H14,Teams!$E14,ROUND(Teams!$E14*(Teams!$I14-C$6+1)/(Teams!$I14-Teams!$H14),0)))) | D16: =IF(OR(D$6<Teams!$F14,D$6>Teams!$I14),0,IF(D$6<Teams!$G14,ROUND(Teams!$E14*(D$6-Teams!$F14+1)/(Teams!$G14-Teams!$F14+1),0),IF(D$6<=Teams!$H14,Teams!$E14,ROUND(Teams!$E14*(Teams!$I14-D$6+1)/(Teams!$I14-Teams!$H14),0)))) | E16: =IF(OR(E$6<Teams!$F14,E$6>Teams!$I14),0,IF(E$6<Teams!$G14,ROUND(Teams!$E14*(E$6-Teams!$F14+1)/(Teams!$G14-Teams!$F14+1),0),IF(E$6<=Teams!$H14,Teams!$E14,ROUND(Teams!$E14*(Teams!$I14-E$6+1)/(Teams!$I14-Teams!$H14),0)))) | F16: =IF(OR(F$6<Teams!$F14,F$6>Teams!$I14),0,IF(F$6<Teams!$G14,ROUND(Teams!$E14*(F$6-Teams!$F14+1)/(Teams!$G14-Teams!$F14+1),0),IF(F$6<=Teams!$H14,Teams!$E14,ROUND(Teams!$E14*(Teams!$I14-F$6+1)/(Teams!$I14-Teams!$H14),0)))) | G16: =IF(OR(G$6<Teams!$F14,G$6>Teams!$I14),0,IF(G$6<Teams!$G14,ROUND(Teams!$E14*(G$6-Teams!$F14+1)/(Teams!$G14-Teams!$F14+1),0),IF(G$6<=Teams!$H14,Teams!$E14,ROUND(Teams!$E14*(Teams!$I14-G$6+1)/(Teams!$I14-Teams!$H14),0)))) | H16: =IF(OR(H$6<Teams!$F14,H$6>Teams!$I14),0,IF(H$6<Teams!$G14,ROUND(Teams!$E14*(H$6-Teams!$F14+1)/(Teams!$G14-Teams!$F14+1),0),IF(H$6<=Teams!$H14,Teams!$E14,ROUND(Teams!$E14*(Teams!$I14-H$6+1)/(Teams!$I14-Teams!$H14),0)))) | I16: =IF(OR(I$6<Teams!$F14,I$6>Teams!$I14),0,IF(I$6<Teams!$G14,ROUND(Teams!$E14*(I$6-Teams!$F14+1)/(Teams!$G14-Teams!$F14+1),0),IF(I$6<=Teams!$H14,Teams!$E14,ROUND(Teams!$E14*(Teams!$I14-I$6+1)/(Teams!$I14-Teams!$H14),0)))) | J16: =IF(OR(J$6<Teams!$F14,J$6>Teams!$I14),0,IF(J$6<Teams!$G14,ROUND(Teams!$E14*(J$6-Teams!$F14+1)/(Teams!$G14-Teams!$F14+1),0),IF(J$6<=Teams!$H14,Teams!$E14,ROUND(Teams!$E14*(Teams!$I14-J$6+1)/(Teams!$I14-Teams!$H14),0)))) | ... AN16: =IF(OR(AN$6<Teams!$F14,AN$6>Teams!$I14),0,IF(AN$6<Teams!$G14,ROUND(Teams!$E14*(AN$6-Teams!$F14+1)/(Teams!$G14-Teams!$F14+1),0),IF(AN$6<=Teams!$H14,Teams!$E14,ROUND(Teams!$E14*(Teams!$I14-AN$6+1)/(Teams!$I14-Teams!$H14),0))))
A17: =Teams!A15 | B17: =Teams!C15&" — "&Teams!B15 | C17: =IF(OR(C$6<Teams!$F15,C$6>Teams!$I15),0,IF(C$6<Teams!$G15,ROUND(Teams!$E15*(C$6-Teams!$F15+1)/(Teams!$G15-Teams!$F15+1),0),IF(C$6<=Teams!$H15,Teams!$E15,ROUND(Teams!$E15*(Teams!$I15-C$6+1)/(Teams!$I15-Teams!$H15),0)))) | D17: =IF(OR(D$6<Teams!$F15,D$6>Teams!$I15),0,IF(D$6<Teams!$G15,ROUND(Teams!$E15*(D$6-Teams!$F15+1)/(Teams!$G15-Teams!$F15+1),0),IF(D$6<=Teams!$H15,Teams!$E15,ROUND(Teams!$E15*(Teams!$I15-D$6+1)/(Teams!$I15-Teams!$H15),0)))) | E17: =IF(OR(E$6<Teams!$F15,E$6>Teams!$I15),0,IF(E$6<Teams!$G15,ROUND(Teams!$E15*(E$6-Teams!$F15+1)/(Teams!$G15-Teams!$F15+1),0),IF(E$6<=Teams!$H15,Teams!$E15,ROUND(Teams!$E15*(Teams!$I15-E$6+1)/(Teams!$I15-Teams!$H15),0)))) | F17: =IF(OR(F$6<Teams!$F15,F$6>Teams!$I15),0,IF(F$6<Teams!$G15,ROUND(Teams!$E15*(F$6-Teams!$F15+1)/(Teams!$G15-Teams!$F15+1),0),IF(F$6<=Teams!$H15,Teams!$E15,ROUND(Teams!$E15*(Teams!$I15-F$6+1)/(Teams!$I15-Teams!$H15),0)))) | G17: =IF(OR(G$6<Teams!$F15,G$6>Teams!$I15),0,IF(G$6<Teams!$G15,ROUND(Teams!$E15*(G$6-Teams!$F15+1)/(Teams!$G15-Teams!$F15+1),0),IF(G$6<=Teams!$H15,Teams!$E15,ROUND(Teams!$E15*(Teams!$I15-G$6+1)/(Teams!$I15-Teams!$H15),0)))) | H17: =IF(OR(H$6<Teams!$F15,H$6>Teams!$I15),0,IF(H$6<Teams!$G15,ROUND(Teams!$E15*(H$6-Teams!$F15+1)/(Teams!$G15-Teams!$F15+1),0),IF(H$6<=Teams!$H15,Teams!$E15,ROUND(Teams!$E15*(Teams!$I15-H$6+1)/(Teams!$I15-Teams!$H15),0)))) | I17: =IF(OR(I$6<Teams!$F15,I$6>Teams!$I15),0,IF(I$6<Teams!$G15,ROUND(Teams!$E15*(I$6-Teams!$F15+1)/(Teams!$G15-Teams!$F15+1),0),IF(I$6<=Teams!$H15,Teams!$E15,ROUND(Teams!$E15*(Teams!$I15-I$6+1)/(Teams!$I15-Teams!$H15),0)))) | J17: =IF(OR(J$6<Teams!$F15,J$6>Teams!$I15),0,IF(J$6<Teams!$G15,ROUND(Teams!$E15*(J$6-Teams!$F15+1)/(Teams!$G15-Teams!$F15+1),0),IF(J$6<=Teams!$H15,Teams!$E15,ROUND(Teams!$E15*(Teams!$I15-J$6+1)/(Teams!$I15-Teams!$H15),0)))) | ... AN17: =IF(OR(AN$6<Teams!$F15,AN$6>Teams!$I15),0,IF(AN$6<Teams!$G15,ROUND(Teams!$E15*(AN$6-Teams!$F15+1)/(Teams!$G15-Teams!$F15+1),0),IF(AN$6<=Teams!$H15,Teams!$E15,ROUND(Teams!$E15*(Teams!$I15-AN$6+1)/(Teams!$I15-Teams!$H15),0))))
A18: =Teams!A16 | B18: =Teams!C16&" — "&Teams!B16 | C18: =IF(OR(C$6<Teams!$F16,C$6>Teams!$I16),0,IF(C$6<Teams!$G16,ROUND(Teams!$E16*(C$6-Teams!$F16+1)/(Teams!$G16-Teams!$F16+1),0),IF(C$6<=Teams!$H16,Teams!$E16,ROUND(Teams!$E16*(Teams!$I16-C$6+1)/(Teams!$I16-Teams!$H16),0)))) | D18: =IF(OR(D$6<Teams!$F16,D$6>Teams!$I16),0,IF(D$6<Teams!$G16,ROUND(Teams!$E16*(D$6-Teams!$F16+1)/(Teams!$G16-Teams!$F16+1),0),IF(D$6<=Teams!$H16,Teams!$E16,ROUND(Teams!$E16*(Teams!$I16-D$6+1)/(Teams!$I16-Teams!$H16),0)))) | E18: =IF(OR(E$6<Teams!$F16,E$6>Teams!$I16),0,IF(E$6<Teams!$G16,ROUND(Teams!$E16*(E$6-Teams!$F16+1)/(Teams!$G16-Teams!$F16+1),0),IF(E$6<=Teams!$H16,Teams!$E16,ROUND(Teams!$E16*(Teams!$I16-E$6+1)/(Teams!$I16-Teams!$H16),0)))) | F18: =IF(OR(F$6<Teams!$F16,F$6>Teams!$I16),0,IF(F$6<Teams!$G16,ROUND(Teams!$E16*(F$6-Teams!$F16+1)/(Teams!$G16-Teams!$F16+1),0),IF(F$6<=Teams!$H16,Teams!$E16,ROUND(Teams!$E16*(Teams!$I16-F$6+1)/(Teams!$I16-Teams!$H16),0)))) | G18: =IF(OR(G$6<Teams!$F16,G$6>Teams!$I16),0,IF(G$6<Teams!$G16,ROUND(Teams!$E16*(G$6-Teams!$F16+1)/(Teams!$G16-Teams!$F16+1),0),IF(G$6<=Teams!$H16,Teams!$E16,ROUND(Teams!$E16*(Teams!$I16-G$6+1)/(Teams!$I16-Teams!$H16),0)))) | H18: =IF(OR(H$6<Teams!$F16,H$6>Teams!$I16),0,IF(H$6<Teams!$G16,ROUND(Teams!$E16*(H$6-Teams!$F16+1)/(Teams!$G16-Teams!$F16+1),0),IF(H$6<=Teams!$H16,Teams!$E16,ROUND(Teams!$E16*(Teams!$I16-H$6+1)/(Teams!$I16-Teams!$H16),0)))) | I18: =IF(OR(I$6<Teams!$F16,I$6>Teams!$I16),0,IF(I$6<Teams!$G16,ROUND(Teams!$E16*(I$6-Teams!$F16+1)/(Teams!$G16-Teams!$F16+1),0),IF(I$6<=Teams!$H16,Teams!$E16,ROUND(Teams!$E16*(Teams!$I16-I$6+1)/(Teams!$I16-Teams!$H16),0)))) | J18: =IF(OR(J$6<Teams!$F16,J$6>Teams!$I16),0,IF(J$6<Teams!$G16,ROUND(Teams!$E16*(J$6-Teams!$F16+1)/(Teams!$G16-Teams!$F16+1),0),IF(J$6<=Teams!$H16,Teams!$E16,ROUND(Teams!$E16*(Teams!$I16-J$6+1)/(Teams!$I16-Teams!$H16),0)))) | ... AN18: =IF(OR(AN$6<Teams!$F16,AN$6>Teams!$I16),0,IF(AN$6<Teams!$G16,ROUND(Teams!$E16*(AN$6-Teams!$F16+1)/(Teams!$G16-Teams!$F16+1),0),IF(AN$6<=Teams!$H16,Teams!$E16,ROUND(Teams!$E16*(Teams!$I16-AN$6+1)/(Teams!$I16-Teams!$H16),0))))
... A28: =Teams!A26 | B28: =Teams!C26&" — "&Teams!B26 | C28: =IF(OR(C$6<Teams!$F26,C$6>Teams!$I26),0,IF(C$6<Teams!$G26,ROUND(Teams!$E26*(C$6-Teams!$F26+1)/(Teams!$G26-Teams!$F26+1),0),IF(C$6<=Teams!$H26,Teams!$E26,ROUND(Teams!$E26*(Teams!$I26-C$6+1)/(Teams!$I26-Teams!$H26),0)))) | D28: =IF(OR(D$6<Teams!$F26,D$6>Teams!$I26),0,IF(D$6<Teams!$G26,ROUND(Teams!$E26*(D$6-Teams!$F26+1)/(Teams!$G26-Teams!$F26+1),0),IF(D$6<=Teams!$H26,Teams!$E26,ROUND(Teams!$E26*(Teams!$I26-D$6+1)/(Teams!$I26-Teams!$H26),0)))) | E28: =IF(OR(E$6<Teams!$F26,E$6>Teams!$I26),0,IF(E$6<Teams!$G26,ROUND(Teams!$E26*(E$6-Teams!$F26+1)/(Teams!$G26-Teams!$F26+1),0),IF(E$6<=Teams!$H26,Teams!$E26,ROUND(Teams!$E26*(Teams!$I26-E$6+1)/(Teams!$I26-Teams!$H26),0)))) | F28: =IF(OR(F$6<Teams!$F26,F$6>Teams!$I26),0,IF(F$6<Teams!$G26,ROUND(Teams!$E26*(F$6-Teams!$F26+1)/(Teams!$G26-Teams!$F26+1),0),IF(F$6<=Teams!$H26,Teams!$E26,ROUND(Teams!$E26*(Teams!$I26-F$6+1)/(Teams!$I26-Teams!$H26),0)))) | G28: =IF(OR(G$6<Teams!$F26,G$6>Teams!$I26),0,IF(G$6<Teams!$G26,ROUND(Teams!$E26*(G$6-Teams!$F26+1)/(Teams!$G26-Teams!$F26+1),0),IF(G$6<=Teams!$H26,Teams!$E26,ROUND(Teams!$E26*(Teams!$I26-G$6+1)/(Teams!$I26-Teams!$H26),0)))) | H28: =IF(OR(H$6<Teams!$F26,H$6>Teams!$I26),0,IF(H$6<Teams!$G26,ROUND(Teams!$E26*(H$6-Teams!$F26+1)/(Teams!$G26-Teams!$F26+1),0),IF(H$6<=Teams!$H26,Teams!$E26,ROUND(Teams!$E26*(Teams!$I26-H$6+1)/(Teams!$I26-Teams!$H26),0)))) | I28: =IF(OR(I$6<Teams!$F26,I$6>Teams!$I26),0,IF(I$6<Teams!$G26,ROUND(Teams!$E26*(I$6-Teams!$F26+1)/(Teams!$G26-Teams!$F26+1),0),IF(I$6<=Teams!$H26,Teams!$E26,ROUND(Teams!$E26*(Teams!$I26-I$6+1)/(Teams!$I26-Teams!$H26),0)))) | J28: =IF(OR(J$6<Teams!$F26,J$6>Teams!$I26),0,IF(J$6<Teams!$G26,ROUND(Teams!$E26*(J$6-Teams!$F26+1)/(Teams!$G26-Teams!$F26+1),0),IF(J$6<=Teams!$H26,Teams!$E26,ROUND(Teams!$E26*(Teams!$I26-J$6+1)/(Teams!$I26-Teams!$H26),0)))) | ... AN28: =IF(OR(AN$6<Teams!$F26,AN$6>Teams!$I26),0,IF(AN$6<Teams!$G26,ROUND(Teams!$E26*(AN$6-Teams!$F26+1)/(Teams!$G26-Teams!$F26+1),0),IF(AN$6<=Teams!$H26,Teams!$E26,ROUND(Teams!$E26*(Teams!$I26-AN$6+1)/(Teams!$I26-Teams!$H26),0))))
B29: TOTAL SITE POPULATION | C29: =SUM(C7:C28) | D29: =SUM(D7:D28) | E29: =SUM(E7:E28) | F29: =SUM(F7:F28) | G29: =SUM(G7:G28) | H29: =SUM(H7:H28) | I29: =SUM(I7:I28) | J29: =SUM(J7:J28) | ... AN29: =SUM(AN7:AN28)
B31: Peak site population | C31: =MAX(C29:AN29)
B32: Month of peak | C32: =MATCH(C31,C29:AN29,0)
B33: Average over the programme | C33: =ROUND(AVERAGE(C29:AN29),0)
B34: Person-months of exposure | C34: =SUM(C29:AN29)

Sheet BedDemand
A2: BED DEMAND — WHO NEEDS A ROOM, MONTH BY MONTH
A3: The whole village follows from this sheet. Headcount from Workforce, travelling percentage from Teams, everything else from Assumptions.
B5: Month | C5: =Workforce!C5 | D5: =Workforce!D5 | E5: =Workforce!E5 | F5: =Workforce!F5 | G5: =Workforce!G5 | H5: =Workforce!H5 | I5: =Workforce!I5 | J5: =Workforce!J5 | ... AN5: =Workforce!AN5
B6: Month number | C6: 1 | D6: 2 | E6: 3 | F6: 4 | G6: 5 | H6: 6 | I6: 7 | J6: 8 | K6: 9 | L6: 10 | M6: 11 | N6: 12 | O6: 13 | P6: 14 | Q6: 15 | R6: 16 | S6: 17 | T6: 18 | U6: 19 | V6: 20 | W6: 21 | X6: 22 | Y6: 23 | Z6: 24 | AA6: 25 | AB6: 26 | AC6: 27 | AD6: 28 | AE6: 29 | AF6: 30 | AG6: 31 | AH6: 32 | AI6: 33 | AJ6: 34 | AK6: 35 | AL6: 36 | AM6: 37 | AN6: 38
B7: Travelling workers (need accommodation) | C7: =ROUND(SUMPRODUCT(Workforce!C$7:C$28,Teams!$J$5:$J$26),0) | D7: =ROUND(SUMPRODUCT(Workforce!D$7:D$28,Teams!$J$5:$J$26),0) | E7: =ROUND(SUMPRODUCT(Workforce!E$7:E$28,Teams!$J$5:$J$26),0) | F7: =ROUND(SUMPRODUCT(Workforce!F$7:F$28,Teams!$J$5:$J$26),0) | G7: =ROUND(SUMPRODUCT(Workforce!G$7:G$28,Teams!$J$5:$J$26),0) | H7: =ROUND(SUMPRODUCT(Workforce!H$7:H$28,Teams!$J$5:$J$26),0) | I7: =ROUND(SUMPRODUCT(Workforce!I$7:I$28,Teams!$J$5:$J$26),0) | J7: =ROUND(SUMPRODUCT(Workforce!J$7:J$28,Teams!$J$5:$J$26),0) | ... AN7: =ROUND(SUMPRODUCT(Workforce!AN$7:AN$28,Teams!$J$5:$J$26),0) | AP7: Headcount × each team's travelling percentage. A local team of 30 needs no beds; a commissioning team of 18 needs 17.
B8: Local / commuting workers | C8: =Workforce!C$29-C7 | D8: =Workforce!D$29-D7 | E8: =Workforce!E$29-E7 | F8: =Workforce!F$29-F7 | G8: =Workforce!G$29-G7 | H8: =Workforce!H$29-H7 | I8: =Workforce!I$29-I7 | J8: =Workforce!J$29-J7 | ... AN8: =Workforce!AN$29-AN7 | AP8: Go home at night. They still eat, park and use welfare on site.
B9: Present at any one time (rotation applied) | C9: =C7*Assumptions!$C$17 | D9: =D7*Assumptions!$C$17 | E9: =E7*Assumptions!$C$17 | F9: =F7*Assumptions!$C$17 | G9: =G7*Assumptions!$C$17 | H9: =H7*Assumptions!$C$17 | I9: =I7*Assumptions!$C$17 | J9: =J7*Assumptions!$C$17 | ... AN9: =AN7*Assumptions!$C$17 | AP9: A rotation means not everyone is on site at once. At 1.00 this line equals the one above.
B10: Rooms required for residents | C10: =ROUNDUP(C9*Assumptions!$C$16,0) | D10: =ROUNDUP(D9*Assumptions!$C$16,0) | E10: =ROUNDUP(E9*Assumptions!$C$16,0) | F10: =ROUNDUP(F9*Assumptions!$C$16,0) | G10: =ROUNDUP(G9*Assumptions!$C$16,0) | H10: =ROUNDUP(H9*Assumptions!$C$16,0) | I10: =ROUNDUP(I9*Assumptions!$C$16,0) | J10: =ROUNDUP(J9*Assumptions!$C$16,0) | ... AN10: =ROUNDUP(AN9*Assumptions!$C$16,0)
B11: Void and turnover allowance | C11: =ROUNDUP(C10*Assumptions!$C$18,0) | D11: =ROUNDUP(D10*Assumptions!$C$18,0) | E11: =ROUNDUP(E10*Assumptions!$C$18,0) | F11: =ROUNDUP(F10*Assumptions!$C$18,0) | G11: =ROUNDUP(G10*Assumptions!$C$18,0) | H11: =ROUNDUP(H10*Assumptions!$C$18,0) | I11: =ROUNDUP(I10*Assumptions!$C$18,0) | J11: =ROUNDUP(J10*Assumptions!$C$18,0) | ... AN11: =ROUNDUP(AN10*Assumptions!$C$18,0) | AP11: Rooms unavailable for cleaning, changeover, damage or maintenance.
B12: Contingency | C12: =ROUNDUP(C10*Assumptions!$C$19,0) | D12: =ROUNDUP(D10*Assumptions!$C$19,0) | E12: =ROUNDUP(E10*Assumptions!$C$19,0) | F12: =ROUNDUP(F10*Assumptions!$C$19,0) | G12: =ROUNDUP(G10*Assumptions!$C$19,0) | H12: =ROUNDUP(H10*Assumptions!$C$19,0) | I12: =ROUNDUP(I10*Assumptions!$C$19,0) | J12: =ROUNDUP(J10*Assumptions!$C$19,0) | ... AN12: =ROUNDUP(AN10*Assumptions!$C$19,0)
B13: Visitor and spare rooms | C13: =IF(C10>0,Assumptions!$C$23,0) | D13: =IF(D10>0,Assumptions!$C$23,0) | E13: =IF(E10>0,Assumptions!$C$23,0) | F13: =IF(F10>0,Assumptions!$C$23,0) | G13: =IF(G10>0,Assumptions!$C$23,0) | H13: =IF(H10>0,Assumptions!$C$23,0) | I13: =IF(I10>0,Assumptions!$C$23,0) | J13: =IF(J10>0,Assumptions!$C$23,0) | ... AN13: =IF(AN10>0,Assumptions!$C$23,0)
B14: TOTAL ROOMS REQUIRED | C14: =SUM(C10:C13) | D14: =SUM(D10:D13) | E14: =SUM(E10:E13) | F14: =SUM(F10:F13) | G14: =SUM(G10:G13) | H14: =SUM(H10:H13) | I14: =SUM(I10:I13) | J14: =SUM(J10:J13) | ... AN14: =SUM(AN10:AN13) | AP14: This curve is what the village must satisfy. The peak sizes it; the shape decides whether you phase it.
B15: Helper — month number where rooms are needed | C15: =IF(C14>0,C$6,"") | D15: =IF(D14>0,D$6,"") | E15: =IF(E14>0,E$6,"") | F15: =IF(F14>0,F$6,"") | G15: =IF(G14>0,G$6,"") | H15: =IF(H14>0,H$6,"") | I15: =IF(I14>0,I$6,"") | J15: =IF(J14>0,J$6,"") | ... AN15: =IF(AN14>0,AN$6,"")
B16: Occupancy rate against the built village | C16: =IF($C$22=0,0,C10/$C$22) | D16: =IF($C$22=0,0,D10/$C$22) | E16: =IF($C$22=0,0,E10/$C$22) | F16: =IF($C$22=0,0,F10/$C$22) | G16: =IF($C$22=0,0,G10/$C$22) | H16: =IF($C$22=0,0,H10/$C$22) | I16: =IF($C$22=0,0,I10/$C$22) | J16: =IF($C$22=0,0,J10/$C$22) | ... AN16: =IF($C$22=0,0,AN10/$C$22) | AP16: Against the peak-sized village. The low months are the cost of building for the peak.
B18: THE NUMBERS THAT SIZE THE VILLAGE
B20: Peak rooms required | C20: =MAX(C14:AN14) | E20: The village is built to this.
B21: Month of peak | C21: =MATCH(C20,C14:AN14,0) | E21: Everything upstream must be finished before it.
B22: Peak resident rooms (excluding void, contingency, visitors) | C22: =MAX(C10:AN10)
B23: First month with any bed demand | C23: =MIN(C15:AN15) | E23: The village must be live before this month, not in it.
B24: Last month with bed demand | C24: =MAX(C15:AN15)
B25: Bed-nights over the programme | C25: =ROUND(SUM(C10:AN10)*30.4,0) | E25: Drives catering, utilities and the unit cost of the whole thing.
B26: Average occupancy across the live period | C26: =IFERROR(AVERAGEIF(C10:AN10,">0")/$C$22,0) | E26: Below about 70% the case for phasing the village gets strong.
B28: BEDS BY COMPANY — WHO IS RECHARGED FOR WHAT
B29: Company | C29: Peak beds | D29: Bed-months | E29: Share of bed-months | AP29: Helper — resident rooms by company by month (hide these columns)
B30: Ashfell M&E Ltd | C30: =MAX(AP30:CA30) | D30: =ROUND(SUM(AP30:CA30),0) | E30: =IFERROR(D30/SUM($D$30:$D$43),0) | AP30: =SUMPRODUCT((Teams!$B$5:$B$26=$B30)*Workforce!C$7:C$28*Teams!$J$5:$J$26)*Assumptions!$C$17*Assumptions!$C$16 | AQ30: =SUMPRODUCT((Teams!$B$5:$B$26=$B30)*Workforce!D$7:D$28*Teams!$J$5:$J$26)*Assumptions!$C$17*Assumptions!$C$16 | AR30: =SUMPRODUCT((Teams!$B$5:$B$26=$B30)*Workforce!E$7:E$28*Teams!$J$5:$J$26)*Assumptions!$C$17*Assumptions!$C$16 | AS30: =SUMPRODUCT((Teams!$B$5:$B$26=$B30)*Workforce!F$7:F$28*Teams!$J$5:$J$26)*Assumptions!$C$17*Assumptions!$C$16 | AT30: =SUMPRODUCT((Teams!$B$5:$B$26=$B30)*Workforce!G$7:G$28*Teams!$J$5:$J$26)*Assumptions!$C$17*Assumptions!$C$16 | AU30: =SUMPRODUCT((Teams!$B$5:$B$26=$B30)*Workforce!H$7:H$28*Teams!$J$5:$J$26)*Assumptions!$C$17*Assumptions!$C$16 | AV30: =SUMPRODUCT((Teams!$B$5:$B$26=$B30)*Workforce!I$7:I$28*Teams!$J$5:$J$26)*Assumptions!$C$17*Assumptions!$C$16 | AW30: =SUMPRODUCT((Teams!$B$5:$B$26=$B30)*Workforce!J$7:J$28*Teams!$J$5:$J$26)*Assumptions!$C$17*Assumptions!$C$16 | ... CA30: =SUMPRODUCT((Teams!$B$5:$B$26=$B30)*Workforce!AN$7:AN$28*Teams!$J$5:$J$26)*Assumptions!$C$17*Assumptions!$C$16
B31: Brightbay Facilities Management Ltd | C31: =MAX(AP31:CA31) | D31: =ROUND(SUM(AP31:CA31),0) | E31: =IFERROR(D31/SUM($D$30:$D$43),0) | AP31: =SUMPRODUCT((Teams!$B$5:$B$26=$B31)*Workforce!C$7:C$28*Teams!$J$5:$J$26)*Assumptions!$C$17*Assumptions!$C$16 | AQ31: =SUMPRODUCT((Teams!$B$5:$B$26=$B31)*Workforce!D$7:D$28*Teams!$J$5:$J$26)*Assumptions!$C$17*Assumptions!$C$16 | AR31: =SUMPRODUCT((Teams!$B$5:$B$26=$B31)*Workforce!E$7:E$28*Teams!$J$5:$J$26)*Assumptions!$C$17*Assumptions!$C$16 | AS31: =SUMPRODUCT((Teams!$B$5:$B$26=$B31)*Workforce!F$7:F$28*Teams!$J$5:$J$26)*Assumptions!$C$17*Assumptions!$C$16 | AT31: =SUMPRODUCT((Teams!$B$5:$B$26=$B31)*Workforce!G$7:G$28*Teams!$J$5:$J$26)*Assumptions!$C$17*Assumptions!$C$16 | AU31: =SUMPRODUCT((Teams!$B$5:$B$26=$B31)*Workforce!H$7:H$28*Teams!$J$5:$J$26)*Assumptions!$C$17*Assumptions!$C$16 | AV31: =SUMPRODUCT((Teams!$B$5:$B$26=$B31)*Workforce!I$7:I$28*Teams!$J$5:$J$26)*Assumptions!$C$17*Assumptions!$C$16 | AW31: =SUMPRODUCT((Teams!$B$5:$B$26=$B31)*Workforce!J$7:J$28*Teams!$J$5:$J$26)*Assumptions!$C$17*Assumptions!$C$16 | ... CA31: =SUMPRODUCT((Teams!$B$5:$B$26=$B31)*Workforce!AN$7:AN$28*Teams!$J$5:$J$26)*Assumptions!$C$17*Assumptions!$C$16
B32: Calderbrook Civils Ltd | C32: =MAX(AP32:CA32) | D32: =ROUND(SUM(AP32:CA32),0) | E32: =IFERROR(D32/SUM($D$30:$D$43),0) | AP32: =SUMPRODUCT((Teams!$B$5:$B$26=$B32)*Workforce!C$7:C$28*Teams!$J$5:$J$26)*Assumptions!$C$17*Assumptions!$C$16 | AQ32: =SUMPRODUCT((Teams!$B$5:$B$26=$B32)*Workforce!D$7:D$28*Teams!$J$5:$J$26)*Assumptions!$C$17*Assumptions!$C$16 | AR32: =SUMPRODUCT((Teams!$B$5:$B$26=$B32)*Workforce!E$7:E$28*Teams!$J$5:$J$26)*Assumptions!$C$17*Assumptions!$C$16 | AS32: =SUMPRODUCT((Teams!$B$5:$B$26=$B32)*Workforce!F$7:F$28*Teams!$J$5:$J$26)*Assumptions!$C$17*Assumptions!$C$16 | AT32: =SUMPRODUCT((Teams!$B$5:$B$26=$B32)*Workforce!G$7:G$28*Teams!$J$5:$J$26)*Assumptions!$C$17*Assumptions!$C$16 | AU32: =SUMPRODUCT((Teams!$B$5:$B$26=$B32)*Workforce!H$7:H$28*Teams!$J$5:$J$26)*Assumptions!$C$17*Assumptions!$C$16 | AV32: =SUMPRODUCT((Teams!$B$5:$B$26=$B32)*Workforce!I$7:I$28*Teams!$J$5:$J$26)*Assumptions!$C$17*Assumptions!$C$16 | AW32: =SUMPRODUCT((Teams!$B$5:$B$26=$B32)*Workforce!J$7:J$28*Teams!$J$5:$J$26)*Assumptions!$C$17*Assumptions!$C$16 | ... CA32: =SUMPRODUCT((Teams!$B$5:$B$26=$B32)*Workforce!AN$7:AN$28*Teams!$J$5:$J$26)*Assumptions!$C$17*Assumptions!$C$16
B33: Hollins Catering Ltd | C33: =MAX(AP33:CA33) | D33: =ROUND(SUM(AP33:CA33),0) | E33: =IFERROR(D33/SUM($D$30:$D$43),0) | AP33: =SUMPRODUCT((Teams!$B$5:$B$26=$B33)*Workforce!C$7:C$28*Teams!$J$5:$J$26)*Assumptions!$C$17*Assumptions!$C$16 | AQ33: =SUMPRODUCT((Teams!$B$5:$B$26=$B33)*Workforce!D$7:D$28*Teams!$J$5:$J$26)*Assumptions!$C$17*Assumptions!$C$16 | AR33: =SUMPRODUCT((Teams!$B$5:$B$26=$B33)*Workforce!E$7:E$28*Teams!$J$5:$J$26)*Assumptions!$C$17*Assumptions!$C$16 | AS33: =SUMPRODUCT((Teams!$B$5:$B$26=$B33)*Workforce!F$7:F$28*Teams!$J$5:$J$26)*Assumptions!$C$17*Assumptions!$C$16 | AT33: =SUMPRODUCT((Teams!$B$5:$B$26=$B33)*Workforce!G$7:G$28*Teams!$J$5:$J$26)*Assumptions!$C$17*Assumptions!$C$16 | AU33: =SUMPRODUCT((Teams!$B$5:$B$26=$B33)*Workforce!H$7:H$28*Teams!$J$5:$J$26)*Assumptions!$C$17*Assumptions!$C$16 | AV33: =SUMPRODUCT((Teams!$B$5:$B$26=$B33)*Workforce!I$7:I$28*Teams!$J$5:$J$26)*Assumptions!$C$17*Assumptions!$C$16 | AW33: =SUMPRODUCT((Teams!$B$5:$B$26=$B33)*Workforce!J$7:J$28*Teams!$J$5:$J$26)*Assumptions!$C$17*Assumptions!$C$16 | ... CA33: =SUMPRODUCT((Teams!$B$5:$B$26=$B33)*Workforce!AN$7:AN$28*Teams!$J$5:$J$26)*Assumptions!$C$17*Assumptions!$C$16
B34: Ironvale Welding Ltd | C34: =MAX(AP34:CA34) | D34: =ROUND(SUM(AP34:CA34),0) | E34: =IFERROR(D34/SUM($D$30:$D$43),0) | AP34: =SUMPRODUCT((Teams!$B$5:$B$26=$B34)*Workforce!C$7:C$28*Teams!$J$5:$J$26)*Assumptions!$C$17*Assumptions!$C$16 | AQ34: =SUMPRODUCT((Teams!$B$5:$B$26=$B34)*Workforce!D$7:D$28*Teams!$J$5:$J$26)*Assumptions!$C$17*Assumptions!$C$16 | AR34: =SUMPRODUCT((Teams!$B$5:$B$26=$B34)*Workforce!E$7:E$28*Teams!$J$5:$J$26)*Assumptions!$C$17*Assumptions!$C$16 | AS34: =SUMPRODUCT((Teams!$B$5:$B$26=$B34)*Workforce!F$7:F$28*Teams!$J$5:$J$26)*Assumptions!$C$17*Assumptions!$C$16 | AT34: =SUMPRODUCT((Teams!$B$5:$B$26=$B34)*Workforce!G$7:G$28*Teams!$J$5:$J$26)*Assumptions!$C$17*Assumptions!$C$16 | AU34: =SUMPRODUCT((Teams!$B$5:$B$26=$B34)*Workforce!H$7:H$28*Teams!$J$5:$J$26)*Assumptions!$C$17*Assumptions!$C$16 | AV34: =SUMPRODUCT((Teams!$B$5:$B$26=$B34)*Workforce!I$7:I$28*Teams!$J$5:$J$26)*Assumptions!$C$17*Assumptions!$C$16 | AW34: =SUMPRODUCT((Teams!$B$5:$B$26=$B34)*Workforce!J$7:J$28*Teams!$J$5:$J$26)*Assumptions!$C$17*Assumptions!$C$16 | ... CA34: =SUMPRODUCT((Teams!$B$5:$B$26=$B34)*Workforce!AN$7:AN$28*Teams!$J$5:$J$26)*Assumptions!$C$17*Assumptions!$C$16
B35: Kestrel Security Ltd | C35: =MAX(AP35:CA35) | D35: =ROUND(SUM(AP35:CA35),0) | E35: =IFERROR(D35/SUM($D$30:$D$43),0) | AP35: =SUMPRODUCT((Teams!$B$5:$B$26=$B35)*Workforce!C$7:C$28*Teams!$J$5:$J$26)*Assumptions!$C$17*Assumptions!$C$16 | AQ35: =SUMPRODUCT((Teams!$B$5:$B$26=$B35)*Workforce!D$7:D$28*Teams!$J$5:$J$26)*Assumptions!$C$17*Assumptions!$C$16 | AR35: =SUMPRODUCT((Teams!$B$5:$B$26=$B35)*Workforce!E$7:E$28*Teams!$J$5:$J$26)*Assumptions!$C$17*Assumptions!$C$16 | AS35: =SUMPRODUCT((Teams!$B$5:$B$26=$B35)*Workforce!F$7:F$28*Teams!$J$5:$J$26)*Assumptions!$C$17*Assumptions!$C$16 | AT35: =SUMPRODUCT((Teams!$B$5:$B$26=$B35)*Workforce!G$7:G$28*Teams!$J$5:$J$26)*Assumptions!$C$17*Assumptions!$C$16 | AU35: =SUMPRODUCT((Teams!$B$5:$B$26=$B35)*Workforce!H$7:H$28*Teams!$J$5:$J$26)*Assumptions!$C$17*Assumptions!$C$16 | AV35: =SUMPRODUCT((Teams!$B$5:$B$26=$B35)*Workforce!I$7:I$28*Teams!$J$5:$J$26)*Assumptions!$C$17*Assumptions!$C$16 | AW35: =SUMPRODUCT((Teams!$B$5:$B$26=$B35)*Workforce!J$7:J$28*Teams!$J$5:$J$26)*Assumptions!$C$17*Assumptions!$C$16 | ... CA35: =SUMPRODUCT((Teams!$B$5:$B$26=$B35)*Workforce!AN$7:AN$28*Teams!$J$5:$J$26)*Assumptions!$C$17*Assumptions!$C$16
B36: Ledwyn Scaffolding Ltd | C36: =MAX(AP36:CA36) | D36: =ROUND(SUM(AP36:CA36),0) | E36: =IFERROR(D36/SUM($D$30:$D$43),0) | AP36: =SUMPRODUCT((Teams!$B$5:$B$26=$B36)*Workforce!C$7:C$28*Teams!$J$5:$J$26)*Assumptions!$C$17*Assumptions!$C$16 | AQ36: =SUMPRODUCT((Teams!$B$5:$B$26=$B36)*Workforce!D$7:D$28*Teams!$J$5:$J$26)*Assumptions!$C$17*Assumptions!$C$16 | AR36: =SUMPRODUCT((Teams!$B$5:$B$26=$B36)*Workforce!E$7:E$28*Teams!$J$5:$J$26)*Assumptions!$C$17*Assumptions!$C$16 | AS36: =SUMPRODUCT((Teams!$B$5:$B$26=$B36)*Workforce!F$7:F$28*Teams!$J$5:$J$26)*Assumptions!$C$17*Assumptions!$C$16 | AT36: =SUMPRODUCT((Teams!$B$5:$B$26=$B36)*Workforce!G$7:G$28*Teams!$J$5:$J$26)*Assumptions!$C$17*Assumptions!$C$16 | AU36: =SUMPRODUCT((Teams!$B$5:$B$26=$B36)*Workforce!H$7:H$28*Teams!$J$5:$J$26)*Assumptions!$C$17*Assumptions!$C$16 | AV36: =SUMPRODUCT((Teams!$B$5:$B$26=$B36)*Workforce!I$7:I$28*Teams!$J$5:$J$26)*Assumptions!$C$17*Assumptions!$C$16 | AW36: =SUMPRODUCT((Teams!$B$5:$B$26=$B36)*Workforce!J$7:J$28*Teams!$J$5:$J$26)*Assumptions!$C$17*Assumptions!$C$16 | ... CA36: =SUMPRODUCT((Teams!$B$5:$B$26=$B36)*Workforce!AN$7:AN$28*Teams!$J$5:$J$26)*Assumptions!$C$17*Assumptions!$C$16
B37: Marrowbridge Infrastructure Ltd | C37: =MAX(AP37:CA37) | D37: =ROUND(SUM(AP37:CA37),0) | E37: =IFERROR(D37/SUM($D$30:$D$43),0) | AP37: =SUMPRODUCT((Teams!$B$5:$B$26=$B37)*Workforce!C$7:C$28*Teams!$J$5:$J$26)*Assumptions!$C$17*Assumptions!$C$16 | AQ37: =SUMPRODUCT((Teams!$B$5:$B$26=$B37)*Workforce!D$7:D$28*Teams!$J$5:$J$26)*Assumptions!$C$17*Assumptions!$C$16 | AR37: =SUMPRODUCT((Teams!$B$5:$B$26=$B37)*Workforce!E$7:E$28*Teams!$J$5:$J$26)*Assumptions!$C$17*Assumptions!$C$16 | AS37: =SUMPRODUCT((Teams!$B$5:$B$26=$B37)*Workforce!F$7:F$28*Teams!$J$5:$J$26)*Assumptions!$C$17*Assumptions!$C$16 | AT37: =SUMPRODUCT((Teams!$B$5:$B$26=$B37)*Workforce!G$7:G$28*Teams!$J$5:$J$26)*Assumptions!$C$17*Assumptions!$C$16 | AU37: =SUMPRODUCT((Teams!$B$5:$B$26=$B37)*Workforce!H$7:H$28*Teams!$J$5:$J$26)*Assumptions!$C$17*Assumptions!$C$16 | AV37: =SUMPRODUCT((Teams!$B$5:$B$26=$B37)*Workforce!I$7:I$28*Teams!$J$5:$J$26)*Assumptions!$C$17*Assumptions!$C$16 | AW37: =SUMPRODUCT((Teams!$B$5:$B$26=$B37)*Workforce!J$7:J$28*Teams!$J$5:$J$26)*Assumptions!$C$17*Assumptions!$C$16 | ... CA37: =SUMPRODUCT((Teams!$B$5:$B$26=$B37)*Workforce!AN$7:AN$28*Teams!$J$5:$J$26)*Assumptions!$C$17*Assumptions!$C$16
B38: Northgate Steel Ltd | C38: =MAX(AP38:CA38) | D38: =ROUND(SUM(AP38:CA38),0) | E38: =IFERROR(D38/SUM($D$30:$D$43),0) | AP38: =SUMPRODUCT((Teams!$B$5:$B$26=$B38)*Workforce!C$7:C$28*Teams!$J$5:$J$26)*Assumptions!$C$17*Assumptions!$C$16 | AQ38: =SUMPRODUCT((Teams!$B$5:$B$26=$B38)*Workforce!D$7:D$28*Teams!$J$5:$J$26)*Assumptions!$C$17*Assumptions!$C$16 | AR38: =SUMPRODUCT((Teams!$B$5:$B$26=$B38)*Workforce!E$7:E$28*Teams!$J$5:$J$26)*Assumptions!$C$17*Assumptions!$C$16 | AS38: =SUMPRODUCT((Teams!$B$5:$B$26=$B38)*Workforce!F$7:F$28*Teams!$J$5:$J$26)*Assumptions!$C$17*Assumptions!$C$16 | AT38: =SUMPRODUCT((Teams!$B$5:$B$26=$B38)*Workforce!G$7:G$28*Teams!$J$5:$J$26)*Assumptions!$C$17*Assumptions!$C$16 | AU38: =SUMPRODUCT((Teams!$B$5:$B$26=$B38)*Workforce!H$7:H$28*Teams!$J$5:$J$26)*Assumptions!$C$17*Assumptions!$C$16 | AV38: =SUMPRODUCT((Teams!$B$5:$B$26=$B38)*Workforce!I$7:I$28*Teams!$J$5:$J$26)*Assumptions!$C$17*Assumptions!$C$16 | AW38: =SUMPRODUCT((Teams!$B$5:$B$26=$B38)*Workforce!J$7:J$28*Teams!$J$5:$J$26)*Assumptions!$C$17*Assumptions!$C$16 | ... CA38: =SUMPRODUCT((Teams!$B$5:$B$26=$B38)*Workforce!AN$7:AN$28*Teams!$J$5:$J$26)*Assumptions!$C$17*Assumptions!$C$16
B39: Penmark Cable Services Ltd | C39: =MAX(AP39:CA39) | D39: =ROUND(SUM(AP39:CA39),0) | E39: =IFERROR(D39/SUM($D$30:$D$43),0) | AP39: =SUMPRODUCT((Teams!$B$5:$B$26=$B39)*Workforce!C$7:C$28*Teams!$J$5:$J$26)*Assumptions!$C$17*Assumptions!$C$16 | AQ39: =SUMPRODUCT((Teams!$B$5:$B$26=$B39)*Workforce!D$7:D$28*Teams!$J$5:$J$26)*Assumptions!$C$17*Assumptions!$C$16 | AR39: =SUMPRODUCT((Teams!$B$5:$B$26=$B39)*Workforce!E$7:E$28*Teams!$J$5:$J$26)*Assumptions!$C$17*Assumptions!$C$16 | AS39: =SUMPRODUCT((Teams!$B$5:$B$26=$B39)*Workforce!F$7:F$28*Teams!$J$5:$J$26)*Assumptions!$C$17*Assumptions!$C$16 | AT39: =SUMPRODUCT((Teams!$B$5:$B$26=$B39)*Workforce!G$7:G$28*Teams!$J$5:$J$26)*Assumptions!$C$17*Assumptions!$C$16 | AU39: =SUMPRODUCT((Teams!$B$5:$B$26=$B39)*Workforce!H$7:H$28*Teams!$J$5:$J$26)*Assumptions!$C$17*Assumptions!$C$16 | AV39: =SUMPRODUCT((Teams!$B$5:$B$26=$B39)*Workforce!I$7:I$28*Teams!$J$5:$J$26)*Assumptions!$C$17*Assumptions!$C$16 | AW39: =SUMPRODUCT((Teams!$B$5:$B$26=$B39)*Workforce!J$7:J$28*Teams!$J$5:$J$26)*Assumptions!$C$17*Assumptions!$C$16 | ... CA39: =SUMPRODUCT((Teams!$B$5:$B$26=$B39)*Workforce!AN$7:AN$28*Teams!$J$5:$J$26)*Assumptions!$C$17*Assumptions!$C$16
B40: Redmoor Groundworks Ltd | C40: =MAX(AP40:CA40) | D40: =ROUND(SUM(AP40:CA40),0) | E40: =IFERROR(D40/SUM($D$30:$D$43),0) | AP40: =SUMPRODUCT((Teams!$B$5:$B$26=$B40)*Workforce!C$7:C$28*Teams!$J$5:$J$26)*Assumptions!$C$17*Assumptions!$C$16 | AQ40: =SUMPRODUCT((Teams!$B$5:$B$26=$B40)*Workforce!D$7:D$28*Teams!$J$5:$J$26)*Assumptions!$C$17*Assumptions!$C$16 | AR40: =SUMPRODUCT((Teams!$B$5:$B$26=$B40)*Workforce!E$7:E$28*Teams!$J$5:$J$26)*Assumptions!$C$17*Assumptions!$C$16 | AS40: =SUMPRODUCT((Teams!$B$5:$B$26=$B40)*Workforce!F$7:F$28*Teams!$J$5:$J$26)*Assumptions!$C$17*Assumptions!$C$16 | AT40: =SUMPRODUCT((Teams!$B$5:$B$26=$B40)*Workforce!G$7:G$28*Teams!$J$5:$J$26)*Assumptions!$C$17*Assumptions!$C$16 | AU40: =SUMPRODUCT((Teams!$B$5:$B$26=$B40)*Workforce!H$7:H$28*Teams!$J$5:$J$26)*Assumptions!$C$17*Assumptions!$C$16 | AV40: =SUMPRODUCT((Teams!$B$5:$B$26=$B40)*Workforce!I$7:I$28*Teams!$J$5:$J$26)*Assumptions!$C$17*Assumptions!$C$16 | AW40: =SUMPRODUCT((Teams!$B$5:$B$26=$B40)*Workforce!J$7:J$28*Teams!$J$5:$J$26)*Assumptions!$C$17*Assumptions!$C$16 | ... CA40: =SUMPRODUCT((Teams!$B$5:$B$26=$B40)*Workforce!AN$7:AN$28*Teams!$J$5:$J$26)*Assumptions!$C$17*Assumptions!$C$16
B41: Southgate Testing & Commissioning Ltd | C41: =MAX(AP41:CA41) | D41: =ROUND(SUM(AP41:CA41),0) | E41: =IFERROR(D41/SUM($D$30:$D$43),0) | AP41: =SUMPRODUCT((Teams!$B$5:$B$26=$B41)*Workforce!C$7:C$28*Teams!$J$5:$J$26)*Assumptions!$C$17*Assumptions!$C$16 | AQ41: =SUMPRODUCT((Teams!$B$5:$B$26=$B41)*Workforce!D$7:D$28*Teams!$J$5:$J$26)*Assumptions!$C$17*Assumptions!$C$16 | AR41: =SUMPRODUCT((Teams!$B$5:$B$26=$B41)*Workforce!E$7:E$28*Teams!$J$5:$J$26)*Assumptions!$C$17*Assumptions!$C$16 | AS41: =SUMPRODUCT((Teams!$B$5:$B$26=$B41)*Workforce!F$7:F$28*Teams!$J$5:$J$26)*Assumptions!$C$17*Assumptions!$C$16 | AT41: =SUMPRODUCT((Teams!$B$5:$B$26=$B41)*Workforce!G$7:G$28*Teams!$J$5:$J$26)*Assumptions!$C$17*Assumptions!$C$16 | AU41: =SUMPRODUCT((Teams!$B$5:$B$26=$B41)*Workforce!H$7:H$28*Teams!$J$5:$J$26)*Assumptions!$C$17*Assumptions!$C$16 | AV41: =SUMPRODUCT((Teams!$B$5:$B$26=$B41)*Workforce!I$7:I$28*Teams!$J$5:$J$26)*Assumptions!$C$17*Assumptions!$C$16 | AW41: =SUMPRODUCT((Teams!$B$5:$B$26=$B41)*Workforce!J$7:J$28*Teams!$J$5:$J$26)*Assumptions!$C$17*Assumptions!$C$16 | ... CA41: =SUMPRODUCT((Teams!$B$5:$B$26=$B41)*Workforce!AN$7:AN$28*Teams!$J$5:$J$26)*Assumptions!$C$17*Assumptions!$C$16
... B43: Vellamo Power Systems Ltd | C43: =MAX(AP43:CA43) | D43: =ROUND(SUM(AP43:CA43),0) | E43: =IFERROR(D43/SUM($D$30:$D$43),0) | AP43: =SUMPRODUCT((Teams!$B$5:$B$26=$B43)*Workforce!C$7:C$28*Teams!$J$5:$J$26)*Assumptions!$C$17*Assumptions!$C$16 | AQ43: =SUMPRODUCT((Teams!$B$5:$B$26=$B43)*Workforce!D$7:D$28*Teams!$J$5:$J$26)*Assumptions!$C$17*Assumptions!$C$16 | AR43: =SUMPRODUCT((Teams!$B$5:$B$26=$B43)*Workforce!E$7:E$28*Teams!$J$5:$J$26)*Assumptions!$C$17*Assumptions!$C$16 | AS43: =SUMPRODUCT((Teams!$B$5:$B$26=$B43)*Workforce!F$7:F$28*Teams!$J$5:$J$26)*Assumptions!$C$17*Assumptions!$C$16 | AT43: =SUMPRODUCT((Teams!$B$5:$B$26=$B43)*Workforce!G$7:G$28*Teams!$J$5:$J$26)*Assumptions!$C$17*Assumptions!$C$16 | AU43: =SUMPRODUCT((Teams!$B$5:$B$26=$B43)*Workforce!H$7:H$28*Teams!$J$5:$J$26)*Assumptions!$C$17*Assumptions!$C$16 | AV43: =SUMPRODUCT((Teams!$B$5:$B$26=$B43)*Workforce!I$7:I$28*Teams!$J$5:$J$26)*Assumptions!$C$17*Assumptions!$C$16 | AW43: =SUMPRODUCT((Teams!$B$5:$B$26=$B43)*Workforce!J$7:J$28*Teams!$J$5:$J$26)*Assumptions!$C$17*Assumptions!$C$16 | ... CA43: =SUMPRODUCT((Teams!$B$5:$B$26=$B43)*Workforce!AN$7:AN$28*Teams!$J$5:$J$26)*Assumptions!$C$17*Assumptions!$C$16
B44: TOTAL | D44: =SUM(D30:D43)

Sheet Accommodation
B2: ACCOMMODATION SCHEDULE — WHAT GETS BUILT
B3: Sized to the peak from BedDemand. Room mix, block count, floor area and land take.
B5: Item | C5: Quantity | D5: Unit | E5: How it is derived — and what to verify
A6: ROOM SCHEDULE
B7: Peak rooms required (from BedDemand) | C7: =BedDemand!$C$20 | D7: rooms | E7: The village is built to this number, not to the average.
B8: Accessible rooms | C8: =ROUNDUP(C7*Assumptions!$C$21,0) | D8: rooms | E8: Level access, accessible shower room, turning circle. Confirm the required proportion with Building Control — the percentage on Assumptions is a placeholder, not a standard.
B9: Senior / manager rooms | C9: =ROUNDUP(C7*Assumptions!$C$22,0) | D9: rooms | E9: A commercial choice, not a requirement.
B10: Standard single ensuite rooms | C10: =C7-C8-C9 | D10: rooms | E10: The balance.
B11: of which allocated to women | C11: =ROUNDUP(C10*Assumptions!$C$20,0) | D11: rooms | E11: Drives a separate lockable block or floor with its own entrance, not simply a count of rooms. Set the percentage from your own workforce data.
B12: TOTAL ROOMS | C12: =C8+C9+C10 | D12: rooms
A14: BLOCKS AND FLOOR AREA
B15: Accommodation blocks | C15: =ROUNDUP(C12/Assumptions!$C$29,0) | D15: blocks | E15: At the module size on Assumptions. Round up — a part block is a whole block.
B16: Net room area | C16: =C10*Assumptions!$C$26+C8*Assumptions!$C$27+C9*Assumptions!$C$28 | D16: m² | E16: Rooms only, before corridors and plant.
B17: Gross accommodation area | C17: =C16*Assumptions!$C$30 | D17: m² | E17: Corridors, stairs, risers and plant included. The gross-up factor should come from the supplier's actual block layout.
A19: LAND TAKE
B20: Accommodation footprint (two storey) | C20: =C17/2 | D20: m² | E20: Assumes two-storey blocks. Single storey doubles this.
B21: External works, roads, parking, standoff | C21: =C12*Assumptions!$C$31 | D21: m² | E21: Roads, footpaths, parking, drainage, landscaping, and separation between blocks for fire and privacy.
B22: Amenity and facilities footprint | C22: =Facilities!$C$29 | D22: m² | E22: From the facilities schedule.
B23: TOTAL SITE AREA REQUIRED | C23: =C20+C21+C22 | D23: m²
B24: in hectares | C24: =C23/10000 | D24: ha | E24: Test this against the land you actually have before anything else on this sheet matters.
A26: SANITY CHECKS
B27: Rooms per resident at peak | C27: =IFERROR(C12/BedDemand!$C$22,0) | D27: × | E27: A little above 1.0 is right. Well above means the void and contingency allowances are generous.
B28: Gross area per bed | C28: =IFERROR(C17/C12,0) | D28: m²/bed | E28: Typically 14–18 m² gross for a modular village. Outside that, check the gross-up factor.

Sheet Facilities
B2: FACILITIES SCHEDULE — WHAT THE VILLAGE NEEDS TO WORK
B3: Sized to peak occupancy. Every ratio sits on Assumptions, and every one is a first-pass planning figure.
B5: Item | C5: Quantity | D5: Unit | E5: How it is derived — and what to verify
A6: CATERING
B7: Peak residents | C7: =BedDemand!$C$22 | D7: people
B8: Breakfast covers required | C8: =ROUNDUP(C7*Assumptions!$C$34/Assumptions!$C$37,0) | D8: covers | E8: Residents taking breakfast, divided by sittings.
B9: Evening meal covers required | C9: =ROUNDUP(C7*Assumptions!$C$35/Assumptions!$C$37,0) | D9: covers | E9: Usually the binding case — everyone is back at once.
B10: DINING ROOM COVERS (design case) | C10: =MAX(C8,C9) | D10: covers | E10: Size the room to the larger of the two.
B11: Dining room area | C11: =C10*Assumptions!$C$38 | D11: m²
B12: Kitchen, servery, stores and wash-up | C12: =C10*Assumptions!$C$39 | D12: m² | E12: To verify with the caterer against their menu and delivery cycle.
B13: Packed lunches per day | C13: =ROUNDUP(C7*Assumptions!$C$36,0) | D13: no. | E13: Made in the same kitchen overnight — no covers, but real labour and real cold storage.
B14: Meals served per day (all sittings) | C14: =ROUNDUP(C7*(Assumptions!$C$34+Assumptions!$C$35),0) | D14: meals | E14: Drives the catering line on Opex.
A16: LAUNDRY, DRYING AND HOUSEKEEPING
B17: Washing machines | C17: =ROUNDUP(C7/Assumptions!$C$42,0) | D17: no. | E17: Self-service. Fewer if bed linen is contracted out — personal laundry still has to happen somewhere.
B18: Tumble dryers | C18: =ROUNDUP(C7/Assumptions!$C$43,0) | D18: no.
B19: Drying rooms for wet PPE and boots | C19: =ROUNDUP(C7/100*Assumptions!$C$44,0) | D19: rooms | E19: Separate from the laundry. On a wet site this is the difference between dry boots and a dispute.
B20: Laundry and drying area | C20: =C17*3.5+C18*2.5+C19*24 | D20: m² | E20: Machine footprint plus circulation, plus the drying rooms. To verify against equipment schedules.
B21: Rooms cleaned per day | C21: =ROUNDUP(BedDemand!$C$20/7*Assumptions!$C$46,0) | D21: rooms | E21: Full clean and linen change at the frequency on Assumptions, spread across the week.
A23: SOCIAL, WELFARE AND SUPPORT
B24: Gym area | C24: =ROUNDUP(C7/100*Assumptions!$C$47,0) | D24: m² | E24: On a 38-month village this is retention, not a perk. Under-provide it and it shows up in turnover.
B25: Social, TV and quiet space | C25: =ROUNDUP(C7/100*Assumptions!$C$48,0) | D25: m² | E25: Several small rooms beat one large one — shift patterns mean somebody is always asleep.
B26: Reception, admin and village office | C26: =90 | D26: m² | E26: Reception, office, meeting room, first aid. Fixed provision; increase above about 400 beds.
B27: Stores, plant and maintenance | C27: =ROUNDUP(C7*0.6,0) | D27: m² | E27: Linen store, consumables, maintenance workshop, plant room. To verify.
B28: Refuse and recycling compound | C28: =ROUNDUP(C7*0.35,0) | D28: m² | E28: Sized for the arisings on Utilities and the collection frequency you can actually get.
B29: TOTAL FACILITIES AREA | C29: =C11+C12+C20+C24+C25+C26+C27+C28 | D29: m² | E29: Feeds the land take on Accommodation.
A31: FIRE, MUSTER AND SAFETY — TO BE DESIGNED, NOT ASSUMED
B32: Muster capacity required | C32: =C7+VillageStaff!$C$23 | D32: people | E32: Residents plus village staff on shift. The number, location and travel distances of muster points are a fire engineer's decision, not this ratio's.
B33: Muster area (indicative only) | C33: =C32*0.5 | D33: m² | E33: 0.5 m² per person is an indicative planning figure. It does not constitute a fire strategy.
B34: Fire strategy, compartmentation, alarm and detection | C34: By design | E34: A residential village of this size is a designed fire-engineering case under BS 9991 and Approved Document B — compartmentation, escape distances, detection, alarm and a management plan. Nothing in this workbook sizes any of it, and nothing here should be read as doing so.

Sheet Utilities
B2: UTILITIES, ENERGY AND WASTE — MONTH BY MONTH
B3: Driven by occupancy from BedDemand. Design against the peak; budget against the curve.
B5: Month | C5: =Workforce!C5 | D5: =Workforce!D5 | E5: =Workforce!E5 | F5: =Workforce!F5 | G5: =Workforce!G5 | H5: =Workforce!H5 | I5: =Workforce!I5 | J5: =Workforce!J5 | ... AN5: =Workforce!AN5 | AP5: Basis, and what to verify
B6: Month number | C6: 1 | D6: 2 | E6: 3 | F6: 4 | G6: 5 | H6: 6 | I6: 7 | J6: 8 | K6: 9 | L6: 10 | M6: 11 | N6: 12 | O6: 13 | P6: 14 | Q6: 15 | R6: 16 | S6: 17 | T6: 18 | U6: 19 | V6: 20 | W6: 21 | X6: 22 | Y6: 23 | Z6: 24 | AA6: 25 | AB6: 26 | AC6: 27 | AD6: 28 | AE6: 29 | AF6: 30 | AG6: 31 | AH6: 32 | AI6: 33 | AJ6: 34 | AK6: 35 | AL6: 36 | AM6: 37 | AN6: 38
B7: Residents in village | C7: BedDemand!C10 | D7: BedDemand!D10 | E7: BedDemand!E10 | F7: BedDemand!F10 | G7: BedDemand!G10 | H7: BedDemand!H10 | I7: BedDemand!I10 | J7: BedDemand!J10 | K7: BedDemand!K10 | L7: BedDemand!L10 | M7: BedDemand!M10 | N7: BedDemand!N10 | O7: BedDemand!O10 | P7: BedDemand!P10 | Q7: BedDemand!Q10 | R7: BedDemand!R10 | S7: BedDemand!S10 | T7: BedDemand!T10 | U7: BedDemand!U10 | V7: BedDemand!V10 | W7: BedDemand!W10 | X7: BedDemand!X10 | Y7: BedDemand!Y10 | Z7: BedDemand!Z10 | AA7: BedDemand!AA10 | AB7: BedDemand!AB10 | AC7: BedDemand!AC10 | AD7: BedDemand!AD10 | AE7: BedDemand!AE10 | AF7: BedDemand!AF10 | AG7: BedDemand!AG10 | AH7: BedDemand!AH10 | AI7: BedDemand!AI10 | AJ7: BedDemand!AJ10 | AK7: BedDemand!AK10 | AL7: BedDemand!AL10 | AM7: BedDemand!AM10 | AN7: BedDemand!AN10 | AP7: From BedDemand. Everything on this sheet follows it.
B9: Water demand | C9: =ROUND(BedDemand!C10*Assumptions!$C$51/1000,1) | D9: =ROUND(BedDemand!D10*Assumptions!$C$51/1000,1) | E9: =ROUND(BedDemand!E10*Assumptions!$C$51/1000,1) | F9: =ROUND(BedDemand!F10*Assumptions!$C$51/1000,1) | G9: =ROUND(BedDemand!G10*Assumptions!$C$51/1000,1) | H9: =ROUND(BedDemand!H10*Assumptions!$C$51/1000,1) | I9: =ROUND(BedDemand!I10*Assumptions!$C$51/1000,1) | J9: =ROUND(BedDemand!J10*Assumptions!$C$51/1000,1) | ... AN9: =ROUND(BedDemand!AN10*Assumptions!$C$51/1000,1) | AP9: m³/day. Residential occupancy — showers, laundry, catering, WCs. Far above a site-welfare figure. Verify with the water undertaker before relying on a connection.
B10: of which hot water | C10: =ROUND(C9*Assumptions!$C$52,1) | D10: =ROUND(D9*Assumptions!$C$52,1) | E10: =ROUND(E9*Assumptions!$C$52,1) | F10: =ROUND(F9*Assumptions!$C$52,1) | G10: =ROUND(G9*Assumptions!$C$52,1) | H10: =ROUND(H9*Assumptions!$C$52,1) | I10: =ROUND(I9*Assumptions!$C$52,1) | J10: =ROUND(J9*Assumptions!$C$52,1) | ... AN10: =ROUND(AN9*Assumptions!$C$52,1) | AP10: m³/day. Sizes calorifiers and the heating load that serves them.
B11: Foul return | C11: =ROUND(C9*Assumptions!$C$53,1) | D11: =ROUND(D9*Assumptions!$C$53,1) | E11: =ROUND(E9*Assumptions!$C$53,1) | F11: =ROUND(F9*Assumptions!$C$53,1) | G11: =ROUND(G9*Assumptions!$C$53,1) | H11: =ROUND(H9*Assumptions!$C$53,1) | I11: =ROUND(I9*Assumptions!$C$53,1) | J11: =ROUND(J9*Assumptions!$C$53,1) | ... AN11: =ROUND(AN9*Assumptions!$C$53,1) | AP11: m³/day. Treatment plant capacity, or tanker frequency if there is no connection.
B12: Tanker movements if no foul connection | C12: =ROUNDUP(C11/30,0) | D12: =ROUNDUP(D11/30,0) | E12: =ROUNDUP(E11/30,0) | F12: =ROUNDUP(F11/30,0) | G12: =ROUNDUP(G11/30,0) | H12: =ROUNDUP(H11/30,0) | I12: =ROUNDUP(I11/30,0) | J12: =ROUNDUP(J11/30,0) | ... AN12: =ROUNDUP(AN11/30,0) | AP12: loads/day at 30 m³ a tanker. If this number is above one or two, a connection or a package plant stops being optional.
B14: Electrical connected load | C14: =ROUND(BedDemand!C10*Assumptions!$C$54+IF(BedDemand!C10>0,Assumptions!$C$56,0),0) | D14: =ROUND(BedDemand!D10*Assumptions!$C$54+IF(BedDemand!D10>0,Assumptions!$C$56,0),0) | E14: =ROUND(BedDemand!E10*Assumptions!$C$54+IF(BedDemand!E10>0,Assumptions!$C$56,0),0) | F14: =ROUND(BedDemand!F10*Assumptions!$C$54+IF(BedDemand!F10>0,Assumptions!$C$56,0),0) | G14: =ROUND(BedDemand!G10*Assumptions!$C$54+IF(BedDemand!G10>0,Assumptions!$C$56,0),0) | H14: =ROUND(BedDemand!H10*Assumptions!$C$54+IF(BedDemand!H10>0,Assumptions!$C$56,0),0) | I14: =ROUND(BedDemand!I10*Assumptions!$C$54+IF(BedDemand!I10>0,Assumptions!$C$56,0),0) | J14: =ROUND(BedDemand!J10*Assumptions!$C$54+IF(BedDemand!J10>0,Assumptions!$C$56,0),0) | ... AN14: =ROUND(BedDemand!AN10*Assumptions!$C$54+IF(BedDemand!AN10>0,Assumptions!$C$56,0),0) | AP14: kW. Accommodation plus catering. Excludes electric space heating, which is on the line below.
B15: Heating load | C15: =ROUND(BedDemand!C10*Assumptions!$C$57,0) | D15: =ROUND(BedDemand!D10*Assumptions!$C$57,0) | E15: =ROUND(BedDemand!E10*Assumptions!$C$57,0) | F15: =ROUND(BedDemand!F10*Assumptions!$C$57,0) | G15: =ROUND(BedDemand!G10*Assumptions!$C$57,0) | H15: =ROUND(BedDemand!H10*Assumptions!$C$57,0) | I15: =ROUND(BedDemand!I10*Assumptions!$C$57,0) | J15: =ROUND(BedDemand!J10*Assumptions!$C$57,0) | ... AN15: =ROUND(BedDemand!AN10*Assumptions!$C$57,0) | AP15: kW at design outside temperature. Verify against the module supplier's U-values and the fuel you actually use.
B16: Diversified demand | C16: =ROUND(C14*Assumptions!$C$55,0) | D16: =ROUND(D14*Assumptions!$C$55,0) | E16: =ROUND(E14*Assumptions!$C$55,0) | F16: =ROUND(F14*Assumptions!$C$55,0) | G16: =ROUND(G14*Assumptions!$C$55,0) | H16: =ROUND(H14*Assumptions!$C$55,0) | I16: =ROUND(I14*Assumptions!$C$55,0) | J16: =ROUND(J14*Assumptions!$C$55,0) | ... AN16: =ROUND(AN14*Assumptions!$C$55,0) | AP16: kW. Not every load runs at once. The diversity factor is on Assumptions and needs an engineer's eye.
B17: Diversified demand | C17: =ROUND(C16/Assumptions!$C$58,0) | D17: =ROUND(D16/Assumptions!$C$58,0) | E17: =ROUND(E16/Assumptions!$C$58,0) | F17: =ROUND(F16/Assumptions!$C$58,0) | G17: =ROUND(G16/Assumptions!$C$58,0) | H17: =ROUND(H16/Assumptions!$C$58,0) | I17: =ROUND(I16/Assumptions!$C$58,0) | J17: =ROUND(J16/Assumptions!$C$58,0) | ... AN17: =ROUND(AN16/Assumptions!$C$58,0) | AP17: kVA — the unit a DNO connection or a generator is actually sized in. Getting kW and kVA confused undersizes a village by a fifth.
B19: Waste arisings | C19: =ROUND(BedDemand!C10*Assumptions!$C$59/1000*30.4,1) | D19: =ROUND(BedDemand!D10*Assumptions!$C$59/1000*30.4,1) | E19: =ROUND(BedDemand!E10*Assumptions!$C$59/1000*30.4,1) | F19: =ROUND(BedDemand!F10*Assumptions!$C$59/1000*30.4,1) | G19: =ROUND(BedDemand!G10*Assumptions!$C$59/1000*30.4,1) | H19: =ROUND(BedDemand!H10*Assumptions!$C$59/1000*30.4,1) | I19: =ROUND(BedDemand!I10*Assumptions!$C$59/1000*30.4,1) | J19: =ROUND(BedDemand!J10*Assumptions!$C$59/1000*30.4,1) | ... AN19: =ROUND(BedDemand!AN10*Assumptions!$C$59/1000*30.4,1) | AP19: tonnes/month. Residential plus catering.
B20: recycled or diverted | C20: =ROUND(C19*Assumptions!$C$60,1) | D20: =ROUND(D19*Assumptions!$C$60,1) | E20: =ROUND(E19*Assumptions!$C$60,1) | F20: =ROUND(F19*Assumptions!$C$60,1) | G20: =ROUND(G19*Assumptions!$C$60,1) | H20: =ROUND(H19*Assumptions!$C$60,1) | I20: =ROUND(I19*Assumptions!$C$60,1) | J20: =ROUND(J19*Assumptions!$C$60,1) | ... AN20: =ROUND(AN19*Assumptions!$C$60,1) | AP20: tonnes/month against the target on Assumptions.
B21: General waste collections | C21: =ROUNDUP(C19*1000/1100/12,0) | D21: =ROUNDUP(D19*1000/1100/12,0) | E21: =ROUNDUP(E19*1000/1100/12,0) | F21: =ROUNDUP(F19*1000/1100/12,0) | G21: =ROUNDUP(G19*1000/1100/12,0) | H21: =ROUNDUP(H19*1000/1100/12,0) | I21: =ROUNDUP(I19*1000/1100/12,0) | J21: =ROUNDUP(J19*1000/1100/12,0) | ... AN21: =ROUNDUP(AN19*1000/1100/12,0) | AP21: collections/month at 1100 l bins, twelve per collection. Indicative — set against the contractor's actual round.
B23: PEAK — WHAT YOU DESIGN AND PROCURE AGAINST
B24: Peak water demand | C24: =MAX(C9:AN9) | E24: m³/day — the figure that goes on the water undertaker's enquiry.
B25: Peak foul return | C25: =MAX(C11:AN11) | E25: m³/day — treatment plant or tanker capacity.
B26: Peak connected load | C26: =MAX(C14:AN14) | E26: kW.
B27: Peak diversified demand | C27: =MAX(C17:AN17) | E27: kVA — the figure that goes on the DNO application or the generator enquiry.
B28: Peak waste arisings | C28: =MAX(C19:AN19) | E28: tonnes/month.
B30: Every figure on this sheet is a first-pass planning figure requiring validation by a competent person before it is procured against.

Sheet Transport
B2: TRANSPORT — MOVING THE VILLAGE TO SITE AND BACK
B3: A village that cannot get its people to the gate on time is an expensive dormitory.
B5: Month | C5: =Workforce!C5 | D5: =Workforce!D5 | E5: =Workforce!E5 | F5: =Workforce!F5 | G5: =Workforce!G5 | H5: =Workforce!H5 | I5: =Workforce!I5 | J5: =Workforce!J5 | ... AN5: =Workforce!AN5 | AP5: Basis, and what to verify
B6: Month number | C6: 1 | D6: 2 | E6: 3 | F6: 4 | G6: 5 | H6: 6 | I6: 7 | J6: 8 | K6: 9 | L6: 10 | M6: 11 | N6: 12 | O6: 13 | P6: 14 | Q6: 15 | R6: 16 | S6: 17 | T6: 18 | U6: 19 | V6: 20 | W6: 21 | X6: 22 | Y6: 23 | Z6: 24 | AA6: 25 | AB6: 26 | AC6: 27 | AD6: 28 | AE6: 29 | AF6: 30 | AG6: 31 | AH6: 32 | AI6: 33 | AJ6: 34 | AK6: 35 | AL6: 36 | AM6: 37 | AN6: 38
B7: Residents in village | C7: BedDemand!C10 | D7: BedDemand!D10 | E7: BedDemand!E10 | F7: BedDemand!F10 | G7: BedDemand!G10 | H7: BedDemand!H10 | I7: BedDemand!I10 | J7: BedDemand!J10 | K7: BedDemand!K10 | L7: BedDemand!L10 | M7: BedDemand!M10 | N7: BedDemand!N10 | O7: BedDemand!O10 | P7: BedDemand!P10 | Q7: BedDemand!Q10 | R7: BedDemand!R10 | S7: BedDemand!S10 | T7: BedDemand!T10 | U7: BedDemand!U10 | V7: BedDemand!V10 | W7: BedDemand!W10 | X7: BedDemand!X10 | Y7: BedDemand!Y10 | Z7: BedDemand!Z10 | AA7: BedDemand!AA10 | AB7: BedDemand!AB10 | AC7: BedDemand!AC10 | AD7: BedDemand!AD10 | AE7: BedDemand!AE10 | AF7: BedDemand!AF10 | AG7: BedDemand!AG10 | AH7: BedDemand!AH10 | AI7: BedDemand!AI10 | AJ7: BedDemand!AJ10 | AK7: BedDemand!AK10 | AL7: BedDemand!AL10 | AM7: BedDemand!AM10 | AN7: BedDemand!AN10
B8: Residents requiring transport | C8: =ROUND(BedDemand!C10*Assumptions!$C$63,0) | D8: =ROUND(BedDemand!D10*Assumptions!$C$63,0) | E8: =ROUND(BedDemand!E10*Assumptions!$C$63,0) | F8: =ROUND(BedDemand!F10*Assumptions!$C$63,0) | G8: =ROUND(BedDemand!G10*Assumptions!$C$63,0) | H8: =ROUND(BedDemand!H10*Assumptions!$C$63,0) | I8: =ROUND(BedDemand!I10*Assumptions!$C$63,0) | J8: =ROUND(BedDemand!J10*Assumptions!$C$63,0) | ... AN8: =ROUND(BedDemand!AN10*Assumptions!$C$63,0) | AP8: The rest drive or walk. If the village adjoins the site this whole sheet shrinks.
B10: Seats required per shift change | C10: =ROUNDUP(C8/Assumptions!$C$66,0) | D10: =ROUNDUP(D8/Assumptions!$C$66,0) | E10: =ROUNDUP(E8/Assumptions!$C$66,0) | F10: =ROUNDUP(F8/Assumptions!$C$66,0) | G10: =ROUNDUP(G8/Assumptions!$C$66,0) | H10: =ROUNDUP(H8/Assumptions!$C$66,0) | I10: =ROUNDUP(I8/Assumptions!$C$66,0) | J10: =ROUNDUP(J8/Assumptions!$C$66,0) | ... AN10: =ROUNDUP(AN8/Assumptions!$C$66,0) | AP10: Split across the runs on Assumptions. Two runs stagger the arrival peak at the gate — which is usually the real constraint, not the buses.
B11: Buses required | C11: =ROUNDUP(C10/(Assumptions!$C$64*Assumptions!$C$65),0) | D11: =ROUNDUP(D10/(Assumptions!$C$64*Assumptions!$C$65),0) | E11: =ROUNDUP(E10/(Assumptions!$C$64*Assumptions!$C$65),0) | F11: =ROUNDUP(F10/(Assumptions!$C$64*Assumptions!$C$65),0) | G11: =ROUNDUP(G10/(Assumptions!$C$64*Assumptions!$C$65),0) | H11: =ROUNDUP(H10/(Assumptions!$C$64*Assumptions!$C$65),0) | I11: =ROUNDUP(I10/(Assumptions!$C$64*Assumptions!$C$65),0) | J11: =ROUNDUP(J10/(Assumptions!$C$64*Assumptions!$C$65),0) | ... AN11: =ROUNDUP(AN10/(Assumptions!$C$64*Assumptions!$C$65),0) | AP11: At the seat count and load factor on Assumptions. Nobody fills every seat every run.
B12: Bus journeys per day | C12: =C11*Assumptions!$C$66*Assumptions!$C$67*2 | D12: =D11*Assumptions!$C$66*Assumptions!$C$67*2 | E12: =E11*Assumptions!$C$66*Assumptions!$C$67*2 | F12: =F11*Assumptions!$C$66*Assumptions!$C$67*2 | G12: =G11*Assumptions!$C$66*Assumptions!$C$67*2 | H12: =H11*Assumptions!$C$66*Assumptions!$C$67*2 | I12: =I11*Assumptions!$C$66*Assumptions!$C$67*2 | J12: =J11*Assumptions!$C$66*Assumptions!$C$67*2 | ... AN12: =AN11*Assumptions!$C$66*Assumptions!$C$67*2 | AP12: Out and back, every run, every shift change.
B13: Bus movements per day at the village gate | C13: =C12 | D13: =D12 | E13: =E12 | F13: =F12 | G13: =G12 | H13: =H12 | I13: =I12 | J13: =J12 | ... AN13: =AN12 | AP13: The village access has to take this, at 06:00, in the dark, in winter.
B15: Resident parking spaces | C15: =ROUNDUP(BedDemand!C10/10*Assumptions!$C$68,0) | D15: =ROUNDUP(BedDemand!D10/10*Assumptions!$C$68,0) | E15: =ROUNDUP(BedDemand!E10/10*Assumptions!$C$68,0) | F15: =ROUNDUP(BedDemand!F10/10*Assumptions!$C$68,0) | G15: =ROUNDUP(BedDemand!G10/10*Assumptions!$C$68,0) | H15: =ROUNDUP(BedDemand!H10/10*Assumptions!$C$68,0) | I15: =ROUNDUP(BedDemand!I10/10*Assumptions!$C$68,0) | J15: =ROUNDUP(BedDemand!J10/10*Assumptions!$C$68,0) | ... AN15: =ROUNDUP(BedDemand!AN10/10*Assumptions!$C$68,0) | AP15: Most residents are bussed; some keep a car for days off. Under-provide this and they park on the verge.
B16: Village staff and visitor parking | C16: =IF(BedDemand!C10>0,Assumptions!$C$69,0) | D16: =IF(BedDemand!D10>0,Assumptions!$C$69,0) | E16: =IF(BedDemand!E10>0,Assumptions!$C$69,0) | F16: =IF(BedDemand!F10>0,Assumptions!$C$69,0) | G16: =IF(BedDemand!G10>0,Assumptions!$C$69,0) | H16: =IF(BedDemand!H10>0,Assumptions!$C$69,0) | I16: =IF(BedDemand!I10>0,Assumptions!$C$69,0) | J16: =IF(BedDemand!J10>0,Assumptions!$C$69,0) | ... AN16: =IF(BedDemand!AN10>0,Assumptions!$C$69,0)
B17: TOTAL PARKING SPACES | C17: =C15+C16 | D17: =D15+D16 | E17: =E15+E16 | F17: =F15+F16 | G17: =G15+G16 | H17: =H15+H16 | I17: =I15+I16 | J17: =J15+J16 | ... AN17: =AN15+AN16
B18: Parking area | C18: =C17*25 | D18: =D17*25 | E18: =E17*25 | F18: =F17*25 | G18: =G17*25 | H18: =H17*25 | I18: =I17*25 | J18: =J17*25 | ... AN18: =AN17*25 | AP18: m² at 25 m² a space including circulation.
B20: PEAK — WHAT YOU DESIGN AND PROCURE AGAINST
B21: Peak buses required | C21: =MAX(C11:AN11) | E21: The fleet to contract. Consider one spare — a broken bus is 45 people late.
B22: Peak seats per shift change | C22: =MAX(C10:AN10)
B23: Peak parking spaces | C23: =MAX(C17:AN17)
B24: Peak bus journeys per day | C24: =MAX(C12:AN12)

Sheet VillageStaff
B2: RUNNING THE VILLAGE — WHO IT TAKES
B3: A village is a hotel that never closes. These are the people who run it, scaled to occupancy.
B5: Month | C5: =Workforce!C5 | D5: =Workforce!D5 | E5: =Workforce!E5 | F5: =Workforce!F5 | G5: =Workforce!G5 | H5: =Workforce!H5 | I5: =Workforce!I5 | J5: =Workforce!J5 | ... AN5: =Workforce!AN5 | AP5: Basis, and what to verify
B6: Month number | C6: 1 | D6: 2 | E6: 3 | F6: 4 | G6: 5 | H6: 6 | I6: 7 | J6: 8 | K6: 9 | L6: 10 | M6: 11 | N6: 12 | O6: 13 | P6: 14 | Q6: 15 | R6: 16 | S6: 17 | T6: 18 | U6: 19 | V6: 20 | W6: 21 | X6: 22 | Y6: 23 | Z6: 24 | AA6: 25 | AB6: 26 | AC6: 27 | AD6: 28 | AE6: 29 | AF6: 30 | AG6: 31 | AH6: 32 | AI6: 33 | AJ6: 34 | AK6: 35 | AL6: 36 | AM6: 37 | AN6: 38
B7: Residents in village | C7: BedDemand!C10 | D7: BedDemand!D10 | E7: BedDemand!E10 | F7: BedDemand!F10 | G7: BedDemand!G10 | H7: BedDemand!H10 | I7: BedDemand!I10 | J7: BedDemand!J10 | K7: BedDemand!K10 | L7: BedDemand!L10 | M7: BedDemand!M10 | N7: BedDemand!N10 | O7: BedDemand!O10 | P7: BedDemand!P10 | Q7: BedDemand!Q10 | R7: BedDemand!R10 | S7: BedDemand!S10 | T7: BedDemand!T10 | U7: BedDemand!U10 | V7: BedDemand!V10 | W7: BedDemand!W10 | X7: BedDemand!X10 | Y7: BedDemand!Y10 | Z7: BedDemand!Z10 | AA7: BedDemand!AA10 | AB7: BedDemand!AB10 | AC7: BedDemand!AC10 | AD7: BedDemand!AD10 | AE7: BedDemand!AE10 | AF7: BedDemand!AF10 | AG7: BedDemand!AG10 | AH7: BedDemand!AH10 | AI7: BedDemand!AI10 | AJ7: BedDemand!AJ10 | AK7: BedDemand!AK10 | AL7: BedDemand!AL10 | AM7: BedDemand!AM10 | AN7: BedDemand!AN10
B8: Rooms in service | C8: BedDemand!C14 | D8: BedDemand!D14 | E8: BedDemand!E14 | F8: BedDemand!F14 | G8: BedDemand!G14 | H8: BedDemand!H14 | I8: BedDemand!I14 | J8: BedDemand!J14 | K8: BedDemand!K14 | L8: BedDemand!L14 | M8: BedDemand!M14 | N8: BedDemand!N14 | O8: BedDemand!O14 | P8: BedDemand!P14 | Q8: BedDemand!Q14 | R8: BedDemand!R14 | S8: BedDemand!S14 | T8: BedDemand!T14 | U8: BedDemand!U14 | V8: BedDemand!V14 | W8: BedDemand!W14 | X8: BedDemand!X14 | Y8: BedDemand!Y14 | Z8: BedDemand!Z14 | AA8: BedDemand!AA14 | AB8: BedDemand!AB14 | AC8: BedDemand!AC14 | AD8: BedDemand!AD14 | AE8: BedDemand!AE14 | AF8: BedDemand!AF14 | AG8: BedDemand!AG14 | AH8: BedDemand!AH14 | AI8: BedDemand!AI14 | AJ8: BedDemand!AJ14 | AK8: BedDemand!AK14 | AL8: BedDemand!AL14 | AM8: BedDemand!AM14 | AN8: BedDemand!AN14 | AP8: Including void and visitor rooms — they still get cleaned.
B10: Village management | C10: =IF(BedDemand!C10>0,Assumptions!$C$79,0) | D10: =IF(BedDemand!D10>0,Assumptions!$C$79,0) | E10: =IF(BedDemand!E10>0,Assumptions!$C$79,0) | F10: =IF(BedDemand!F10>0,Assumptions!$C$79,0) | G10: =IF(BedDemand!G10>0,Assumptions!$C$79,0) | H10: =IF(BedDemand!H10>0,Assumptions!$C$79,0) | I10: =IF(BedDemand!I10>0,Assumptions!$C$79,0) | J10: =IF(BedDemand!J10>0,Assumptions!$C$79,0) | ... AN10: =IF(BedDemand!AN10>0,Assumptions!$C$79,0) | AP10: Village manager and deputy. Below about 150 beds, one.
B11: Reception (24/7) | C11: =IF(BedDemand!C10>0,Assumptions!$C$74*Assumptions!$C$73,0) | D11: =IF(BedDemand!D10>0,Assumptions!$C$74*Assumptions!$C$73,0) | E11: =IF(BedDemand!E10>0,Assumptions!$C$74*Assumptions!$C$73,0) | F11: =IF(BedDemand!F10>0,Assumptions!$C$74*Assumptions!$C$73,0) | G11: =IF(BedDemand!G10>0,Assumptions!$C$74*Assumptions!$C$73,0) | H11: =IF(BedDemand!H10>0,Assumptions!$C$74*Assumptions!$C$73,0) | I11: =IF(BedDemand!I10>0,Assumptions!$C$74*Assumptions!$C$73,0) | J11: =IF(BedDemand!J10>0,Assumptions!$C$74*Assumptions!$C$73,0) | ... AN11: =IF(BedDemand!AN10>0,Assumptions!$C$74*Assumptions!$C$73,0) | AP11: Posts × the 24/7 cover factor on Assumptions, which includes leave, sickness and training cover.
B12: Security (24/7) | C12: =IF(BedDemand!C10>0,Assumptions!$C$75*Assumptions!$C$73,0) | D12: =IF(BedDemand!D10>0,Assumptions!$C$75*Assumptions!$C$73,0) | E12: =IF(BedDemand!E10>0,Assumptions!$C$75*Assumptions!$C$73,0) | F12: =IF(BedDemand!F10>0,Assumptions!$C$75*Assumptions!$C$73,0) | G12: =IF(BedDemand!G10>0,Assumptions!$C$75*Assumptions!$C$73,0) | H12: =IF(BedDemand!H10>0,Assumptions!$C$75*Assumptions!$C$73,0) | I12: =IF(BedDemand!I10>0,Assumptions!$C$75*Assumptions!$C$73,0) | J12: =IF(BedDemand!J10>0,Assumptions!$C$75*Assumptions!$C$73,0) | ... AN12: =IF(BedDemand!AN10>0,Assumptions!$C$75*Assumptions!$C$73,0) | AP12: Gatehouse plus patrol. Confirm the posts against the security risk assessment, not against this workbook.
B13: Housekeeping | C13: =ROUNDUP(BedDemand!C14/Assumptions!$C$76,1) | D13: =ROUNDUP(BedDemand!D14/Assumptions!$C$76,1) | E13: =ROUNDUP(BedDemand!E14/Assumptions!$C$76,1) | F13: =ROUNDUP(BedDemand!F14/Assumptions!$C$76,1) | G13: =ROUNDUP(BedDemand!G14/Assumptions!$C$76,1) | H13: =ROUNDUP(BedDemand!H14/Assumptions!$C$76,1) | I13: =ROUNDUP(BedDemand!I14/Assumptions!$C$76,1) | J13: =ROUNDUP(BedDemand!J14/Assumptions!$C$76,1) | ... AN13: =ROUNDUP(BedDemand!AN14/Assumptions!$C$76,1) | AP13: From beds per housekeeping FTE. Cross-check against rooms cleaned per shift on Facilities.
B14: Catering | C14: =ROUNDUP(Facilities!$C$11/Assumptions!$C$77,1)*IF(BedDemand!C10>0,1,0) | D14: =ROUNDUP(Facilities!$C$11/Assumptions!$C$77,1)*IF(BedDemand!D10>0,1,0) | E14: =ROUNDUP(Facilities!$C$11/Assumptions!$C$77,1)*IF(BedDemand!E10>0,1,0) | F14: =ROUNDUP(Facilities!$C$11/Assumptions!$C$77,1)*IF(BedDemand!F10>0,1,0) | G14: =ROUNDUP(Facilities!$C$11/Assumptions!$C$77,1)*IF(BedDemand!G10>0,1,0) | H14: =ROUNDUP(Facilities!$C$11/Assumptions!$C$77,1)*IF(BedDemand!H10>0,1,0) | I14: =ROUNDUP(Facilities!$C$11/Assumptions!$C$77,1)*IF(BedDemand!I10>0,1,0) | J14: =ROUNDUP(Facilities!$C$11/Assumptions!$C$77,1)*IF(BedDemand!J10>0,1,0) | ... AN14: =ROUNDUP(Facilities!$C$11/Assumptions!$C$77,1)*IF(BedDemand!AN10>0,1,0) | AP14: Chefs, servery, wash-up and stores across the whole meal cycle, sized on the design covers.
B15: Maintenance, grounds and waste | C15: =ROUND(BedDemand!C10/100*Assumptions!$C$78,1) | D15: =ROUND(BedDemand!D10/100*Assumptions!$C$78,1) | E15: =ROUND(BedDemand!E10/100*Assumptions!$C$78,1) | F15: =ROUND(BedDemand!F10/100*Assumptions!$C$78,1) | G15: =ROUND(BedDemand!G10/100*Assumptions!$C$78,1) | H15: =ROUND(BedDemand!H10/100*Assumptions!$C$78,1) | I15: =ROUND(BedDemand!I10/100*Assumptions!$C$78,1) | J15: =ROUND(BedDemand!J10/100*Assumptions!$C$78,1) | ... AN15: =ROUND(BedDemand!AN10/100*Assumptions!$C$78,1) | AP15: Reactive and planned. A 38-month village wears out.
B16: Administration and welfare | C16: =IF(BedDemand!C10>0,Assumptions!$C$80,0) | D16: =IF(BedDemand!D10>0,Assumptions!$C$80,0) | E16: =IF(BedDemand!E10>0,Assumptions!$C$80,0) | F16: =IF(BedDemand!F10>0,Assumptions!$C$80,0) | G16: =IF(BedDemand!G10>0,Assumptions!$C$80,0) | H16: =IF(BedDemand!H10>0,Assumptions!$C$80,0) | I16: =IF(BedDemand!I10>0,Assumptions!$C$80,0) | J16: =IF(BedDemand!J10>0,Assumptions!$C$80,0) | ... AN16: =IF(BedDemand!AN10>0,Assumptions!$C$80,0) | AP16: Bookings, inductions, pastoral support and complaints. The last of those is why villages succeed or fail.
B17: Transport drivers | C17: =ROUNDUP(Transport!C11*2.2,1) | D17: =ROUNDUP(Transport!D11*2.2,1) | E17: =ROUNDUP(Transport!E11*2.2,1) | F17: =ROUNDUP(Transport!F11*2.2,1) | G17: =ROUNDUP(Transport!G11*2.2,1) | H17: =ROUNDUP(Transport!H11*2.2,1) | I17: =ROUNDUP(Transport!I11*2.2,1) | J17: =ROUNDUP(Transport!J11*2.2,1) | ... AN17: =ROUNDUP(Transport!AN11*2.2,1) | AP17: Drivers per bus across the shift pattern, including cover. To verify against drivers' hours rules.
B19: TOTAL VILLAGE FTE | C19: =SUM(C10:C17) | D19: =SUM(D10:D17) | E19: =SUM(E10:E17) | F19: =SUM(F10:F17) | G19: =SUM(G10:G17) | H19: =SUM(H10:H17) | I19: =SUM(I10:I17) | J19: =SUM(J10:J17) | ... AN19: =SUM(AN10:AN17)
B20: Residents per village FTE | C20: =IFERROR(C7/C19,0) | D20: =IFERROR(D7/D19,0) | E20: =IFERROR(E7/E19,0) | F20: =IFERROR(F7/F19,0) | G20: =IFERROR(G7/G19,0) | H20: =IFERROR(H7/H19,0) | I20: =IFERROR(I7/I19,0) | J20: =IFERROR(J7/J19,0) | ... AN20: =IFERROR(AN7/AN19,0) | AP20: A full-service village with 24/7 security and its own bus fleet runs richer than a hotel: expect 5–8 residents per FTE. Security (posts × 4.6) and drivers dominate, so if this number looks heavy, test those two inputs before anything else — one security post instead of two is 4.6 FTE.
B22: PEAK — WHAT YOU DESIGN AND PROCURE AGAINST
B23: Peak village FTE | C23: =MAX(C19:AN19) | E23: The team to recruit, induct and house — they need beds too, and they are in the Teams list.
B24: Peak housekeeping FTE | C24: =MAX(C13:AN13)
B25: Peak catering FTE | C25: =MAX(C14:AN14)

Sheet BuildProgramme
B2: CREATING THE VILLAGE — WORKED BACKWARDS FROM THE FIRST ARRIVAL
B3: The only date that matters is the month the first travelling worker arrives. Everything else is worked backwards from it. If the bar runs off the left of the chart, the village is already late.
B5: Stage | C5: Months | D5: Start | E5: Finish | F5: 1 | G5: 2 | H5: 3 | I5: 4 | J5: 5 | K5: 6 | L5: 7 | M5: 8 | N5: 9 | O5: 10 | P5: 11 | Q5: 12 | R5: 13 | S5: 14 | T5: 15 | U5: 16 | V5: 17 | W5: 18 | X5: 19 | Y5: 20 | Z5: 21 | AA5: 22 | AB5: 23 | AC5: 24 | AD5: 25 | AE5: 26 | AF5: 27 | AG5: 28 | AH5: 29 | AI5: 30 | AJ5: 31 | AK5: 32 | AL5: 33 | AM5: 34 | AN5: 35 | AO5: 36 | AP5: 37 | AQ5: 38
B6: Design, planning and consents | C6: =Assumptions!$C$100 | D6: =E6-C6+1 | E6: =Assumptions!$C$105-1 | F6: =IF(AND(6-5>=$D6,6-5<=$E6),"█","") | G6: =IF(AND(7-5>=$D6,7-5<=$E6),"█","") | H6: =IF(AND(8-5>=$D6,8-5<=$E6),"█","") | I6: =IF(AND(9-5>=$D6,9-5<=$E6),"█","") | J6: =IF(AND(10-5>=$D6,10-5<=$E6),"█","") | K6: =IF(AND(11-5>=$D6,11-5<=$E6),"█","") | L6: =IF(AND(12-5>=$D6,12-5<=$E6),"█","") | M6: =IF(AND(13-5>=$D6,13-5<=$E6),"█","") | N6: =IF(AND(14-5>=$D6,14-5<=$E6),"█","") | O6: =IF(AND(15-5>=$D6,15-5<=$E6),"█","") | P6: =IF(AND(16-5>=$D6,16-5<=$E6),"█","") | Q6: =IF(AND(17-5>=$D6,17-5<=$E6),"█","") | R6: =IF(AND(18-5>=$D6,18-5<=$E6),"█","") | S6: =IF(AND(19-5>=$D6,19-5<=$E6),"█","") | T6: =IF(AND(20-5>=$D6,20-5<=$E6),"█","") | U6: =IF(AND(21-5>=$D6,21-5<=$E6),"█","") | V6: =IF(AND(22-5>=$D6,22-5<=$E6),"█","") | W6: =IF(AND(23-5>=$D6,23-5<=$E6),"█","") | X6: =IF(AND(24-5>=$D6,24-5<=$E6),"█","") | Y6: =IF(AND(25-5>=$D6,25-5<=$E6),"█","") | Z6: =IF(AND(26-5>=$D6,26-5<=$E6),"█","") | AA6: =IF(AND(27-5>=$D6,27-5<=$E6),"█","") | AB6: =IF(AND(28-5>=$D6,28-5<=$E6),"█","") | AC6: =IF(AND(29-5>=$D6,29-5<=$E6),"█","") | AD6: =IF(AND(30-5>=$D6,30-5<=$E6),"█","") | AE6: =IF(AND(31-5>=$D6,31-5<=$E6),"█","") | AF6: =IF(AND(32-5>=$D6,32-5<=$E6),"█","") | AG6: =IF(AND(33-5>=$D6,33-5<=$E6),"█","") | AH6: =IF(AND(34-5>=$D6,34-5<=$E6),"█","") | AI6: =IF(AND(35-5>=$D6,35-5<=$E6),"█","") | AJ6: =IF(AND(36-5>=$D6,36-5<=$E6),"█","") | AK6: =IF(AND(37-5>=$D6,37-5<=$E6),"█","") | AL6: =IF(AND(38-5>=$D6,38-5<=$E6),"█","") | AM6: =IF(AND(39-5>=$D6,39-5<=$E6),"█","") | AN6: =IF(AND(40-5>=$D6,40-5<=$E6),"█","") | AO6: =IF(AND(41-5>=$D6,41-5<=$E6),"█","") | AP6: =IF(AND(42-5>=$D6,42-5<=$E6),"█","") | AQ6: =IF(AND(43-5>=$D6,43-5<=$E6),"█","")
B7: Procurement and module lead time | C7: =Assumptions!$C$101 | D7: =E7-C7+1 | E7: =D6-1 | F7: =IF(AND(6-5>=$D7,6-5<=$E7),"█","") | G7: =IF(AND(7-5>=$D7,7-5<=$E7),"█","") | H7: =IF(AND(8-5>=$D7,8-5<=$E7),"█","") | I7: =IF(AND(9-5>=$D7,9-5<=$E7),"█","") | J7: =IF(AND(10-5>=$D7,10-5<=$E7),"█","") | K7: =IF(AND(11-5>=$D7,11-5<=$E7),"█","") | L7: =IF(AND(12-5>=$D7,12-5<=$E7),"█","") | M7: =IF(AND(13-5>=$D7,13-5<=$E7),"█","") | N7: =IF(AND(14-5>=$D7,14-5<=$E7),"█","") | O7: =IF(AND(15-5>=$D7,15-5<=$E7),"█","") | P7: =IF(AND(16-5>=$D7,16-5<=$E7),"█","") | Q7: =IF(AND(17-5>=$D7,17-5<=$E7),"█","") | R7: =IF(AND(18-5>=$D7,18-5<=$E7),"█","") | S7: =IF(AND(19-5>=$D7,19-5<=$E7),"█","") | T7: =IF(AND(20-5>=$D7,20-5<=$E7),"█","") | U7: =IF(AND(21-5>=$D7,21-5<=$E7),"█","") | V7: =IF(AND(22-5>=$D7,22-5<=$E7),"█","") | W7: =IF(AND(23-5>=$D7,23-5<=$E7),"█","") | X7: =IF(AND(24-5>=$D7,24-5<=$E7),"█","") | Y7: =IF(AND(25-5>=$D7,25-5<=$E7),"█","") | Z7: =IF(AND(26-5>=$D7,26-5<=$E7),"█","") | AA7: =IF(AND(27-5>=$D7,27-5<=$E7),"█","") | AB7: =IF(AND(28-5>=$D7,28-5<=$E7),"█","") | AC7: =IF(AND(29-5>=$D7,29-5<=$E7),"█","") | AD7: =IF(AND(30-5>=$D7,30-5<=$E7),"█","") | AE7: =IF(AND(31-5>=$D7,31-5<=$E7),"█","") | AF7: =IF(AND(32-5>=$D7,32-5<=$E7),"█","") | AG7: =IF(AND(33-5>=$D7,33-5<=$E7),"█","") | AH7: =IF(AND(34-5>=$D7,34-5<=$E7),"█","") | AI7: =IF(AND(35-5>=$D7,35-5<=$E7),"█","") | AJ7: =IF(AND(36-5>=$D7,36-5<=$E7),"█","") | AK7: =IF(AND(37-5>=$D7,37-5<=$E7),"█","") | AL7: =IF(AND(38-5>=$D7,38-5<=$E7),"█","") | AM7: =IF(AND(39-5>=$D7,39-5<=$E7),"█","") | AN7: =IF(AND(40-5>=$D7,40-5<=$E7),"█","") | AO7: =IF(AND(41-5>=$D7,41-5<=$E7),"█","") | AP7: =IF(AND(42-5>=$D7,42-5<=$E7),"█","") | AQ7: =IF(AND(43-5>=$D7,43-5<=$E7),"█","")
B8: Groundworks and infrastructure | C8: =Assumptions!$C$102 | D8: =E8-C8+1 | E8: =D7-1 | F8: =IF(AND(6-5>=$D8,6-5<=$E8),"█","") | G8: =IF(AND(7-5>=$D8,7-5<=$E8),"█","") | H8: =IF(AND(8-5>=$D8,8-5<=$E8),"█","") | I8: =IF(AND(9-5>=$D8,9-5<=$E8),"█","") | J8: =IF(AND(10-5>=$D8,10-5<=$E8),"█","") | K8: =IF(AND(11-5>=$D8,11-5<=$E8),"█","") | L8: =IF(AND(12-5>=$D8,12-5<=$E8),"█","") | M8: =IF(AND(13-5>=$D8,13-5<=$E8),"█","") | N8: =IF(AND(14-5>=$D8,14-5<=$E8),"█","") | O8: =IF(AND(15-5>=$D8,15-5<=$E8),"█","") | P8: =IF(AND(16-5>=$D8,16-5<=$E8),"█","") | Q8: =IF(AND(17-5>=$D8,17-5<=$E8),"█","") | R8: =IF(AND(18-5>=$D8,18-5<=$E8),"█","") | S8: =IF(AND(19-5>=$D8,19-5<=$E8),"█","") | T8: =IF(AND(20-5>=$D8,20-5<=$E8),"█","") | U8: =IF(AND(21-5>=$D8,21-5<=$E8),"█","") | V8: =IF(AND(22-5>=$D8,22-5<=$E8),"█","") | W8: =IF(AND(23-5>=$D8,23-5<=$E8),"█","") | X8: =IF(AND(24-5>=$D8,24-5<=$E8),"█","") | Y8: =IF(AND(25-5>=$D8,25-5<=$E8),"█","") | Z8: =IF(AND(26-5>=$D8,26-5<=$E8),"█","") | AA8: =IF(AND(27-5>=$D8,27-5<=$E8),"█","") | AB8: =IF(AND(28-5>=$D8,28-5<=$E8),"█","") | AC8: =IF(AND(29-5>=$D8,29-5<=$E8),"█","") | AD8: =IF(AND(30-5>=$D8,30-5<=$E8),"█","") | AE8: =IF(AND(31-5>=$D8,31-5<=$E8),"█","") | AF8: =IF(AND(32-5>=$D8,32-5<=$E8),"█","") | AG8: =IF(AND(33-5>=$D8,33-5<=$E8),"█","") | AH8: =IF(AND(34-5>=$D8,34-5<=$E8),"█","") | AI8: =IF(AND(35-5>=$D8,35-5<=$E8),"█","") | AJ8: =IF(AND(36-5>=$D8,36-5<=$E8),"█","") | AK8: =IF(AND(37-5>=$D8,37-5<=$E8),"█","") | AL8: =IF(AND(38-5>=$D8,38-5<=$E8),"█","") | AM8: =IF(AND(39-5>=$D8,39-5<=$E8),"█","") | AN8: =IF(AND(40-5>=$D8,40-5<=$E8),"█","") | AO8: =IF(AND(41-5>=$D8,41-5<=$E8),"█","") | AP8: =IF(AND(42-5>=$D8,42-5<=$E8),"█","") | AQ8: =IF(AND(43-5>=$D8,43-5<=$E8),"█","")
B9: Module delivery and installation | C9: =Assumptions!$C$103 | D9: =E9-C9+1 | E9: =D8-1 | F9: =IF(AND(6-5>=$D9,6-5<=$E9),"█","") | G9: =IF(AND(7-5>=$D9,7-5<=$E9),"█","") | H9: =IF(AND(8-5>=$D9,8-5<=$E9),"█","") | I9: =IF(AND(9-5>=$D9,9-5<=$E9),"█","") | J9: =IF(AND(10-5>=$D9,10-5<=$E9),"█","") | K9: =IF(AND(11-5>=$D9,11-5<=$E9),"█","") | L9: =IF(AND(12-5>=$D9,12-5<=$E9),"█","") | M9: =IF(AND(13-5>=$D9,13-5<=$E9),"█","") | N9: =IF(AND(14-5>=$D9,14-5<=$E9),"█","") | O9: =IF(AND(15-5>=$D9,15-5<=$E9),"█","") | P9: =IF(AND(16-5>=$D9,16-5<=$E9),"█","") | Q9: =IF(AND(17-5>=$D9,17-5<=$E9),"█","") | R9: =IF(AND(18-5>=$D9,18-5<=$E9),"█","") | S9: =IF(AND(19-5>=$D9,19-5<=$E9),"█","") | T9: =IF(AND(20-5>=$D9,20-5<=$E9),"█","") | U9: =IF(AND(21-5>=$D9,21-5<=$E9),"█","") | V9: =IF(AND(22-5>=$D9,22-5<=$E9),"█","") | W9: =IF(AND(23-5>=$D9,23-5<=$E9),"█","") | X9: =IF(AND(24-5>=$D9,24-5<=$E9),"█","") | Y9: =IF(AND(25-5>=$D9,25-5<=$E9),"█","") | Z9: =IF(AND(26-5>=$D9,26-5<=$E9),"█","") | AA9: =IF(AND(27-5>=$D9,27-5<=$E9),"█","") | AB9: =IF(AND(28-5>=$D9,28-5<=$E9),"█","") | AC9: =IF(AND(29-5>=$D9,29-5<=$E9),"█","") | AD9: =IF(AND(30-5>=$D9,30-5<=$E9),"█","") | AE9: =IF(AND(31-5>=$D9,31-5<=$E9),"█","") | AF9: =IF(AND(32-5>=$D9,32-5<=$E9),"█","") | AG9: =IF(AND(33-5>=$D9,33-5<=$E9),"█","") | AH9: =IF(AND(34-5>=$D9,34-5<=$E9),"█","") | AI9: =IF(AND(35-5>=$D9,35-5<=$E9),"█","") | AJ9: =IF(AND(36-5>=$D9,36-5<=$E9),"█","") | AK9: =IF(AND(37-5>=$D9,37-5<=$E9),"█","") | AL9: =IF(AND(38-5>=$D9,38-5<=$E9),"█","") | AM9: =IF(AND(39-5>=$D9,39-5<=$E9),"█","") | AN9: =IF(AND(40-5>=$D9,40-5<=$E9),"█","") | AO9: =IF(AND(41-5>=$D9,41-5<=$E9),"█","") | AP9: =IF(AND(42-5>=$D9,42-5<=$E9),"█","") | AQ9: =IF(AND(43-5>=$D9,43-5<=$E9),"█","")
B10: Commissioning and handover | C10: =Assumptions!$C$104 | D10: =E10-C10+1 | E10: =D9-1 | F10: =IF(AND(6-5>=$D10,6-5<=$E10),"█","") | G10: =IF(AND(7-5>=$D10,7-5<=$E10),"█","") | H10: =IF(AND(8-5>=$D10,8-5<=$E10),"█","") | I10: =IF(AND(9-5>=$D10,9-5<=$E10),"█","") | J10: =IF(AND(10-5>=$D10,10-5<=$E10),"█","") | K10: =IF(AND(11-5>=$D10,11-5<=$E10),"█","") | L10: =IF(AND(12-5>=$D10,12-5<=$E10),"█","") | M10: =IF(AND(13-5>=$D10,13-5<=$E10),"█","") | N10: =IF(AND(14-5>=$D10,14-5<=$E10),"█","") | O10: =IF(AND(15-5>=$D10,15-5<=$E10),"█","") | P10: =IF(AND(16-5>=$D10,16-5<=$E10),"█","") | Q10: =IF(AND(17-5>=$D10,17-5<=$E10),"█","") | R10: =IF(AND(18-5>=$D10,18-5<=$E10),"█","") | S10: =IF(AND(19-5>=$D10,19-5<=$E10),"█","") | T10: =IF(AND(20-5>=$D10,20-5<=$E10),"█","") | U10: =IF(AND(21-5>=$D10,21-5<=$E10),"█","") | V10: =IF(AND(22-5>=$D10,22-5<=$E10),"█","") | W10: =IF(AND(23-5>=$D10,23-5<=$E10),"█","") | X10: =IF(AND(24-5>=$D10,24-5<=$E10),"█","") | Y10: =IF(AND(25-5>=$D10,25-5<=$E10),"█","") | Z10: =IF(AND(26-5>=$D10,26-5<=$E10),"█","") | AA10: =IF(AND(27-5>=$D10,27-5<=$E10),"█","") | AB10: =IF(AND(28-5>=$D10,28-5<=$E10),"█","") | AC10: =IF(AND(29-5>=$D10,29-5<=$E10),"█","") | AD10: =IF(AND(30-5>=$D10,30-5<=$E10),"█","") | AE10: =IF(AND(31-5>=$D10,31-5<=$E10),"█","") | AF10: =IF(AND(32-5>=$D10,32-5<=$E10),"█","") | AG10: =IF(AND(33-5>=$D10,33-5<=$E10),"█","") | AH10: =IF(AND(34-5>=$D10,34-5<=$E10),"█","") | AI10: =IF(AND(35-5>=$D10,35-5<=$E10),"█","") | AJ10: =IF(AND(36-5>=$D10,36-5<=$E10),"█","") | AK10: =IF(AND(37-5>=$D10,37-5<=$E10),"█","") | AL10: =IF(AND(38-5>=$D10,38-5<=$E10),"█","") | AM10: =IF(AND(39-5>=$D10,39-5<=$E10),"█","") | AN10: =IF(AND(40-5>=$D10,40-5<=$E10),"█","") | AO10: =IF(AND(41-5>=$D10,41-5<=$E10),"█","") | AP10: =IF(AND(42-5>=$D10,42-5<=$E10),"█","") | AQ10: =IF(AND(43-5>=$D10,43-5<=$E10),"█","")
B12: Village must be live by month | C12: =Assumptions!$C$105
B13: First month with bed demand | C13: =BedDemand!$C$23
B14: Earliest the village work must start | C14: =D10
B15: VERDICT | C15: =IF(C14<1,"ALREADY LATE by "&(1-C14)&" months",IF(C12<=C13,"Deliverable — "&(C14-1)&" months of slack before month 1","LATE — the village is live after the first arrival"))
B17: A negative start month is the finding, not a formatting problem. It means the consent and lead-time chain does not fit before the first worker arrives, and the choices are: start now, phase the village, or house the early trades commercially at a cost nobody has budgeted.

Sheet Capex
B2: CAPEX BY PACKAGE — WHAT IT COSTS TO CREATE THE VILLAGE
B3: Grouped as the five packages are bought. Every rate is INDICATIVE, sits in blue on Assumptions, and must be replaced with your own quotation before this number leaves the building.
B5: Pkg | C5: Item | D5: Quantity | E5: Unit | F5: Cost | G5: Basis
B6: P1 | C6: Site clearance, cut and fill, ground improvement | D6: =Accommodation!$C$23 | E6: m² | F6: =D6*(Assumptions!$C$84*0.45) | G6: Total site area. Ground conditions are unknown here and drive this line more than anything else.
B7: P1 | C7: Roads, hardstanding, footpaths and parking | D7: =Accommodation!$C$21 | E7: m² | F7: =D7*(Assumptions!$C$84*0.55) | G7: External works area from Accommodation.
B8: P1 | C8: Foundations and bases for modules | D8: =Accommodation!$C$20 | E8: m² | F8: =D8*(180) | G8: Module footprint. INDICATIVE £180/m² — depends entirely on the ground investigation nobody has done.
B9: P1 | C9: Drainage, surface and foul | D9: =Accommodation!$C$23 | E9: m² | F9: =D9*(38) | G9: INDICATIVE.
B10: P1 | C10: Incoming utility infrastructure to termination points | D10: 1 | E10: lump | F10: =D10*(Assumptions!$C$85) | G10: Water, foul, power and comms. Get this priced before the land is committed, not after.
B11: P2 | C11: Bedroom modules — supply, deliver, install | D11: =Accommodation!$C$12 | E11: rooms | F11: =D11*(Assumptions!$C$83) | G11: The largest single line and the most specification-sensitive.
B12: P2 | C12: Amenity buildings — gym, social, laundry, drying | D12: =Facilities!$C$24+Facilities!$C$25+Facilities!$C$20 | E12: m² | F12: =D12*(1450) | G12: INDICATIVE £1,450/m² for a modular amenity building.
B13: P2 | C13: Reception, office and stores | D13: =Facilities!$C$26+Facilities!$C$27 | E13: m² | F13: =D13*(1250) | G13: INDICATIVE.
B14: P2 | C14: Kitchen and dining building shell | D14: =Facilities!$C$11+Facilities!$C$12 | E14: m² | F14: =D14*(1600) | G14: INDICATIVE. Shell only — the fit-out is P3. If the kitchen is bought as a finished module instead, move this and the P3 line together.
B15: P3 | C15: Kitchen fit-out, servery, wash-up and cold stores | D15: =Facilities!$C$10 | E15: covers | F15: =D15*(Assumptions!$C$87) | G15: Design covers from Facilities.
B16: P3 | C16: Extraction, interlocks and gas safety | D16: 1 | E16: lump | F16: =D16*(145000) | G16: INDICATIVE.
B17: P4 | C17: Bedroom furniture and FF&E | D17: =Accommodation!$C$12 | E17: rooms | F17: =D17*(Assumptions!$C$86) | G17: Bed, mattress, wardrobe, desk, chair, storage, soft furnishings.
B18: P4 | C18: Dining furniture | D18: =Facilities!$C$10 | E18: covers | F18: =D18*(260) | G18: INDICATIVE. In P4, not P3 — see interface IF-04.
B19: P4 | C19: Social, gym and office furniture and equipment | D19: =Facilities!$C$24+Facilities!$C$25+Facilities!$C$26 | E19: m² | F19: =D19*(220) | G19: INDICATIVE.
B20: P4 | C20: Laundry white goods | D20: =Facilities!$C$17+Facilities!$C$18 | E20: no. | F20: =D20*(1400) | G20: INDICATIVE.
B21: P5 | C21: Mobilisation — recruit, induct, policies, systems | D21: 1 | E21: lump | F21: =D21*(165000) | G21: INDICATIVE. Operational readiness before the first resident, not after.
B22: -- | C22: Design, consents, surveys and fees | D22: 1 | E22: lump | F22: =D22*(Assumptions!$C$88) | G22: Planning, building control, fire engineering, ground investigation, ecology, transport assessment. Sits across all five packages and belongs to none.
A24: BY PACKAGE
B25: Pkg | C25: Package | D25: Capex | E25: Share
B26: P1 | C26: Civil works | D26: =SUMIF($B$6:$B$22,B26,$F$6:$F$22) | E26: =IFERROR(D26/$D$32,0)
B27: P2 | C27: Modular accommodation | D27: =SUMIF($B$6:$B$22,B27,$F$6:$F$22) | E27: =IFERROR(D27/$D$32,0)
B28: P3 | C28: Kitchen | D28: =SUMIF($B$6:$B$22,B28,$F$6:$F$22) | E28: =IFERROR(D28/$D$32,0)
B29: P4 | C29: Furniture | D29: =SUMIF($B$6:$B$22,B29,$F$6:$F$22) | E29: =IFERROR(D29/$D$32,0)
B30: P5 | C30: FM and operation | D30: =SUMIF($B$6:$B$22,B30,$F$6:$F$22) | E30: =IFERROR(D30/$D$32,0)
C31: Design, consents and fees (across all packages) | D31: =SUMIF($B$6:$B$22,"--",$F$6:$F$22)
C32: Demobilisation and reinstatement | D32: =SUM(D26:D29)*Assumptions!$C$89 | G32: Applied to the physical packages P1–P4 only. Design fees and operational mobilisation are not demobilised.
C33: TOTAL CAPEX | D33: =SUM(D26:D32)
C34: Capex per room | D34: =IFERROR(D33/Accommodation!$C$12,0)

Sheet Opex
B2: OPEX — WHAT IT COSTS TO RUN, MONTH BY MONTH
B3: Follows occupancy, so the empty months cost less than the full ones. Every rate is INDICATIVE and sits on Assumptions.
B5: Month | C5: =Workforce!C5 | D5: =Workforce!D5 | E5: =Workforce!E5 | F5: =Workforce!F5 | G5: =Workforce!G5 | H5: =Workforce!H5 | I5: =Workforce!I5 | J5: =Workforce!J5 | ... AN5: =Workforce!AN5 | AP5: TOTAL
B6: Room hire | C6: =BedDemand!C14*Assumptions!$C$90 | D6: =BedDemand!D14*Assumptions!$C$90 | E6: =BedDemand!E14*Assumptions!$C$90 | F6: =BedDemand!F14*Assumptions!$C$90 | G6: =BedDemand!G14*Assumptions!$C$90 | H6: =BedDemand!H14*Assumptions!$C$90 | I6: =BedDemand!I14*Assumptions!$C$90 | J6: =BedDemand!J14*Assumptions!$C$90 | ... AN6: =BedDemand!AN14*Assumptions!$C$90 | AP6: =SUM(C6:AN6)
B7: Utilities | C7: =BedDemand!C10*Assumptions!$C$91 | D7: =BedDemand!D10*Assumptions!$C$91 | E7: =BedDemand!E10*Assumptions!$C$91 | F7: =BedDemand!F10*Assumptions!$C$91 | G7: =BedDemand!G10*Assumptions!$C$91 | H7: =BedDemand!H10*Assumptions!$C$91 | I7: =BedDemand!I10*Assumptions!$C$91 | J7: =BedDemand!J10*Assumptions!$C$91 | ... AN7: =BedDemand!AN10*Assumptions!$C$91 | AP7: =SUM(C7:AN7)
B8: Catering | C8: =ROUND(BedDemand!C10*Assumptions!$C$92*30.4,0) | D8: =ROUND(BedDemand!D10*Assumptions!$C$92*30.4,0) | E8: =ROUND(BedDemand!E10*Assumptions!$C$92*30.4,0) | F8: =ROUND(BedDemand!F10*Assumptions!$C$92*30.4,0) | G8: =ROUND(BedDemand!G10*Assumptions!$C$92*30.4,0) | H8: =ROUND(BedDemand!H10*Assumptions!$C$92*30.4,0) | I8: =ROUND(BedDemand!I10*Assumptions!$C$92*30.4,0) | J8: =ROUND(BedDemand!J10*Assumptions!$C$92*30.4,0) | ... AN8: =ROUND(BedDemand!AN10*Assumptions!$C$92*30.4,0) | AP8: =SUM(C8:AN8)
B9: Housekeeping and laundry | C9: =BedDemand!C14*Assumptions!$C$93 | D9: =BedDemand!D14*Assumptions!$C$93 | E9: =BedDemand!E14*Assumptions!$C$93 | F9: =BedDemand!F14*Assumptions!$C$93 | G9: =BedDemand!G14*Assumptions!$C$93 | H9: =BedDemand!H14*Assumptions!$C$93 | I9: =BedDemand!I14*Assumptions!$C$93 | J9: =BedDemand!J14*Assumptions!$C$93 | ... AN9: =BedDemand!AN14*Assumptions!$C$93 | AP9: =SUM(C9:AN9)
B10: Village staff | C10: =ROUND(VillageStaff!C19*Assumptions!$C$95,0) | D10: =ROUND(VillageStaff!D19*Assumptions!$C$95,0) | E10: =ROUND(VillageStaff!E19*Assumptions!$C$95,0) | F10: =ROUND(VillageStaff!F19*Assumptions!$C$95,0) | G10: =ROUND(VillageStaff!G19*Assumptions!$C$95,0) | H10: =ROUND(VillageStaff!H19*Assumptions!$C$95,0) | I10: =ROUND(VillageStaff!I19*Assumptions!$C$95,0) | J10: =ROUND(VillageStaff!J19*Assumptions!$C$95,0) | ... AN10: =ROUND(VillageStaff!AN19*Assumptions!$C$95,0) | AP10: =SUM(C10:AN10)
B11: Transport | C11: =Transport!C11*Assumptions!$C$94 | D11: =Transport!D11*Assumptions!$C$94 | E11: =Transport!E11*Assumptions!$C$94 | F11: =Transport!F11*Assumptions!$C$94 | G11: =Transport!G11*Assumptions!$C$94 | H11: =Transport!H11*Assumptions!$C$94 | I11: =Transport!I11*Assumptions!$C$94 | J11: =Transport!J11*Assumptions!$C$94 | ... AN11: =Transport!AN11*Assumptions!$C$94 | AP11: =SUM(C11:AN11)
B12: Maintenance and consumables | C12: =BedDemand!C14*Assumptions!$C$97 | D12: =BedDemand!D14*Assumptions!$C$97 | E12: =BedDemand!E14*Assumptions!$C$97 | F12: =BedDemand!F14*Assumptions!$C$97 | G12: =BedDemand!G14*Assumptions!$C$97 | H12: =BedDemand!H14*Assumptions!$C$97 | I12: =BedDemand!I14*Assumptions!$C$97 | J12: =BedDemand!J14*Assumptions!$C$97 | ... AN12: =BedDemand!AN14*Assumptions!$C$97 | AP12: =SUM(C12:AN12)
B13: Insurance, licences and rates | C13: =IF(BedDemand!C10>0,Assumptions!$C$96,0) | D13: =IF(BedDemand!D10>0,Assumptions!$C$96,0) | E13: =IF(BedDemand!E10>0,Assumptions!$C$96,0) | F13: =IF(BedDemand!F10>0,Assumptions!$C$96,0) | G13: =IF(BedDemand!G10>0,Assumptions!$C$96,0) | H13: =IF(BedDemand!H10>0,Assumptions!$C$96,0) | I13: =IF(BedDemand!I10>0,Assumptions!$C$96,0) | J13: =IF(BedDemand!J10>0,Assumptions!$C$96,0) | ... AN13: =IF(BedDemand!AN10>0,Assumptions!$C$96,0) | AP13: =SUM(C13:AN13)
B14: TOTAL MONTHLY OPEX | C14: =SUM(C6:C13) | D14: =SUM(D6:D13) | E14: =SUM(E6:E13) | F14: =SUM(F6:F13) | G14: =SUM(G6:G13) | H14: =SUM(H6:H13) | I14: =SUM(I6:I13) | J14: =SUM(J6:J13) | ... AN14: =SUM(AN6:AN13) | AP14: =SUM(C14:AN14)
B15: Cost per occupied bed-night | C15: =IFERROR(C14/(BedDemand!C10*30.4),0) | D15: =IFERROR(D14/(BedDemand!D10*30.4),0) | E15: =IFERROR(E14/(BedDemand!E10*30.4),0) | F15: =IFERROR(F14/(BedDemand!F10*30.4),0) | G15: =IFERROR(G14/(BedDemand!G10*30.4),0) | H15: =IFERROR(H14/(BedDemand!H10*30.4),0) | I15: =IFERROR(I14/(BedDemand!I10*30.4),0) | J15: =IFERROR(J14/(BedDemand!J10*30.4),0) | ... AN15: =IFERROR(AN14/(BedDemand!AN10*30.4),0)

Sheet CostSummary
B2: WHOLE-LIFE COST AND WHO PAYS IT
B3: Indicative throughout. This sizes a decision — buy or hire, build or book hotels, phase or not. It is not a budget and not a price.
A5: THE WHOLE-LIFE NUMBER
B6: Capex — creating the village | C6: =Capex!$D$33 | E6: From Capex. Includes demobilisation and reinstatement.
B7: Opex — running it for the programme | C7: =Opex!$AP$14 | E7: From Opex, summed across every month.
B8: TOTAL WHOLE-LIFE COST | C8: =C6+C7 | E8: The number to compare against the alternatives below.
B10: Bed-nights delivered | C10: =BedDemand!$C$25 | E10: From BedDemand.
B11: Whole-life cost per bed-night | C11: =IFERROR(C8/C10,0) | E11: The single most useful number here. Compare it directly against a hotel room rate — including the travel time a hotel adds at both ends of every shift.
B12: Cost per person-month of site presence | C12: =IFERROR(C8/Workforce!$C$34,0) | E12: Whole-life cost against every person-month worked, travelling or local. What the village really costs the project.
A14: THE COMPARISON THAT DECIDES IT
B15: Commercial accommodation — nightly rate | C15: 125 | E15: INDICATIVE. Put your own market rate here — and remember a village of this size takes the local market with it, so the rate you are quoted today is not the rate you pay in month twenty.
B16: Commercial equivalent over the programme | C16: =C10*C15 | E16: Bed-nights × nightly rate. Excludes the extra travel time, the fatigue, and the loss of control over where your workforce sleeps.
B17: Difference | C17: =C16-C8 | E17: Positive means the village is cheaper on these assumptions. Test it by changing the nightly rate above — the point at which it flips is the answer worth knowing.
B18: Break-even nightly rate | C18: =IFERROR(C8/C10,0) | E18: Below this rate, book rooms. Above it, build the village — subject to whether the rooms exist at all, which on most of these projects they do not.
A20: RECHARGE BY COMPANY
B21: Company | C21: Bed-months | D21: Share | E21: Indicative opex recharge
B22: =BedDemand!B30 | C22: =BedDemand!D30 | D22: =BedDemand!E30 | E22: =D22*Opex!$AP$14
B23: =BedDemand!B31 | C23: =BedDemand!D31 | D23: =BedDemand!E31 | E23: =D23*Opex!$AP$14
B24: =BedDemand!B32 | C24: =BedDemand!D32 | D24: =BedDemand!E32 | E24: =D24*Opex!$AP$14
B25: =BedDemand!B33 | C25: =BedDemand!D33 | D25: =BedDemand!E33 | E25: =D25*Opex!$AP$14
B26: =BedDemand!B34 | C26: =BedDemand!D34 | D26: =BedDemand!E34 | E26: =D26*Opex!$AP$14
B27: =BedDemand!B35 | C27: =BedDemand!D35 | D27: =BedDemand!E35 | E27: =D27*Opex!$AP$14
B28: =BedDemand!B36 | C28: =BedDemand!D36 | D28: =BedDemand!E36 | E28: =D28*Opex!$AP$14
B29: =BedDemand!B37 | C29: =BedDemand!D37 | D29: =BedDemand!E37 | E29: =D29*Opex!$AP$14
B30: =BedDemand!B38 | C30: =BedDemand!D38 | D30: =BedDemand!E38 | E30: =D30*Opex!$AP$14
B31: =BedDemand!B39 | C31: =BedDemand!D39 | D31: =BedDemand!E39 | E31: =D31*Opex!$AP$14
B32: =BedDemand!B40 | C32: =BedDemand!D40 | D32: =BedDemand!E40 | E32: =D32*Opex!$AP$14
B33: =BedDemand!B41 | C33: =BedDemand!D41 | D33: =BedDemand!E41 | E33: =D33*Opex!$AP$14
... B35: =BedDemand!B43 | C35: =BedDemand!D43 | D35: =BedDemand!E43 | E35: =D35*Opex!$AP$14
B36: TOTAL | E36: =SUM(E22:E35)
B38: Recharge on share of bed-months is the defensible basis: a company that occupies a fifth of the village for a fifth of the time pays a fifth. Agree the basis in the subcontract before anyone occupies a room, or it becomes a dispute in month nine.
A40: WHOLE-LIFE COST BY PACKAGE
B41: Package | C41: Capex | D41: Opex | E41: Whole life
B42: Civil works | C42: =Capex!$D$26 | D42: 0 | E42: =C42+D42
B43: Modular accommodation | C43: =Capex!$D$27 | D43: =Opex!$AP$6 | E43: =C43+D43
B44: Kitchen | C44: =Capex!$D$28 | D44: =Opex!$AP$8 | E44: =C44+D44
B45: Furniture | C45: =Capex!$D$29 | D45: 0 | E45: =C45+D45
B46: FM and operation | C46: =Capex!$D$30 | D46: =Opex!$AP$7+Opex!$AP$9+Opex!$AP$10+Opex!$AP$11+Opex!$AP$12+Opex!$AP$13 | E46: =C46+D46
B47: TOTAL (excludes design, fees and demobilisation) | C47: =SUM(C42:C46) | D47: =SUM(D42:D46) | E47: =SUM(E42:E46)
B49: Civil works and Furniture carry no operating cost of their own — their consequences land in FM. That is the point of interfaces IF-06 and IF-07: replacing broken furniture and maintaining the roads are real annual costs that belong to nobody unless they are written into P5.

Sheet Compliance
B2: COMPLIANCE AND CONSENTS REGISTER
B3: A workers village is a residential development that happens to be temporary. It is consented, licensed and inspected as one. Confirm every line below with the relevant authority — none of it is settled by this workbook.
B5: Ref | C5: Requirement | D5: Who decides | E5: Why it bites | F5: Lead time | G5: Status
B6: C01 | C6: Planning permission — temporary workers accommodation | D6: Local planning authority | E6: A village is rarely permitted development. Expect a full application with transport, noise, ecology and landscape assessments, and a condition restricting the life of the consent. | F6: 6–12 months | G6: Not started
B7: C02 | C7: Building Regulations approval | D7: Building Control body | E7: Structure, fire, means of escape, ventilation, insulation, accessibility. Modular does not mean exempt. | F7: 2–4 months | G7: Not started
B8: C03 | C8: Fire strategy and fire risk assessment | D8: Fire engineer; Fire & Rescue Service consulted | E8: Sleeping accommodation is the highest-risk occupancy there is. Compartmentation, escape distances, detection, alarm, and a management plan that survives 300 shift workers. | F8: 3–6 months | G8: Not started
B9: C04 | C9: HMO or equivalent licensing | D9: Local authority housing team | E9: Whether a workers village needs an HMO licence depends on its form and the authority. Ask early and in writing — the answer changes the design. | F9: 2–6 months | G9: To confirm
B10: C05 | C10: Food business registration and hygiene rating | D10: Local authority environmental health | E10: At least 28 days before the kitchen opens. A poor rating on a village kitchen becomes a workforce relations problem within a week. | F10: 1–2 months | G10: Not started
B11: C06 | C11: Private water supply / potable certification | D11: Water undertaker; environmental health | E11: No supply is proven potable until it is tested. Residential occupancy is not site welfare. | F11: 2–4 months | G11: Not started
B12: C07 | C12: Foul discharge consent or package treatment permit | D12: Environment Agency / water undertaker | E12: Where there is no public sewer. Tanker frequency at village scale is not a plan, it is a cost. | F12: 4–9 months | G12: Not started
B13: C08 | C13: Legionella risk assessment and water safety plan | D13: Duty holder; competent person | E13: Showers, calorifiers, low occupancy in early months and long dead legs. ACOP L8 applies from the day water enters the system, not from first occupation. | F13: 1 month | G13: Not started
B14: C09 | C14: Electrical installation certification and periodic inspection | D14: Competent person, BS 7671 | E14: Plus a DNO connection agreement, or a generation strategy that survives 38 months. | F14: Ongoing | G14: Not started
B15: C10 | C15: Gas safety — installation and annual certification | D15: Gas Safe registered engineer | E15: If catering or heating is gas. Certificates per appliance, per year, without exception. | F15: Ongoing | G15: Not started
B16: C11 | C16: Waste carrier registration and duty of care | D16: Environment Agency; waste contractor | E16: Transfer notes for every movement. Village waste is commercial waste. | F16: 1 month | G16: Not started
... B21: C16 | C21: Data protection for resident records | D21: Employer / operator | E21: Occupancy, next of kin, health information and CCTV. A lawful basis and a retention period for each. | F21: 1 month | G21: Not started

Sheet Risks
B2: RISK REGISTER — VILLAGE DELIVERY AND OPERATION
B3: Scored probability × impact. Sixteen and above is immediate management attention. Every mitigation names an action and an owner; none of them says “monitor”.
B5: Ref | C5: Risk | D5: P | E5: I | F5: Score | G5: Mitigation — what is actually done | H5: Owner
B6: R01 | C6: Planning consent refused or heavily conditioned | D6: 3 | E6: 5 | F6: =D6*E6 | G6: Pre-application meeting before any design spend; transport, noise and landscape assessments commissioned early; a fallback of phased commercial accommodation priced before the application goes in. | H6: Development manager
B7: R02 | C7: Village not live before the first travelling worker arrives | D7: 4 | E7: 4 | F7: =D7*E7 | G7: Work the programme backwards from first arrival, not forwards from today. Commit long-lead modules before consent at a priced, accepted risk. Book bridging accommodation now for the first ninety days. | H7: Project director
B8: R03 | C8: Ground conditions worse than assumed | D8: 3 | E8: 4 | F8: =D8*E8 | G8: Ground investigation before the layout is fixed, not after. Hold a provisional sum against foundations until it reports. | H8: Engineering
B9: R04 | C9: Utility connection unavailable or capacity refused | D9: 3 | E9: 5 | F9: =D9*E9 | G9: Enquiries to water and DNO before land is committed. Generation and package treatment priced in parallel as the fallback, not as an afterthought. | H9: Engineering
B10: R05 | C10: Fire strategy forces a design change late | D10: 2 | E10: 5 | F10: =D10*E10 | G10: Fire engineer appointed at concept, not at Building Control. Compartmentation and escape agreed before modules are ordered. | H10: Fire engineer
B11: R06 | C11: Occupancy materially below plan — the village runs empty | D11: 3 | E11: 4 | F11: =D11*E11 | G11: Phase the blocks against the bed curve. Contract for hire with a break, or a sublet right, rather than buying the peak on day one. | H11: Commercial
B12: R07 | C12: Occupancy above plan — no room for a late package | D12: 3 | E12: 3 | F12: =D12*E12 | G12: Contingency rooms in the schedule and a pre-agreed call-off for additional modules with a stated lead time. | H12: Commercial
B13: R08 | C13: Legionella or water quality failure | D13: 2 | E13: 5 | F13: =D13*E13 | G13: Water safety plan from first fill, flushing regime through the low-occupancy months, competent person appointed, records kept. | H13: Village operator
B14: R09 | C14: Fire, flood or major incident in occupied accommodation | D14: 2 | E14: 5 | F14: =D14*E14 | G14: Detection and alarm to the fire strategy, drills from first occupation, 24/7 staffed reception, muster and roll-call procedure tested. | H14: Village manager
B15: R10 | C15: Anti-social behaviour, alcohol or violence | D15: 4 | E15: 3 | F15: =D15*E15 | G15: Written conduct policy accepted at induction, alcohol policy agreed with all employers, 24/7 security, a real complaints route and consequences that are applied. | H15: Village manager
B16: R11 | C16: Catering failure — hygiene, supply or quality | D16: 3 | E16: 4 | F16: =D16*E16 | G16: Registered caterer, hygiene rating monitored, contingency supplier identified, resident feedback acted on monthly. Bad food empties a village faster than bad beds. | H16: Village operator
B17: R12 | C17: Transport failure — workforce late to site | D17: 3 | E17: 4 | F17: =D17*E17 | G17: Spare bus in the contract, drivers' hours modelled, a walking or minibus fallback, and a gate arrival plan that does not depend on every bus being on time. | H17: Logistics
... B22: R17 | C22: Demobilisation and reinstatement not budgeted | D22: 4 | E22: 2 | F22: =D22*E22 | G22: Priced in Capex from day one and held in the cost plan, not left to the final account. | H22: Commercial

Sheet Mobilisation
B2: MOBILISATION CHECKLIST — THE ORDER THINGS HAVE TO HAPPEN IN
B3: Ordered by what blocks what. The first block is the one that is already late on most projects.
B5: Ref | C5: Action | D5: When | E5: Owner | F5: Blocks what, if it slips
B6: M01 | C6: Fix the first-arrival month from the bed curve | D6: Now | E6: Project director | F6: Everything. This is the only date the village programme is worked back from.
B7: M02 | C7: Pre-application meeting with the planning authority | D7: Now | E7: Development manager | F7: The consent, and therefore the whole programme.
B8: M03 | C8: Commission ground investigation on the village site | D8: Now | E8: Engineering | F8: Foundations, hardstanding, drainage and the capex number.
B9: M04 | C9: Water and DNO capacity enquiries | D9: Now | E9: Engineering | F9: Whether the village can be where you want it at all.
B10: M05 | C10: Appoint the fire engineer | D10: Now | E10: Project director | F10: Block layout, compartmentation, escape and module specification.
B11: M06 | C11: Agree the room specification with employers and unions | D11: Month 1 | E11: Project director | F11: Module order. A room nobody will accept is worse than no village.
B12: M07 | C12: Price bridging accommodation for the first ninety days | D12: Month 1 | E12: Commercial | F12: The gap between first arrival and village live, which almost always exists.
B13: M08 | C13: Market test modules and fix the lead time | D13: Month 1 | E13: Procurement | F13: The critical path from month two onwards.
B14: M09 | C14: Agree the recharge basis in every subcontract | D14: Month 2 | E14: Commercial | F14: A dispute in month nine that nobody can settle retrospectively.
B15: M10 | C15: Submit the planning application | D15: Month 2 | E15: Development manager | F15: Consent, and every date after it.
B16: M11 | C16: Appoint the village operator | D16: Month 3 | E16: Project director | F16: Staffing, mobilisation, policies and the operational readiness plan.
... B23: M18 | C23: Demobilisation plan and reinstatement scope agreed | D23: Month 6 | E23: Commercial | F23: The end of the job, priced while there is still time to price it.
